Workbook

Sheet 00_TONG_QUAN
A1: BẢNG TỔNG HỢP YÊU CẦU PWA SƠN CẢNG — V3
A2: 11/10/2026 | Đã nhập nguyên văn phản hồi V1 đúng; bổ sung đăng ký cắm điện trước khi cont vào và chỉnh số cont.
A4: TIẾN ĐỘ XÁC NHẬN
A5: TỔNG CÂU HỎI | C5: ĐÃ CÓ LỰA CHỌN | E5: CẦN LÀM RÕ | G5: P0 CẦN XỬ LÝ | I5: ĐỦ RÕ ĐẶC TẢ
A6: =COUNTA('01_CAU_HOI'!$A$5:$A$250) | C6: =COUNTIF('01_CAU_HOI'!$F$5:$F$250,"<>") | E6: =COUNTIF('01_CAU_HOI'!$N$5:$N$250,"Cần làm rõ") | G6: =COUNTIFS('01_CAU_HOI'!$C$5:$C$250,"P0",'01_CAU_HOI'!$N$5:$N$250,"Cần làm rõ")+COUNTIFS('01_CAU_HOI'!$C$5:$C$250,"P0",'01_CAU_HOI'!$N$5:$N$250,"Chưa trả lời") | I6: =IFERROR(COUNTIF('01_CAU_HOI'!$N$5:$N$250,"Đủ rõ để đặc tả")/A6,0)
A8: CÁCH ĐIỀN FILE
A9: 1. Mở 01_CAU_HOI: F/G/H giữ NGUYÊN phản hồi V1 của bạn; không cần nhập lại.
A10: 2. Lọc N = Cần làm rõ/Chưa trả lời; hoặc vào 11_RA_SOAT_V1 để bổ sung quyết định và giải thích.
A11: 3. Những câu PR/SC liên quan container dự kiến, sai số cont đã được đưa từ V2 sang và vẫn giữ trạng thái đúng.
A12: 4. 02_DA_CHOT tổng hợp các nguyên tắc được xác nhận; 12_TRA_LOI_V1_GOC lưu nguyên các câu trả lời V1 để đối chiếu.
A13: 5. Tiếp tục rà soát giá/thu tiền/ngoại lệ cho ra; KHÔNG xem mọi ô H=Đã chốt là đặc tả đã đủ rõ.
A14: 6. Dùng 04_PHAN_QUYEN để gán quyền, 05_KICH_BAN để kiểm thử, 09_TINH_DIEN để thử tiền điện 15 phút.
A15: 7. Sử dụng các tab tham chiếu: giá, tài khoản, mapping, đối soát và quy trình dự kiến/sửa số cont.
A18: TỔNG HỢP THEO NHÓM
A19: Nhóm nghiệp vụ | D19: Tổng | F19: Đủ rõ | H19: Cần xử lý
A20: 01. Vé xe / cổng | D20: =COUNTIF('01_CAU_HOI'!$B$5:$B$250,A20) | F20: =COUNTIFS('01_CAU_HOI'!$B$5:$B$250,A20,'01_CAU_HOI'!$N$5:$N$250,"Đủ rõ để đặc tả") | H20: =COUNTIFS('01_CAU_HOI'!$B$5:$B$250,A20,'01_CAU_HOI'!$N$5:$N$250,"Cần làm rõ")+COUNTIFS('01_CAU_HOI'!$B$5:$B$250,A20,'01_CAU_HOI'!$N$5:$N$250,"Chưa trả lời")
A21: 02. Lưu container | D21: =COUNTIF('01_CAU_HOI'!$B$5:$B$250,A21) | F21: =COUNTIFS('01_CAU_HOI'!$B$5:$B$250,A21,'01_CAU_HOI'!$N$5:$N$250,"Đủ rõ để đặc tả") | H21: =COUNTIFS('01_CAU_HOI'!$B$5:$B$250,A21,'01_CAU_HOI'!$N$5:$N$250,"Cần làm rõ")+COUNTIFS('01_CAU_HOI'!$B$5:$B$250,A21,'01_CAU_HOI'!$N$5:$N$250,"Chưa trả lời")
A22: 03. Cắm/rút điện | D22: =COUNTIF('01_CAU_HOI'!$B$5:$B$250,A22) | F22: =COUNTIFS('01_CAU_HOI'!$B$5:$B$250,A22,'01_CAU_HOI'!$N$5:$N$250,"Đủ rõ để đặc tả") | H22: =COUNTIFS('01_CAU_HOI'!$B$5:$B$250,A22,'01_CAU_HOI'!$N$5:$N$250,"Cần làm rõ")+COUNTIFS('01_CAU_HOI'!$B$5:$B$250,A22,'01_CAU_HOI'!$N$5:$N$250,"Chưa trả lời")
A23: 04. Thanh toán | D23: =COUNTIF('01_CAU_HOI'!$B$5:$B$250,A23) | F23: =COUNTIFS('01_CAU_HOI'!$B$5:$B$250,A23,'01_CAU_HOI'!$N$5:$N$250,"Đủ rõ để đặc tả") | H23: =COUNTIFS('01_CAU_HOI'!$B$5:$B$250,A23,'01_CAU_HOI'!$N$5:$N$250,"Cần làm rõ")+COUNTIFS('01_CAU_HOI'!$B$5:$B$250,A23,'01_CAU_HOI'!$N$5:$N$250,"Chưa trả lời")
A24: 05. Phân quyền | D24: =COUNTIF('01_CAU_HOI'!$B$5:$B$250,A24) | F24: =COUNTIFS('01_CAU_HOI'!$B$5:$B$250,A24,'01_CAU_HOI'!$N$5:$N$250,"Đủ rõ để đặc tả") | H24: =COUNTIFS('01_CAU_HOI'!$B$5:$B$250,A24,'01_CAU_HOI'!$N$5:$N$250,"Cần làm rõ")+COUNTIFS('01_CAU_HOI'!$B$5:$B$250,A24,'01_CAU_HOI'!$N$5:$N$250,"Chưa trả lời")
A25: 06. Điều phối / container | D25: =COUNTIF('01_CAU_HOI'!$B$5:$B$250,A25) | F25: =COUNTIFS('01_CAU_HOI'!$B$5:$B$250,A25,'01_CAU_HOI'!$N$5:$N$250,"Đủ rõ để đặc tả") | H25: =COUNTIFS('01_CAU_HOI'!$B$5:$B$250,A25,'01_CAU_HOI'!$N$5:$N$250,"Cần làm rõ")+COUNTIFS('01_CAU_HOI'!$B$5:$B$250,A25,'01_CAU_HOI'!$N$5:$N$250,"Chưa trả lời")
A26: 07. Báo cáo / đối soát | D26: =COUNTIF('01_CAU_HOI'!$B$5:$B$250,A26) | F26: =COUNTIFS('01_CAU_HOI'!$B$5:$B$250,A26,'01_CAU_HOI'!$N$5:$N$250,"Đủ rõ để đặc tả") | H26: =COUNTIFS('01_CAU_HOI'!$B$5:$B$250,A26,'01_CAU_HOI'!$N$5:$N$250,"Cần làm rõ")+COUNTIFS('01_CAU_HOI'!$B$5:$B$250,A26,'01_CAU_HOI'!$N$5:$N$250,"Chưa trả lời")
A27: 08. Kỹ thuật / bảo mật | D27: =COUNTIF('01_CAU_HOI'!$B$5:$B$250,A27) | F27: =COUNTIFS('01_CAU_HOI'!$B$5:$B$250,A27,'01_CAU_HOI'!$N$5:$N$250,"Đủ rõ để đặc tả") | H27: =COUNTIFS('01_CAU_HOI'!$B$5:$B$250,A27,'01_CAU_HOI'!$N$5:$N$250,"Cần làm rõ")+COUNTIFS('01_CAU_HOI'!$B$5:$B$250,A27,'01_CAU_HOI'!$N$5:$N$250,"Chưa trả lời")
A28: 09. Chuyển dữ liệu | D28: =COUNTIF('01_CAU_HOI'!$B$5:$B$250,A28) | F28: =COUNTIFS('01_CAU_HOI'!$B$5:$B$250,A28,'01_CAU_HOI'!$N$5:$N$250,"Đủ rõ để đặc tả") | H28: =COUNTIFS('01_CAU_HOI'!$B$5:$B$250,A28,'01_CAU_HOI'!$N$5:$N$250,"Cần làm rõ")+COUNTIFS('01_CAU_HOI'!$B$5:$B$250,A28,'01_CAU_HOI'!$N$5:$N$250,"Chưa trả lời")
A29: 10. Nghiệm thu / triển khai | D29: =COUNTIF('01_CAU_HOI'!$B$5:$B$250,A29) | F29: =COUNTIFS('01_CAU_HOI'!$B$5:$B$250,A29,'01_CAU_HOI'!$N$5:$N$250,"Đủ rõ để đặc tả") | H29: =COUNTIFS('01_CAU_HOI'!$B$5:$B$250,A29,'01_CAU_HOI'!$N$5:$N$250,"Cần làm rõ")+COUNTIFS('01_CAU_HOI'!$B$5:$B$250,A29,'01_CAU_HOI'!$N$5:$N$250,"Chưa trả lời")
A32: LƯU Ý: 98 dòng V1 được giữ nguyên trạng thái người dùng tự đánh dấu; cột RÀ SOÁT mới là thước đo độ đủ rõ để lập trình.
A34: DỮ LIỆU GỐC: PRICE_LIST và USERS do Sơn Cảng cung cấp; VEHICLE 315 bản ghi, CONTAINER 259 bản ghi (tính từ các tệp đính kèm).
A35: BẢN V1 TRẢ LỜI ĐÚNG ĐÃ NHẬP: Untitled spreadsheet (1).xlsx | Không tự sửa dữ liệu gốc; mọi điểm xung đột được đánh dấu.
A36: Đi tới bảng CÂU HỎI | D36: Đi tới các quyết định ĐÃ CHỐT | G36: Đi tới MA TRẬN PHÂN QUYỀN
A38: Đi tới BẢNG GIÁ | D38: Đi tới TÌNH HUỐNG UAT | G38: Đi tới MÔ PHỎNG TIỀN ĐIỆN

Sheet 01_CAU_HOI
A1: BẢNG CÂU HỎI PWA SƠN CẢNG — ĐÃ HỢP NHẤT TRẢ LỜI V1
A2: Cột F/G/H: dữ liệu trả lời nguyên văn từ V1; cột N/O: kết quả rà soát của trợ lý. Cần làm rõ KHÔNG đồng nghĩa bác bỏ câu trả lời.
A4: Mã | B4: Nhóm nghiệp vụ | C4: Ưu tiên | D4: Câu hỏi cần chốt | E4: Phương án gợi ý / cách điền | F4: Lựa chọn (điền) | G4: Quyết định/Thông số cụ thể (điền) | H4: Trạng thái (điền) | I4: Đơn vị xác nhận đề xuất | J4: Người xác nhận (điền) | K4: Ngày chốt (điền) | L4: Ghi chú bổ sung (điền) | M4: Căn cứ / nguồn | N4: ĐÁNH GIÁ RÀ SOÁT | O4: LƯU Ý / CẦN XÁC NHẬN
A5: V01 | B5: 01. Vé xe / cổng | C5: P0 | D5: Đầu kéo vào KHÔNG có container (vé vào 0đ), sau đó kéo container ra: có thu thêm 250.000đ ở lượt ra không? | E5: A. Không, giữ giá tại cổng vào; B. Có, bổ sung phí khi ra có kéo cont; C. Chính sách khác. | F5: A | H5: Đã chốt | I5: Ban quản lý Sơn Cảng | M5: PRICE_LIST + luồng xe nhận container | N5: Đủ rõ để đặc tả | O5: Có lựa chọn được người dùng đánh dấu đã chốt; giữ nguyên câu trả lời và ghi chú.
A6: V02 | B6: 01. Vé xe / cổng | C6: P0 | D6: Vé vào có bắt buộc thu ngay trước khi cho xe qua cổng vào, hay được phép ghi Chưa thu để bổ sung sau? | E6: A. Bắt buộc thu đủ; B. Cho ghi Chưa thu có điều kiện; C. Chỉ ngoại lệ cần phê duyệt. | F6: A | G6: Nhưng cũng có trường họp thu sau(ít) | H6: Đã chốt | I6: Trưởng BP An ninh + CCKB | M6: Trao đổi nghiệp vụ Sơn Cảng, 10-11/10/2026 | N6: Cần làm rõ | O6: Thu vé ngay là mặc định, nhưng ghi chú cho phép thu sau (ít). Cần xác định ai cho phép và cách báo Chưa thu.
A7: V03 | B7: 01. Vé xe / cổng | C7: P0 | D7: Xe container KHÔNG lạnh/container khô hiện có được tiếp nhận không? Nếu có mã xe và đơn giá vé nào? | E7: A. Dùng CONT_LANH nếu chung 250.000đ; B. Tạo mã giá xe container khác; C. Không sử dụng loại này. | F7: Khác | G7: Chỉ có xe cont(250K) và xe đầu kéo k còn(0Đ) | H7: Đã chốt | I7: Trưởng BP An ninh | M7: Trao đổi nghiệp vụ Sơn Cảng, 10-11/10/2026 | N7: Cần làm rõ | O7: Người dùng dùng tên “xe cont” chung; PRICE_LIST hiện ghi CONT_LANH. Cần rà nhãn hiển thị, không đổi mã giá đã chốt.
A8: V04 | B8: 01. Vé xe / cổng | C8: P1 | D8: Xe bo ba bánh không có biển số được phân biệt lượt bằng mã vé; có cần thêm tên lái xe/đặc điểm xe/ảnh xe không? | E8: A. Chỉ mã vé tự sinh; B. Thêm thông tin nhận diện; C. Có thể nhập biển số khi có. | F8: A | G8: chỉ sinh cũng được nhưng đến lúc ra cũng chịu à, hoặc có thể sinh mã r điền vào vé thôi | H8: Đã chốt | I8: Trưởng BP An ninh | M8: Trao đổi nghiệp vụ Sơn Cảng, 10-11/10/2026 | N8: Cần làm rõ | O8: Không có biển số; người dùng lo không biết đối chiếu khi ra. Cần quy trình mã vé/tìm lượt.
A9: V05 | B9: 01. Vé xe / cổng | C9: P0 | D9: Vé giấy 2 liên có cần nhập/kiểm soát SỐ VÉ GIẤY bắt buộc khi ghi nhận xe vào không? | E9: A. Bắt buộc; B. Khuyến khích, không bắt buộc; C. Chuyển sang in/QR từ PWA. | F9: B | G9: sau này sẽ in | H9: Đã chốt | I9: Trưởng BP An ninh | M9: Trao đổi nghiệp vụ Sơn Cảng, 10-11/10/2026 | N9: Cần làm rõ | O9: Số vé giấy hiện không bắt buộc; người dùng nói “sau này sẽ in”. Cần xác định thuộc giai đoạn nào.
A10: V06 | B10: 01. Vé xe / cổng | C10: P0 | D10: Mất liên 02, phạt 250.000đ: bộ phận nào xác nhận, thu tiền và đánh dấu đã xử lý? | E10: A. An ninh nhận phạt; B. CCKB thu; C. An ninh xác nhận mất, CCKB thu; ghi rõ ngoại lệ. | F10: A | H10: Đã chốt | I10: Trưởng BP An ninh + CCKB | M10: Thông báo vé giấy Sơn Cảng | N10: Đủ rõ để đặc tả | O10: Có lựa chọn được người dùng đánh dấu đã chốt; giữ nguyên câu trả lời và ghi chú.
A11: V07 | B11: 01. Vé xe / cổng | C11: P1 | D11: Trường hợp khách có vé nhưng số vé/biển số không khớp: cho sửa vé tại cổng hay báo Trưởng BP xử lý? | E11: A. Chặn và yêu cầu phê duyệt; B. Cho xác minh bằng chứng từ; C. Quy trình khác. | F11: A | H11: Đã chốt | I11: Trưởng BP An ninh | M11: Trao đổi nghiệp vụ Sơn Cảng, 10-11/10/2026 | N11: Đủ rõ để đặc tả | O11: Có lựa chọn được người dùng đánh dấu đã chốt; giữ nguyên câu trả lời và ghi chú.
A12: V08 | B12: 01. Vé xe / cổng | C12: P1 | D12: Xe sang tải (tạp), đầu kéo 0đ có cần ghi nhận phiếu/vé giấy và xác nhận trạng thái Miễn phí hay không? | E12: A. Có kiểm soát đủ; B. Chỉ ghi lượt; C. Trường hợp khác. | F12: A | H12: Đã chốt | I12: Trưởng BP An ninh | M12: Trao đổi nghiệp vụ Sơn Cảng, 10-11/10/2026 | N12: Đủ rõ để đặc tả | O12: Có lựa chọn được người dùng đánh dấu đã chốt; giữ nguyên câu trả lời và ghi chú.
A13: V09 | B13: 01. Vé xe / cổng | C13: P1 | D13: Khi xe vào có kéo container, được phép nhập số container tạm/chưa rõ chính xác hay luôn bắt buộc số hợp lệ? | E13: A. Bắt buộc mã chính xác; B. Cho tạo tạm có phê duyệt; C. Được sửa trong thời hạn. | F13: A | H13: Đã chốt | I13: Trưởng BP An ninh + Điều phối | M13: Trao đổi nghiệp vụ Sơn Cảng, 10-11/10/2026 | N13: Cần làm rõ | O13: Chọn số container chính xác khi vào, nhưng nghiệp vụ thực tế thường nhập nhầm; cần cơ chế sửa có lịch sử và đối chiếu.
A14: V10 | B14: 01. Vé xe / cổng | C14: P0 | D14: Một lượt xe có thể chở trên 01 container cùng lúc không, đặc biệt với xe nhỏ hoặc phương tiện đặc biệt? | E14: A. Chỉ 01; B. Cho nhiều container; C. Tùy loại xe. | F14: A | H14: Đã chốt | I14: Trưởng BP An ninh + Điều phối | M14: Trao đổi nghiệp vụ Sơn Cảng, 10-11/10/2026 | N14: Đủ rõ để đặc tả | O14: Có lựa chọn được người dùng đánh dấu đã chốt; giữ nguyên câu trả lời và ghi chú.
A15: V11 | B15: 01. Vé xe / cổng | C15: P1 | D15: Khi xe ra không kéo container (đã hạ), có yêu cầu xác nhận riêng tại cổng hay chỉ chọn phương án ra không cont? | E15: A. Bắt buộc xác nhận; B. Theo trạng thái cont thực tế; C. Quy trình khác. | F15: A | H15: Đã chốt | I15: Trưởng BP An ninh | M15: Trao đổi nghiệp vụ Sơn Cảng, 10-11/10/2026 | N15: Đủ rõ để đặc tả | O15: Có lựa chọn được người dùng đánh dấu đã chốt; giữ nguyên câu trả lời và ghi chú.
A16: V12 | B16: 01. Vé xe / cổng | C16: P1 | D16: Sửa GIO_VAO/GIO_RA, biển số hoặc loại xe: ai được sửa, giới hạn thời gian và cần bằng chứng gì? | E16: A. Nhân viên sửa trước ra; B. TBP duyệt khi đã ra; C. Mọi sửa phải TBP duyệt. | F16: C | G16: cho phép sửa linh hoạt nhưng có log | H16: Đã chốt | I16: Trưởng BP An ninh | M16: Trao đổi nghiệp vụ Sơn Cảng, 10-11/10/2026 | N16: Cần làm rõ | O16: F=C (mọi sửa qua TBP) nhưng G=cho sửa linh hoạt, có log; cần chốt quyền riêng trước và sau khi xe đã ra.
A17: L01 | B17: 02. Lưu container | C17: P0 | D17: Nếu container vào trước 22:00 và ra đúng 22:00, có ghi nhận 1 đêm hay chưa? | E17: A. Tính 1 đêm (>=22:00); B. Chưa tính nếu ra đúng 22:00; C. Theo công thức AppSheet V1 đã nghiệm thu. | F17: A | H17: Đã chốt | I17: Trưởng BP CCKB | M17: Thông báo 22:00–06:00 | N17: Đủ rõ để đặc tả | O17: Có lựa chọn được người dùng đánh dấu đã chốt; giữ nguyên câu trả lời và ghi chú.
A18: L02 | B18: 02. Lưu container | C18: P0 | D18: Nếu container vào đúng 06:00 hoặc ra đúng 06:00, quy tắc gán cho kỳ đêm nào? | E18: A. Kỳ đêm kết thúc tại 06:00, ra 06:00 có tính; B. Kết thúc trước 06:00 mới tính; C. Theo V1. | F18: A | H18: Đã chốt | I18: Trưởng BP CCKB | M18: Trao đổi nghiệp vụ Sơn Cảng, 10-11/10/2026 | N18: Đủ rõ để đặc tả | O18: Có lựa chọn được người dùng đánh dấu đã chốt; giữ nguyên câu trả lời và ghi chú.
A19: L03 | B19: 02. Lưu container | C19: P0 | D19: Xe vào sau 22:00 (ví dụ 23:30) và ra trước 06:00 (02:00), đêm đó vẫn là 1 đêm miễn phí đúng không? | E19: A. Đúng; B. Chỉ khi qua mốc 06:00; C. Khác. | F19: A | H19: Đã chốt | I19: Trưởng BP CCKB | M19: Trao đổi nghiệp vụ Sơn Cảng, 10-11/10/2026 | N19: Đủ rõ để đặc tả | O19: Có lựa chọn được người dùng đánh dấu đã chốt; giữ nguyên câu trả lời và ghi chú.
A20: L04 | B20: 02. Lưu container | C20: P0 | D20: CCKB đã duyệt thanh toán trước 22:00, nhưng container thực tế xuất sau 22:00 và phát sinh thêm kỳ đêm: quy trình cập nhật phí? | E20: A. Hủy hiệu lực xác nhận cũ, tính và thu thêm; B. Khóa phí tại giờ CCKB duyệt; C. Trường hợp ngoại lệ riêng. | F20: B | G20: Vì nhiều lúc thanh toán và rút rồi nhưng chưa ra nhé | H20: Đã chốt | I20: Trưởng BP CCKB + An ninh | M20: Trao đổi nghiệp vụ Sơn Cảng, 10-11/10/2026 | N20: Cần làm rõ | O20: F=B khóa phí tại giờ CCKB duyệt; T09 lại chọn tính lại tại lúc cont thực ra. Cần xác định mốc chốt phí sau 22:00.
A21: L05 | B21: 02. Lưu container | C21: P1 | D21: Container vào ra trong cùng ngày, chưa qua 22:00: SO_DEM_LUU hiển thị 0 hay tối thiểu 1 (miễn phí)? | E21: A. Hiển thị 0; B. Hiển thị 1 (miễn); C. Tách đêm thực tế / đêm tính tiền. | F21: B | H21: Đã chốt | I21: Trưởng BP CCKB | M21: Trao đổi nghiệp vụ Sơn Cảng, 10-11/10/2026 | N21: Đủ rõ để đặc tả | O21: Có lựa chọn được người dùng đánh dấu đã chốt; giữ nguyên câu trả lời và ghi chú.
A22: L06 | B22: 02. Lưu container | C22: P1 | D22: Ai được sửa GIO_CONT_VAO/GIO_CONT_RA khi nhập muộn hoặc phát hiện sai? Việc sửa đã thu cần xử lý ra sao? | E22: A. Nhân viên đề xuất/TBP duyệt sau thu; B. TBP tự sửa có lý do; C. Quy trình khác. | F22: A | G22: A và B luôn | H22: Đã chốt | I22: Trưởng BP CCKB + An ninh | M22: Trao đổi nghiệp vụ Sơn Cảng, 10-11/10/2026 | N22: Cần làm rõ | O22: G=A và B: NV đề xuất/TBP duyệt hoặc TBP sửa trực tiếp; cần tách quyền theo trạng thái đã thu/chưa thu.
A23: L07 | B23: 02. Lưu container | C23: P0 | D23: Xe gốc đã ra nhưng container còn lại: CCKB duyệt tài chính cho lượt xe ra không kéo cont như thế nào? | E23: A. Chỉ cần vé xe; B. Cần xác nhận container tiếp tục ở bãi; C. Cần thêm xác nhận riêng. | F23: Khác | G23: duyệt theo container CCKB k quan tâ tới biểu số xe chỉ số cont | H23: Đã chốt | I23: Trưởng BP CCKB + An ninh | M23: Trao đổi nghiệp vụ Sơn Cảng, 10-11/10/2026 | N23: Đủ rõ để đặc tả | O23: Có lựa chọn được người dùng đánh dấu đã chốt; giữ nguyên câu trả lời và ghi chú.
A24: L08 | B24: 02. Lưu container | C24: P1 | D24: Nếu khách muốn trả trước một phần phí lưu container trong khi cont còn ở bãi, có cho phép ghi nhận không? | E24: A. Không; B. Có thanh toán trước, đối trừ khi ra; C. Chỉ nếu TBP duyệt. | F24: A | H24: Đã chốt | I24: Trưởng BP CCKB | M24: Trao đổi nghiệp vụ Sơn Cảng, 10-11/10/2026 | N24: Đủ rõ để đặc tả | O24: Có lựa chọn được người dùng đánh dấu đã chốt; giữ nguyên câu trả lời và ghi chú.
A25: L09 | B25: 02. Lưu container | C25: P1 | D25: Đơn giá phí lưu khi thay PRICE_LIST trong thời gian một container đang lưu: giữ giá lúc vào hay áp dụng theo từng kỳ ngày? | E25: A. Chốt tại GIO_CONT_VAO; B. Mỗi kỳ đêm theo bảng giá hiệu lực; C. Điều chỉnh bằng quyết định cụ thể. | F25: B | G25: Cái này khó nhỉ? A và B đi cho linh hoạt | H25: Đã chốt | I25: Trưởng BP CCKB + Quản trị | M25: Trao đổi nghiệp vụ Sơn Cảng, 10-11/10/2026 | N25: Cần làm rõ | O25: F=B tính giá theo từng đêm nhưng G muốn cả A và B linh hoạt; cần chính sách mặc định và ngoại lệ theo quyền.
A26: L10 | B26: 02. Lưu container | C26: P1 | D26: Có cần tính phí lưu cho container chưa xác định HÀNG/RỖNG, hay phải chờ Điều phối xác nhận? | E26: A. Vẫn tính; B. Chặn thanh toán đến khi rõ trạng thái; C. Khác. | F26: A | G26: Vẫn tính, có thể phân quyền lại cho user nào đó đi đếm nhé k nhất thiết điều phôi | H26: Đã chốt | I26: Trưởng BP CCKB + Điều phối | M26: Trao đổi nghiệp vụ Sơn Cảng, 10-11/10/2026 | N26: Đủ rõ để đặc tả | O26: Có lựa chọn được người dùng đánh dấu đã chốt; giữ nguyên câu trả lời và ghi chú.
A27: E01 | B27: 03. Cắm/rút điện | C27: P0 | D27: CCKB được tạo phiên cắm/rút và nhập giờ sau khi An ninh báo qua Zalo mà KHÔNG lập trước lệnh trong PWA chứ? | E27: A. Có, được nhập hồi tố và ghi giờ báo; B. Luôn phải lập yêu cầu trước; C. Kết hợp cả hai. | F27: C | G27: Cả 2 đi cho thoải mái | H27: Đã chốt | I27: Trưởng BP CCKB + An ninh | M27: Trao đổi nghiệp vụ Sơn Cảng, 10-11/10/2026 | N27: Đủ rõ để đặc tả | O27: Có lựa chọn được người dùng đánh dấu đã chốt; giữ nguyên câu trả lời và ghi chú.
A28: E02 | B28: 03. Cắm/rút điện | C28: P0 | D28: Trường hợp khách yêu cầu cắm/rút trực tiếp với An ninh mà chưa báo CCKB: xử lý nhập và xác minh ra sao? | E28: A. An ninh báo CCKB, nhập sau; B. Không làm khi chưa có CCKB; C. Ngoại lệ theo ca. | F28: Khác | G28: A và B | H28: Đã chốt | I28: Trưởng BP CCKB + An ninh | M28: Trao đổi nghiệp vụ Sơn Cảng, 10-11/10/2026 | N28: Cần làm rõ | O28: G=A và B: yêu cầu khách đi thẳng tới An ninh, vừa cho làm trước vừa muốn chờ CCKB; cần luồng ngoại lệ rõ.
A29: E03 | B29: 03. Cắm/rút điện | C29: P1 | D29: Hình thức Theo giờ và Cắm liên tục có khác nhau ở cách vận hành/thanh toán hay hiện chỉ khác danh mục yêu cầu? | E29: A. Chỉ khác tên; B. Có quy tắc riêng, ghi cụ thể; C. Sẽ phân biệt ở giai đoạn sau. | F29: A | G29: CHỉ khác là 1 cái biết giờ rút 1 cái chưa | H29: Đã chốt | I29: Trưởng BP CCKB | M29: Trao đổi nghiệp vụ Sơn Cảng, 10-11/10/2026 | N29: Cần làm rõ | O29: G xác định theo giờ biết giờ rút dự kiến, liên tục chưa biết; trước đó form không yêu cầu giờ rút dự kiến. Cần là trường tùy chọn.
A30: E04 | B30: 03. Cắm/rút điện | C30: P0 | D30: CCKB nhập GIO_CAM_THUC_TE khi container đã rút rồi: cho phép nhập cả giờ cắm và rút trong một biểu mẫu không? | E30: A. Có; B. Tách thành hai bước bắt buộc; C. Chỉ TBP nhập hồi tố. | F30: A | G30: có cho thoải mái giờ chưa kiểm soát chặt lắm | H30: Đã chốt | I30: Trưởng BP CCKB | M30: Trao đổi nghiệp vụ Sơn Cảng, 10-11/10/2026 | N30: Đủ rõ để đặc tả | O30: Có lựa chọn được người dùng đánh dấu đã chốt; giữ nguyên câu trả lời và ghi chú.
A31: E05 | B31: 03. Cắm/rút điện | C31: P0 | D31: Khi An ninh báo giờ cắm/rút không chính xác, CCKB xác minh bằng cách nào trước khi sửa? | E31: A. CCKB chỉnh có ghi chú; B. Cần ảnh tin nhắn Zalo; C. Phải có TBP xác nhận khi chênh lệch lớn. | F31: Khác | G31: Hienj tại khi cắm rút thì an ninh sẽ quay bằng camera time stamp, rồi gửi nhóm | H31: Đã chốt | I31: Trưởng BP CCKB | M31: Trao đổi nghiệp vụ Sơn Cảng, 10-11/10/2026 | N31: Đủ rõ để đặc tả | O31: Có lựa chọn được người dùng đánh dấu đã chốt; giữ nguyên câu trả lời và ghi chú.
A32: E06 | B32: 03. Cắm/rút điện | C32: P0 | D32: Sau khi đã thu tiền điện, CCKB được sửa giờ tới mức nào và quy trình phê duyệt chênh lệch? | E32: A. NV tạo đề nghị/TBP CCKB duyệt; B. TBP sửa trực tiếp có nhật ký; C. NV được sửa và ghi lý do (không duyệt). | F32: B | G32: A Và B | H32: Đã chốt | I32: Trưởng BP CCKB | M32: Đồng thuận sơ bộ: cần phê duyệt điều chỉnh sau thu | N32: Cần làm rõ | O32: F=B nhưng G=A và B: vừa NV đề nghị/TBP duyệt vừa TBP sửa trực tiếp; cần điều kiện khi nào mỗi cách.
A33: E07 | B33: 03. Cắm/rút điện | C33: P0 | D33: Phiên điện còn trạng thái Đang cắm trên PWA nhưng thực tế đã rút, container có được xuất không? | E33: A. CCKB bắt buộc hoàn thành ghi nhận trước khi ra; B. TBP duyệt xuất ngoại lệ; C. Khác. | F33: A | G33: Làm cách nào thoai r mái hon, CCKB cứ xác định xe đã được ra thì ra, nếu xe ra đến cổng mà chưa thấy được ra thì gọi hoặc nhắn nhóm có CCKB | H33: Đã chốt | I33: Trưởng BP CCKB + An ninh | M33: Trao đổi nghiệp vụ Sơn Cảng, 10-11/10/2026 | N33: Cần làm rõ | O33: F=A buộc cập nhật xong trước ra, nhưng G ưu tiên CCKB xác nhận bằng tay và Zalo khi cần; cần cơ chế override có audit.
A34: E08 | B34: 03. Cắm/rút điện | C34: P1 | D34: Khi không có mạng/không thể cập nhật giờ rút, cần quy trình bàn giao ngoài hệ thống và bổ sung dữ liệu như thế nào? | E34: A. Nhật ký giấy/Zalo rồi nhập lại có giờ nguồn; B. Không cho xuất cho đến khi hệ thống hoạt động; C. Ngoại lệ TBP. | F34: A | G34: chỗ này chưa hiểu | H34: Đã chốt | I34: Trưởng BP CCKB + Quản trị | M34: Trao đổi nghiệp vụ Sơn Cảng, 10-11/10/2026 | N34: Cần làm rõ | O34: G ghi “chỗ này chưa hiểu”; không thể coi là quyết định đã chốt dù F=A. Cần giải thích quy trình offline và nhập bù.
A35: E09 | B35: 03. Cắm/rút điện | C35: P1 | D35: Tổng thời gian thực tế tính bằng giây hay phút? Ví dụ 4 giờ 00 phút 01 giây có làm tròn thành 4 giờ 15 phút không? | E35: A. Bỏ giây/lấy phút; B. Giữ giây rồi làm tròn block 15 phút; C. Khác. | F35: Khác | G35: Hieện tại CCKB tự làm tròn | H35: Đã chốt | I35: Trưởng BP CCKB | M35: Trao đổi nghiệp vụ Sơn Cảng, 10-11/10/2026 | N35: Cần làm rõ | O35: G: CCKB tự làm tròn, trong khi đã chốt tính tròn lên mỗi 15 phút. Cần xác nhận tự tính mặc định + cho điều chỉnh thủ công.
A36: E10 | B36: 03. Cắm/rút điện | C36: P1 | D36: Phiên cắm ngắn dưới 15 phút hoặc vô tình cắm 0 phút: tính tối thiểu 15 phút khi có cắm thực tế không? | E36: A. >0 phút tính 15 phút; B. Có mức tối thiểu khác; C. Không thu dưới ngưỡng. | F36: Khác | G36: Hieện tại CCKB tự làm tròn | H36: Đã chốt | I36: Trưởng BP CCKB | M36: Trao đổi nghiệp vụ Sơn Cảng, 10-11/10/2026 | N36: Cần làm rõ | O36: G: CCKB tự làm tròn; chưa khóa khoản phí tối thiểu cho phiên ngắn dưới 15 phút và 0 phút.
A37: E11 | B37: 03. Cắm/rút điện | C37: P1 | D37: Một container cắm/rút nhiều phiên trong cùng một lần vào bãi: làm tròn 15 phút riêng mỗi phiên hay gộp trước khi làm tròn? | E37: A. Riêng từng phiên; B. Gộp thời gian nhiều phiên; C. Theo hình thức dịch vụ. | F37: A | H37: Đã chốt | I37: Trưởng BP CCKB | M37: Trao đổi nghiệp vụ Sơn Cảng, 10-11/10/2026 | N37: Đủ rõ để đặc tả | O37: Có lựa chọn được người dùng đánh dấu đã chốt; giữ nguyên câu trả lời và ghi chú.
A38: E12 | B38: 03. Cắm/rút điện | C38: P1 | D38: Có cho một container ghi nhận hai phiên cắm điện đồng thời hay bắt buộc mỗi thời điểm chỉ có một phiên? | E38: A. Chỉ một phiên hoạt động; B. Có nhiều ổ cắm/điểm cấp điện song song; C. Ngoại lệ. | F38: A | H38: Đã chốt | I38: Trưởng BP CCKB | M38: Trao đổi nghiệp vụ Sơn Cảng, 10-11/10/2026 | N38: Đủ rõ để đặc tả | O38: Có lựa chọn được người dùng đánh dấu đã chốt; giữ nguyên câu trả lời và ghi chú.
A39: E13 | B39: 03. Cắm/rút điện | C39: P1 | D39: Khi cập nhật giá điện trong lúc phiên cắm đang chạy: giữ giá lúc bắt đầu hay áp giá mới khi rút? | E39: A. Giữ giá lúc cắm; B. Theo giá lúc rút; C. Chia theo thời điểm đổi giá. | F39: B | G39: tùy A và B | H39: Đã chốt | I39: Trưởng BP CCKB + Quản trị | M39: Trao đổi nghiệp vụ Sơn Cảng, 10-11/10/2026 | N39: Cần làm rõ | O39: F=B tính giá mới khi rút, nhưng G “tùy A và B”; cần chính sách mặc định theo phiên và lựa chọn điều chỉnh giá.
A40: E14 | B40: 03. Cắm/rút điện | C40: P1 | D40: Có yêu cầu lưu vị trí/ổ cắm/số công tơ/ảnh khi cắm, hay chỉ theo container và giờ thực tế? | E40: A. Chỉ cont và giờ; B. Thêm vị trí ổ cắm; C. Thêm ảnh/công tơ; ghi rõ. | F40: A | G40: có thể cho an ninh điền cái này cx được để họ nhớ, sau này làm sơ đồ cũng dễ | H40: Đã chốt | I40: Trưởng BP CCKB + An ninh | M40: Trao đổi nghiệp vụ Sơn Cảng, 10-11/10/2026 | N40: Đủ rõ để đặc tả | O40: Có lựa chọn được người dùng đánh dấu đã chốt; giữ nguyên câu trả lời và ghi chú.
A41: E15 | B41: 03. Cắm/rút điện | C41: P1 | D41: Ai là người được phép sửa danh mục đơn giá cắm điện và có cần TBP/BLĐ phê duyệt mức giá mới? | E41: A. Quản trị; B. Trưởng BP CCKB; C. CCKB đề xuất, Quản trị duyệt; khác. | F41: A | H41: Đã chốt | I41: Trưởng BP CCKB + Quản trị | M41: Trao đổi nghiệp vụ Sơn Cảng, 10-11/10/2026 | N41: Đủ rõ để đặc tả | O41: Có lựa chọn được người dùng đánh dấu đã chốt; giữ nguyên câu trả lời và ghi chú.
A42: E16 | B42: 03. Cắm/rút điện | C42: P1 | D42: CCKB có cần chọn người An ninh đã trực tiếp cắm/rút, dù người nhập giờ là CCKB không? | E42: A. Có, bắt buộc chọn; B. Ghi chú tự do; C. Không cần. | F42: B | H42: Đã chốt | I42: Trưởng BP CCKB + An ninh | M42: Trao đổi nghiệp vụ Sơn Cảng, 10-11/10/2026 | N42: Đủ rõ để đặc tả | O42: Có lựa chọn được người dùng đánh dấu đã chốt; giữ nguyên câu trả lời và ghi chú.
A43: T01 | B43: 04. Thanh toán | C43: P0 | D43: Có cho thanh toán từng phần phí điện/lưu hoặc nộp trước khi container xuất không? | E43: A. Không, thanh toán đủ theo khoản; B. Có, cho thanh toán một phần; C. Chỉ theo phê duyệt. | F43: B | G43: Linh hoạt thu cả hoặc thu từng phần | H43: Đã chốt | I43: Trưởng BP CCKB | M43: Trao đổi nghiệp vụ Sơn Cảng, 10-11/10/2026 | N43: Cần làm rõ | O43: F=B chỉ cho trả một phần, G cho cả trả đủ và trả một phần; cần xác định dữ liệu phân bổ giao dịch.
A44: T02 | B44: 04. Thanh toán | C44: P0 | D44: Một lần thanh toán có thể kết hợp tiền mặt và chuyển khoản không? | E44: A. Có, ghi mỗi phương thức một phần; B. Không, một giao dịch một phương thức; C. Tùy khoản. | F44: A | H44: Đã chốt | I44: Trưởng BP CCKB | M44: Trao đổi nghiệp vụ Sơn Cảng, 10-11/10/2026 | N44: Đủ rõ để đặc tả | O44: Có lựa chọn được người dùng đánh dấu đã chốt; giữ nguyên câu trả lời và ghi chú.
A45: T03 | B45: 04. Thanh toán | C45: P0 | D45: Xác nhận chuyển khoản dựa trên ảnh khách gửi hay bắt buộc kiểm tra tài khoản công ty thực nhận? | E45: A. Kiểm tra tiền về; B. Ảnh biên lai được chấp nhận; C. Theo ngưỡng tiền và quyền. | F45: A | G45: CCKB tự xác định tiền cắm còn Lưu đêm và vé vào thì an ninh | H45: Đã chốt | I45: Trưởng BP CCKB + Kế toán | M45: Trao đổi nghiệp vụ Sơn Cảng, 10-11/10/2026 | N45: Cần làm rõ | O45: G: CCKB kiểm tra tiền cắm, AN NINH nhận lưu đêm và vé; mâu thuẫn phân công CCKB thu phí lưu đã nói trước.
A46: T04 | B46: 04. Thanh toán | C46: P0 | D46: Ảnh bằng chứng thu tiền cần bắt buộc với giao dịch nào (vé, lưu cont, điện, mất vé)? | E46: A. Mọi chuyển khoản; B. Mọi giao dịch; C. Chỉ theo quy định từng loại. | F46: Khác | G46: Xây dưng nhưng chưa ap dụng | H46: Đã chốt | I46: Trưởng BP An ninh + CCKB | M46: Trao đổi nghiệp vụ Sơn Cảng, 10-11/10/2026 | N46: Cần làm rõ | O46: G: “Xây dựng nhưng chưa áp dụng”; cần tách tính năng ảnh chứng từ triển khai V1 hay để tùy chọn.
A47: T05 | B47: 04. Thanh toán | C47: P1 | D47: Khoản phạt mất vé được thanh toán và đối soát như một dòng phí riêng hay gộp cùng tiền vé ban đầu? | E47: A. Tách khoản phí riêng; B. Gộp vào vé; C. Tùy thời điểm phát hiện. | F47: A | H47: Đã chốt | I47: Trưởng BP An ninh + CCKB | M47: Trao đổi nghiệp vụ Sơn Cảng, 10-11/10/2026 | N47: Đủ rõ để đặc tả | O47: Có lựa chọn được người dùng đánh dấu đã chốt; giữ nguyên câu trả lời và ghi chú.
A48: T06 | B48: 04. Thanh toán | C48: P0 | D48: Nếu đã thu thiếu hoặc thừa tiền so với hệ thống: cách điều chỉnh/hoàn trả, ai duyệt? | E48: A. NV lập phiếu, TBP duyệt; B. Chỉ Quản trị; C. Quy trình khác. | F48: Khác | G48: Xây dưng nhưng chưa ap dụng | H48: Đã chốt | I48: Trưởng BP CCKB | M48: Trao đổi nghiệp vụ Sơn Cảng, 10-11/10/2026 | N48: Cần làm rõ | O48: G: xây dựng nhưng chưa áp dụng; hệ thống thu/hoàn tiền cần quy định tối thiểu để không mất dấu chênh lệch.
A49: T07 | B49: 04. Thanh toán | C49: P0 | D49: Có được miễn/giảm giá vé, phí lưu, tiền điện? Ai là người có quyền duyệt? | E49: A. TBP theo bộ phận; B. Quản trị; C. Ban lãnh đạo; tùy loại phí. | F49: Khác | G49: Xây dưng nhưng chưa ap dụng | H49: Đã chốt | I49: Ban quản lý Sơn Cảng | M49: Trao đổi nghiệp vụ Sơn Cảng, 10-11/10/2026 | N49: Cần làm rõ | O49: G: xây dựng nhưng chưa áp dụng; xác định có cho phát sinh ngoại lệ ngay V1 không.
A50: T08 | B50: 04. Thanh toán | C50: P0 | D50: Có cho xuất container khi còn nợ phí hoặc đã gửi chứng từ nhưng chưa xác minh nhận tiền không? | E50: A. Không; B. Cho phép nếu TBP phê duyệt; C. Công nợ khách hàng theo danh sách. | F50: Khác | G50: CCKB sẽ xác nhận cho ra hay k và có thể báo cho ra nhưng tiền chưa thusex hiện cảnh báo, 1 là tự động nếu cckb đã điền đủ thanh toán và có cái xác nhận cho xe ra bằng tay mà tiền chưa ghi nhận | H50: Đã chốt | I50: Trưởng BP CCKB | M50: Trao đổi nghiệp vụ Sơn Cảng, 10-11/10/2026 | N50: Cần làm rõ | O50: Cho CCKB duyệt xuất khi chưa thu tiền bằng tay và cảnh báo; cần vai trò, lý do và xử lý khoản nợ sau ra.
A51: T09 | B51: 04. Thanh toán | C51: P0 | D51: Tại cổng ra, trạng thái tài chính hợp lệ có thời hạn bao lâu trước khi phải tính lại phí lưu? | E51: A. Luôn tính lại lúc xe/cont thực ra; B. CCKB xác nhận hiệu lực n phút; C. Chốt theo giờ duyệt. | F51: A | G51: Phí lưu chỉ có AN ninh tính tại lúc ra | H51: Đã chốt | I51: Trưởng BP CCKB + An ninh | M51: Trao đổi nghiệp vụ Sơn Cảng, 10-11/10/2026 | N51: Cần làm rõ | O51: G: An ninh tính phí lưu khi ra, trong khi phân công CCKB tính/thu phí lưu. Đồng thời mâu thuẫn L04.
A52: T10 | B52: 04. Thanh toán | C52: P1 | D52: Khi xe ra không kéo container, An ninh có cần CCKB xác nhận tài chính riêng cho LƯỢT XE không? | E52: A. Chỉ kiểm tra vé đã thu; B. CCKB duyệt tất cả lượt ra; C. Chỉ duyệt xe có cont. | F52: A | G52: K cần xác nhận nếu k có cont ra vì CCKB chỉ quan tâm cont chứ xe k quan tâm | H52: Đã chốt | I52: Trưởng BP CCKB + An ninh | M52: Trao đổi nghiệp vụ Sơn Cảng, 10-11/10/2026 | N52: Đủ rõ để đặc tả | O52: Có lựa chọn được người dùng đánh dấu đã chốt; giữ nguyên câu trả lời và ghi chú.
A53: T11 | B53: 04. Thanh toán | C53: P1 | D53: CCKB có được thu hộ nhiều container/xe trong một lần chuyển khoản và phân bổ vào nhiều khoản phí không? | E53: A. Có, phân bổ khoản; B. Không, mỗi lần cho một đối tượng; C. Có điều kiện. | F53: A | G53: Linh hoạt như nào dễ cho ng dùng thì làm | H53: Đã chốt | I53: Trưởng BP CCKB | M53: Trao đổi nghiệp vụ Sơn Cảng, 10-11/10/2026 | N53: Đủ rõ để đặc tả | O53: Có lựa chọn được người dùng đánh dấu đã chốt; giữ nguyên câu trả lời và ghi chú.
A54: T12 | B54: 04. Thanh toán | C54: P1 | D54: Khi có khách hàng thường xuyên: có quản lý hồ sơ khách, mã số thuế, công nợ/hóa đơn không? | E54: A. V1 chỉ tên/số điện thoại; B. Quản lý danh mục khách hàng; C. Thêm công nợ/hóa đơn. | F54: Không áp dụng | G54: Sau này có nhé, vì bên Kế toán cũng muốn joint vào hệ thông này ví dụ ở trên vé vào hienejt ại an ninh điền thông tin lái xe hoặc thông tin công ty để xuất hóa đơn, có cái xuất có cái k xuất nhé, xong kế toán cũng cần tổng hợp và điền báo cáo nữa.) Các thông tin cần điền(Họ tên/Tên công ty, Mã só thuế/số CCCD, thương trú, có thể sđt n, e mail nữa | H54: Đã chốt | I54: Trưởng BP CCKB + Kế toán | M54: Trao đổi nghiệp vụ Sơn Cảng, 10-11/10/2026 | N54: Cần làm rõ | O54: Chọn Không áp dụng nhưng G yêu cầu nhập thông tin lái xe/công ty để phục vụ hóa đơn; Kế toán phát triển sau. Cần tách V1/V2.
A55: T13 | B55: 04. Thanh toán | C55: P1 | D55: Có cho hủy giao dịch thu tiền do nhập nhầm? Yêu cầu lý do/phê duyệt và xử lý dòng đối ứng? | E55: A. Chỉ tạo giao dịch đảo; B. Cho hủy với duyệt; C. Khác. | F55: B | G55: Linh hoạt như nào dễ cho ng dùng thì làm | H55: Đã chốt | I55: Trưởng BP CCKB | M55: Trao đổi nghiệp vụ Sơn Cảng, 10-11/10/2026 | N55: Đủ rõ để đặc tả | O55: Có lựa chọn được người dùng đánh dấu đã chốt; giữ nguyên câu trả lời và ghi chú.
A56: T14 | B56: 04. Thanh toán | C56: P1 | D56: Doanh thu vé An ninh thu và doanh thu phí CCKB thu được đối soát cuối ca như thế nào? | E56: A. Theo cá nhân/ca; B. Theo bộ phận/ngày; C. Hai cấp đối soát; ghi quy định. | F56: Khác | G56: theo ca nhé, ca lammf việc của an ninh hiện tại là 6H-18H nhưng chốt doanh thu có thẻ là 16H và 8h30 9H kiểu vậy | H56: Đã chốt | I56: Trưởng BP An ninh + CCKB + Kế toán | M56: Trao đổi nghiệp vụ Sơn Cảng, 10-11/10/2026 | N56: Cần làm rõ | O56: Chốt doanh thu không trùng giờ ca 06–18, ví dụ 16:00 hoặc 08:30–09:00; cần cấu hình kỳ chốt và người chịu trách nhiệm.
A57: T15 | B57: 04. Thanh toán | C57: P1 | D57: Sau khi CCKB đã cấp đủ điều kiện thanh toán, An ninh phát hiện sai số cont/biển số: có quyền hủy xác nhận và gửi duyệt lại không? | E57: A. Tự hủy và yêu cầu kiểm tra; B. Chỉ CCKB thu hồi; C. TBP duyệt. | F57: Không áp dụng | H57: Đã chốt | I57: Trưởng BP An ninh + CCKB | M57: Trao đổi nghiệp vụ Sơn Cảng, 10-11/10/2026 | N57: Cần làm rõ | O57: F=Không áp dụng việc thu hồi duyệt khi phát hiện sai cont; SC08 cần cơ chế xử lý khi sai cont sau duyệt.
A58: P01 | B58: 05. Phân quyền | C58: P0 | D58: Các vai trò chính xác cần tạo là 6 vai trò NV/TBP của 3 bộ phận + Quản trị, hay bổ sung Nhà cân/Kế toán? | E58: A. 7 vai trò; B. Thêm Nhà cân; C. Thêm Kế toán; ghi rõ. | F58: C | H58: Đã chốt | I58: Quản trị + Các TBP | M58: Trao đổi nghiệp vụ Sơn Cảng, 10-11/10/2026 | N58: Cần làm rõ | O58: F=C đề xuất thêm Kế toán, nhưng các tính năng Kế toán ghi giai đoạn sau. Cần xác định vai trò kế toán có ở V1 không.
A59: P02 | B59: 05. Phân quyền | C59: P0 | D59: TBP An ninh có được sửa GIO_VAO/GIO_RA và xuất xe thay NV An ninh không? | E59: A. Có; B. Chỉ duyệt sửa, không thực hiện; C. Tùy chức năng. | F59: A | G59: ghi lại audit | H59: Đã chốt | I59: Trưởng BP An ninh | M59: Trao đổi nghiệp vụ Sơn Cảng, 10-11/10/2026 | N59: Đủ rõ để đặc tả | O59: Có lựa chọn được người dùng đánh dấu đã chốt; giữ nguyên câu trả lời và ghi chú.
A60: P03 | B60: 05. Phân quyền | C60: P0 | D60: TBP CCKB có quyền duyệt điều chỉnh sau thu, duyệt miễn giảm và duyệt xuất ngoại lệ đến hạn mức nào? | E60: A. Toàn bộ; B. Giới hạn theo số tiền; C. Phải chuyển Quản trị/BLĐ. | F60: A | G60: ghi lại audit | H60: Đã chốt | I60: Trưởng BP CCKB | M60: Trao đổi nghiệp vụ Sơn Cảng, 10-11/10/2026 | N60: Đủ rõ để đặc tả | O60: Có lựa chọn được người dùng đánh dấu đã chốt; giữ nguyên câu trả lời và ghi chú.
A61: P04 | B61: 05. Phân quyền | C61: P1 | D61: NV CCKB có được sửa giờ điện trước thanh toán không giới hạn hay chỉ trong ca/24 giờ? | E61: A. Không giới hạn trước thu; B. Trong ca; C. Theo thời hạn khác. | F61: A | G61: được | H61: Đã chốt | I61: Trưởng BP CCKB | M61: Trao đổi nghiệp vụ Sơn Cảng, 10-11/10/2026 | N61: Đủ rõ để đặc tả | O61: Có lựa chọn được người dùng đánh dấu đã chốt; giữ nguyên câu trả lời và ghi chú.
A62: P05 | B62: 05. Phân quyền | C62: P1 | D62: TBP Điều phối có được sửa HÀNG/RỖNG sau khi container xuất bãi không? | E62: A. Có, kèm lý do; B. Chỉ trước khi xuất; C. Quản trị sửa sau xuất. | F62: A | H62: Đã chốt | I62: Trưởng BP Điều phối | M62: Trao đổi nghiệp vụ Sơn Cảng, 10-11/10/2026 | N62: Đủ rõ để đặc tả | O62: Có lựa chọn được người dùng đánh dấu đã chốt; giữ nguyên câu trả lời và ghi chú.
A63: P06 | B63: 05. Phân quyền | C63: P1 | D63: Ai có quyền mở khóa/xử lý dữ liệu đã chốt sau ra cổng mà không làm thay đổi lịch sử thu tiền? | E63: A. Quản trị; B. TBP liên quan + xác nhận; C. Quy trình 2 cấp. | F63: B | H63: Đã chốt | I63: Quản trị + Các TBP | M63: Trao đổi nghiệp vụ Sơn Cảng, 10-11/10/2026 | N63: Đủ rõ để đặc tả | O63: Có lựa chọn được người dùng đánh dấu đã chốt; giữ nguyên câu trả lời và ghi chú.
A64: P07 | B64: 05. Phân quyền | C64: P1 | D64: Một nhân viên có thể kiêm 2 bộ phận/vai trò trên một tài khoản không? | E64: A. Một tài khoản nhiều vai trò; B. Một vai trò; C. Theo ca. | F64: Khác | G64: Cài này có lúc theo ca có lúc 1 tk nhiêu role nhưng cứ xây dựng giai đoạn đầu máy sẽ cố định tại bốt cont CCKB thì sẽ đăng nhập tk cá nhân(Sau này muốn phát triển ai có ca mới được vào) | H64: Đã chốt | I64: Quản trị | M64: Trao đổi nghiệp vụ Sơn Cảng, 10-11/10/2026 | N64: Cần làm rõ | O64: PWA tại bốt An ninh có thể dùng thiết bị cố định; CCKB dùng tài khoản cá nhân, phân vai theo ca sau. Cần audit cá nhân khi dùng thiết bị chung.
A65: P08 | B65: 05. Phân quyền | C65: P1 | D65: Cần tạo tài khoản mới bằng email công ty hay dùng email Gmail hiện có để đăng nhập? | E65: A. Google login email sẵn có; B. Email công ty; C. Email/mật khẩu độc lập. | F65: C | H65: Đã chốt | I65: Quản trị | M65: Trao đổi nghiệp vụ Sơn Cảng, 10-11/10/2026 | N65: Đủ rõ để đặc tả | O65: Có lựa chọn được người dùng đánh dấu đã chốt; giữ nguyên câu trả lời và ghi chú.
A66: P09 | B66: 05. Phân quyền | C66: P1 | D66: Người dùng bị khóa/nghỉ việc thì dữ liệu lịch sử và quyền đăng nhập được xử lý thế nào? | E66: A. Vô hiệu hóa, giữ lịch sử; B. Quy trình khác. | F66: A | H66: Đã chốt | I66: Quản trị | M66: Trao đổi nghiệp vụ Sơn Cảng, 10-11/10/2026 | N66: Đủ rõ để đặc tả | O66: Có lựa chọn được người dùng đánh dấu đã chốt; giữ nguyên câu trả lời và ghi chú.
A67: P10 | B67: 05. Phân quyền | C67: P1 | D67: CCKB có quyền xem và điều chỉnh trạng thái vé An ninh thu hay chỉ đọc? | E67: A. Chỉ xem; B. Có quyền báo sai lệch; C. Được chỉnh sau duyệt. | F67: A | H67: Đã chốt | I67: Trưởng BP An ninh + CCKB | M67: Trao đổi nghiệp vụ Sơn Cảng, 10-11/10/2026 | N67: Đủ rõ để đặc tả | O67: Có lựa chọn được người dùng đánh dấu đã chốt; giữ nguyên câu trả lời và ghi chú.
A68: D01 | B68: 06. Điều phối / container | C68: P0 | D68: Điều phối nhập HÀNG/RỖNG lúc nào và có được để trống khi container vừa vào không? | E68: A. Bắt buộc trước khi tiếp nhận; B. Được trống, hoàn thiện trước ra; C. Linh hoạt theo ca. | F68: B | G68: được trống | H68: Đã chốt | I68: Trưởng BP Điều phối | M68: Trao đổi nghiệp vụ Sơn Cảng, 10-11/10/2026 | N68: Đủ rõ để đặc tả | O68: Có lựa chọn được người dùng đánh dấu đã chốt; giữ nguyên câu trả lời và ghi chú.
A69: D02 | B69: 06. Điều phối / container | C69: P1 | D69: Nếu Điều phối thay đổi HÀNG thành RỖNG (hoặc ngược lại), có cần ghi lý do/người xác nhận không? | E69: A. Có; B. Chỉ khi đã chốt; C. Khác. | F69: A | G69: ghi lí do k bắt bược | H69: Đã chốt | I69: Trưởng BP Điều phối | M69: Trao đổi nghiệp vụ Sơn Cảng, 10-11/10/2026 | N69: Cần làm rõ | O69: F=A ghi lý do nhưng G nói không bắt buộc. Chốt việc đổi HÀNG/RỖNG có bắt buộc lý do hay chỉ lưu audit.
A70: D03 | B70: 06. Điều phối / container | C70: P0 | D70: Xe vào mang container A, ra nhận container B: ai ghép ID_CONTAINER_RA với lượt xe ở bước cuối? | E70: A. An ninh chọn; B. Điều phối chỉ định, An ninh xác nhận; C. CCKB chọn. | F70: A | H70: Đã chốt | I70: Trưởng BP An ninh + Điều phối | M70: Trao đổi nghiệp vụ Sơn Cảng, 10-11/10/2026 | N70: Đủ rõ để đặc tả | O70: Có lựa chọn được người dùng đánh dấu đã chốt; giữ nguyên câu trả lời và ghi chú.
A71: D04 | B71: 06. Điều phối / container | C71: P1 | D71: Có quản lý vị trí container (khu/bãi/dãy/ô) khi hạ, khi xếp lên xe hay chỉ kiểm soát có/không trong bãi? | E71: A. Chỉ trong bãi; B. Khu vực; C. Định vị ô/kệ. | F71: Khác | G71: Cả 3 luôn nhưng giai đoạn đâu chưa, phát triển phase sau | H71: Đã chốt | I71: Trưởng BP Điều phối | M71: Trao đổi nghiệp vụ Sơn Cảng, 10-11/10/2026 | N71: Đủ rõ để đặc tả | O71: Có lựa chọn được người dùng đánh dấu đã chốt; giữ nguyên câu trả lời và ghi chú.
A72: D05 | B72: 06. Điều phối / container | C72: P1 | D72: Một số container có thể vào/ra bãi nhiều lần: hệ thống có cần hiển thị lịch sử theo số cont và phân biệt bằng lượt ID không? | E72: A. Có, lịch sử nhiều lượt; B. Quy tắc khác. | F72: A | H72: Đã chốt | I72: Trưởng BP Điều phối + Quản trị | M72: Trao đổi nghiệp vụ Sơn Cảng, 10-11/10/2026 | N72: Đủ rõ để đặc tả | O72: Có lựa chọn được người dùng đánh dấu đã chốt; giữ nguyên câu trả lời và ghi chú.
A73: D06 | B73: 06. Điều phối / container | C73: P1 | D73: Khi số container gõ nhầm hoặc khác so với trên vé, người nào được xác nhận sửa thông tin? | E73: A. An ninh sửa trước ra; B. Điều phối duyệt; C. TBP An ninh duyệt. | F73: A | G73: TBP thì sửa trực tiếp | H73: Đã chốt | I73: Trưởng BP Điều phối + An ninh | M73: Trao đổi nghiệp vụ Sơn Cảng, 10-11/10/2026 | N73: Cần làm rõ | O73: F=A NV An ninh sửa; G TBP được sửa trực tiếp; yêu cầu mới An ninh sửa và báo CCKB. Cần ngưỡng quyền sau thu/ra.
A74: R01 | B74: 07. Báo cáo / đối soát | C74: P1 | D74: Báo cáo doanh thu yêu cầu chi tiết theo ca, ngày, tháng, loại phí, nhân viên, bộ phận hay tổng hợp nào? | E74: A. Tất cả; B. Theo nhóm được chọn; C. Báo cáo mẫu riêng. | F74: A | H74: Đã chốt | I74: Các TBP + Kế toán | M74: Trao đổi nghiệp vụ Sơn Cảng, 10-11/10/2026 | N74: Đủ rõ để đặc tả | O74: Có lựa chọn được người dùng đánh dấu đã chốt; giữ nguyên câu trả lời và ghi chú.
A75: R02 | B75: 07. Báo cáo / đối soát | C75: P1 | D75: Cần giao ca trên PWA với số dư tiền mặt, biên bản đối soát, người bàn giao/người nhận không? | E75: A. Có; B. Chỉ báo cáo cuối ca; C. Giao ca ngoài hệ thống. | F75: C | G75: Trc mắt ngoài hệ thống | H75: Đã chốt | I75: Trưởng BP An ninh + CCKB | M75: Trao đổi nghiệp vụ Sơn Cảng, 10-11/10/2026 | N75: Đủ rõ để đặc tả | O75: Có lựa chọn được người dùng đánh dấu đã chốt; giữ nguyên câu trả lời và ghi chú.
A76: R03 | B76: 07. Báo cáo / đối soát | C76: P1 | D76: Cần bảng theo dõi xe quá hạn, container còn lưu nhiều ngày, điện chưa rút, chưa thu tiền và thông báo tự động không? | E76: A. Có tất cả; B. Chỉ danh sách; C. Chọn cảnh báo cụ thể. | F76: A | H76: Đã chốt | I76: Các TBP | M76: Trao đổi nghiệp vụ Sơn Cảng, 10-11/10/2026 | N76: Đủ rõ để đặc tả | O76: Có lựa chọn được người dùng đánh dấu đã chốt; giữ nguyên câu trả lời và ghi chú.
A77: R04 | B77: 07. Báo cáo / đối soát | C77: P2 | D77: Các báo cáo xuất Excel/PDF có cần theo mẫu nội bộ và phân quyền người tải xuống? | E77: A. Excel; B. Excel + PDF; C. Có mẫu ban hành. | F77: B | H77: Đã chốt | I77: Các TBP | M77: Trao đổi nghiệp vụ Sơn Cảng, 10-11/10/2026 | N77: Đủ rõ để đặc tả | O77: Có lựa chọn được người dùng đánh dấu đã chốt; giữ nguyên câu trả lời và ghi chú.
A78: R05 | B78: 07. Báo cáo / đối soát | C78: P1 | D78: Người quản lý muốn dashboard thời gian thực chỉ số nào: xe trong bãi, cont trong bãi, cont đang cắm, doanh thu, công nợ? | E78: A. Tất cả; B. Chọn KPI cụ thể; C. Xem theo bộ phận. | F78: A | H78: Đã chốt | I78: Ban quản lý Sơn Cảng | M78: Trao đổi nghiệp vụ Sơn Cảng, 10-11/10/2026 | N78: Đủ rõ để đặc tả | O78: Có lựa chọn được người dùng đánh dấu đã chốt; giữ nguyên câu trả lời và ghi chú.
A79: R06 | B79: 07. Báo cáo / đối soát | C79: P1 | D79: Có bắt buộc đối chiếu sao kê chuyển khoản với chứng từ và ghi lịch sử xác minh trên PWA không? | E79: A. Có; B. Đối soát ngoài hệ thống; C. Theo hạn mức. | F79: B | H79: Đã chốt | I79: Trưởng BP CCKB + Kế toán | M79: Trao đổi nghiệp vụ Sơn Cảng, 10-11/10/2026 | N79: Đủ rõ để đặc tả | O79: Có lựa chọn được người dùng đánh dấu đã chốt; giữ nguyên câu trả lời và ghi chú.
A80: R07 | B80: 07. Báo cáo / đối soát | C80: P2 | D80: Các báo cáo cần tự động gửi qua email/Zalo theo lịch hay chỉ xem khi đăng nhập? | E80: A. Chỉ trong app; B. Gửi email; C. Tích hợp Zalo sau. | F80: B | G80: cả 3, zalo thì sau | H80: Đã chốt | I80: Ban quản lý Sơn Cảng | M80: Trao đổi nghiệp vụ Sơn Cảng, 10-11/10/2026 | N80: Đủ rõ để đặc tả | O80: Có lựa chọn được người dùng đánh dấu đã chốt; giữ nguyên câu trả lời và ghi chú.
A81: K01 | B81: 08. Kỹ thuật / bảo mật | C81: P0 | D81: Phần mềm chạy trên tên miền/subdomain nào và ai chịu trách nhiệm quản trị máy chủ? | E81: A. Subdomain talunglogistics.com; B. Domain riêng; C. Chưa quyết. | F81: A | G81: hoặc vercel domain free | H81: Đã chốt | I81: Quản trị + CNTT | M81: Trao đổi nghiệp vụ Sơn Cảng, 10-11/10/2026 | N81: Chưa trả lời | O81: K01: ô lựa chọn thật sự để trống trong file V1, dù cột H được đánh dấu Đã chốt. Cần chọn tên miền/subdomain.
A82: K02 | B82: 08. Kỹ thuật / bảo mật | C82: P0 | D82: Cơ sở dữ liệu, backend, hosting chọn theo phương án nào? Có yêu cầu dữ liệu lưu tại Việt Nam không? | E82: A. Đề xuất Next.js + PostgreSQL; B. Hạ tầng đang có; C. Phương án khác (cần thẩm định). | F82: A | G82: công cụ free supabase, vercel | H82: Đã chốt | I82: CNTT + Ban quản lý | M82: Trao đổi nghiệp vụ Sơn Cảng, 10-11/10/2026 | N82: Đủ rõ để đặc tả | O82: Có lựa chọn được người dùng đánh dấu đã chốt; giữ nguyên câu trả lời và ghi chú.
A83: K03 | B83: 08. Kỹ thuật / bảo mật | C83: P0 | D83: Khi mất Internet tại cổng: cho phép nhập lượt xe offline nhưng chặn xác nhận xuất, hay cho phép xuất theo quy trình ngoại lệ? | E83: A. Offline chỉ nhập/đợi đồng bộ; B. Cho xuất ngoại lệ có chứng từ/TBP; C. Chỉ online. | F83: A | H83: Đã chốt | I83: CNTT + Trưởng BP An ninh + CCKB | M83: Trao đổi nghiệp vụ Sơn Cảng, 10-11/10/2026 | N83: Đủ rõ để đặc tả | O83: Có lựa chọn được người dùng đánh dấu đã chốt; giữ nguyên câu trả lời và ghi chú.
A84: K04 | B84: 08. Kỹ thuật / bảo mật | C84: P0 | D84: PWA dùng điện thoại cá nhân hay thiết bị công ty? Có yêu cầu camera chụp chứng từ/quét QR số container không? | E84: A. Điện thoại + PC; B. Thiết bị công ty; C. Cần đầu đọc/QR. | F84: A | G84: A và B | H84: Đã chốt | I84: CNTT + Các TBP | M84: Trao đổi nghiệp vụ Sơn Cảng, 10-11/10/2026 | N84: Cần làm rõ | O84: F=A, G=A và B: hỗ trợ điện thoại/PC và cả thiết bị công ty; cần phân biệt cấu hình ưu tiên.
A85: K05 | B85: 08. Kỹ thuật / bảo mật | C85: P1 | D85: Có cần bắt buộc đăng nhập 2 yếu tố với quản trị/TBP, phân quyền theo phiên đăng nhập/thiết bị không? | E85: A. 2FA cho TBP/Quản trị; B. Toàn bộ; C. SSO Google. | F85: Khác | G85: Chưa áp dụng nhưng có thì tốt | H85: Đã chốt | I85: CNTT | M85: Trao đổi nghiệp vụ Sơn Cảng, 10-11/10/2026 | N85: Cần làm rõ | O85: G: 2FA chưa áp dụng nhưng có thì tốt; cần ghi đúng là nâng cấp sau, không coi là bắt buộc V1.
A86: K06 | B86: 08. Kỹ thuật / bảo mật | C86: P1 | D86: Ảnh thu tiền và chứng từ cần lưu bao lâu, dung lượng giới hạn, ai có quyền xem/xóa? | E86: A. Theo thời hạn công ty; B. Tối thiểu 3 năm; C. Theo quy định cụ thể. | F86: A | G86: Chưa áp dụng, lưu trên đâu đó free, cloudflrae R2 10G | H86: Đã chốt | I86: CNTT + Kế toán | M86: Trao đổi nghiệp vụ Sơn Cảng, 10-11/10/2026 | N86: Cần làm rõ | O86: G: “chưa áp dụng”, muốn lưu rẻ/miễn phí, gợi ý Cloudflare R2 10GB; thời gian giữ file và quota còn mở.
A87: K07 | B87: 08. Kỹ thuật / bảo mật | C87: P1 | D87: Tần suất sao lưu, khôi phục sau sự cố và lưu bản sao dữ liệu ở đâu? | E87: A. Hằng ngày; B. Nhiều lần/ngày; C. Yêu cầu cụ thể. | F87: A | H87: Đã chốt | I87: CNTT | M87: Trao đổi nghiệp vụ Sơn Cảng, 10-11/10/2026 | N87: Đủ rõ để đặc tả | O87: Có lựa chọn được người dùng đánh dấu đã chốt; giữ nguyên câu trả lời và ghi chú.
A88: K08 | B88: 08. Kỹ thuật / bảo mật | C88: P1 | D88: Cần môi trường thử nghiệm và chính thức riêng biệt, đồng thời có nhật ký thao tác chi tiết không? | E88: A. Có cả hai + audit; B. Một môi trường; C. Lộ trình khác. | F88: A | H88: Đã chốt | I88: CNTT | M88: Trao đổi nghiệp vụ Sơn Cảng, 10-11/10/2026 | N88: Đủ rõ để đặc tả | O88: Có lựa chọn được người dùng đánh dấu đã chốt; giữ nguyên câu trả lời và ghi chú.
A89: K09 | B89: 08. Kỹ thuật / bảo mật | C89: P2 | D89: Giai đoạn đầu có cần tích hợp Zalo thông báo lệnh cắm/rút tự động không? | E89: A. Không, tiếp tục Zalo thủ công; B. Nhắc qua kênh khác; C. Tích hợp khi khả thi. | F89: A | G89: A B C | H89: Đã chốt | I89: CNTT + CCKB | M89: Trao đổi nghiệp vụ Sơn Cảng, 10-11/10/2026 | N89: Cần làm rõ | O89: F=A không gửi Zalo tự động trong V1 nhưng G “A B C”; cần tách thông báo PWA/gửi thủ công và tích hợp sau.
A90: M01 | B90: 09. Chuyển dữ liệu | C90: P0 | D90: Phạm vi chuyển dữ liệu AppSheet: toàn bộ lịch sử VEHICLE/CONTAINER hay chỉ bản ghi đang hoạt động + lưu kho lịch sử? | E90: A. Toàn bộ; B. Đang hoạt động + kho lưu lịch sử; C. Từ một mốc ngày. | F90: A | H90: Đã chốt | I90: CNTT + Các TBP | M90: Tập dữ liệu AppSheet do Sơn Cảng cung cấp | N90: Đủ rõ để đặc tả | O90: Có lựa chọn được người dùng đánh dấu đã chốt; giữ nguyên câu trả lời và ghi chú.
A91: M02 | B91: 09. Chuyển dữ liệu | C91: P0 | D91: Ngày/giờ chốt dữ liệu và đóng AppSheet để chuyển sang PWA là khi nào? | E91: A. Sau UAT; B. Chạy song song ngắn hạn; C. Cần kế hoạch chi tiết. | F91: A | H91: Đã chốt | I91: CNTT + Ban quản lý | M91: Trao đổi nghiệp vụ Sơn Cảng, 10-11/10/2026 | N91: Đủ rõ để đặc tả | O91: Có lựa chọn được người dùng đánh dấu đã chốt; giữ nguyên câu trả lời và ghi chú.
A92: M03 | B92: 09. Chuyển dữ liệu | C92: P0 | D92: Các dòng dữ liệu cũ có ghi chú tiền thực thu khác tiền phải thu: ai là người kiểm tra, xác nhận kết quả trước chuyển? | E92: A. TBP CCKB; B. Kế toán + CCKB; C. Nhóm đối soát liên BP. | F92: Khác | G92: Tiền thì tạm thời bỏ qua vò giờ trên hệ thống nhiều xe quên chưa cho ra lắ | H92: Đã chốt | I92: Trưởng BP CCKB + Kế toán | M92: CONTAINER V1: xem 08_DOI_SOAT | N92: Cần làm rõ | O92: G: tạm bỏ qua đối soát tài chính lịch sử do còn nhiều xe quên chốt ra; cần đánh dấu dữ liệu cũ chưa xác minh, không đưa vào công nợ V1.
A93: M04 | B93: 09. Chuyển dữ liệu | C93: P0 | D93: Giờ ra xe/container thực tế khác dữ liệu nhập do bổ sung muộn: dùng mốc nào làm dữ liệu gốc khi chuyển? | E93: A. Giờ hệ thống; B. Giờ trên chứng từ đã xác minh; C. Tùy từng dòng có xác nhận. | F93: A | G93: quan trị viên cấp cao có thể sửa trực tiếp hết nhé, vì hiện tại tôi thấy lỗi nhieuf chính trên GG sheets đang đễ sau này sửa thì vào db sửa lại khó hơn | H93: Đã chốt | I93: An ninh + CCKB + CNTT | M93: Dữ liệu VEHICLE/CONTAINER có ghi chú chỉnh ngày | N93: Cần làm rõ | O93: G: Quản trị cấp cao được sửa mọi dữ liệu sai, nhưng cần công cụ sửa trong app kèm audit, tránh sửa DB trực tiếp không lưu lịch sử.
A94: M05 | B94: 09. Chuyển dữ liệu | C94: P1 | D94: Mã ID cũ trong AppSheet cần giữ làm khóa tham chiếu hay chỉ lưu LEGACY_ID để tra cứu? | E94: A. Giữ ID cũ; B. Sinh ID mới và lưu LEGACY_ID; C. Khác. | F94: A | H94: Đã chốt | I94: CNTT | M94: Trao đổi nghiệp vụ Sơn Cảng, 10-11/10/2026 | N94: Đủ rõ để đặc tả | O94: Có lựa chọn được người dùng đánh dấu đã chốt; giữ nguyên câu trả lời và ghi chú.
A95: M06 | B95: 09. Chuyển dữ liệu | C95: P1 | D95: Tài khoản Google cũ cần phân sang 7 vai trò PWA như thế nào và có vô hiệu hóa tài khoản nào không? | E95: A. Map theo bảng 07_TAI_KHOAN; B. Tạo tài khoản mới; C. Kết hợp. | F95: B | H95: Đã chốt | I95: Quản trị + Các TBP | M95: Trao đổi nghiệp vụ Sơn Cảng, 10-11/10/2026 | N95: Đủ rõ để đặc tả | O95: Có lựa chọn được người dùng đánh dấu đã chốt; giữ nguyên câu trả lời và ghi chú.
A96: M07 | B96: 09. Chuyển dữ liệu | C96: P1 | D96: Các container cùng SO_CONTAINER xuất hiện ở nhiều lượt: muốn lưu lịch sử theo mỗi lượt hay hồ sơ container dùng lại nhiều lần? | E96: A. Hồ sơ container + lượt ra/vào; B. Mỗi lượt là một bản ghi; C. Thiết kế lai. | F96: A | H96: Đã chốt | I96: CNTT + Điều phối | M96: Trao đổi nghiệp vụ Sơn Cảng, 10-11/10/2026 | N96: Đủ rõ để đặc tả | O96: Có lựa chọn được người dùng đánh dấu đã chốt; giữ nguyên câu trả lời và ghi chú.
A97: M08 | B97: 09. Chuyển dữ liệu | C97: P1 | D97: Dữ liệu cắm điện AppSheet trước đây có nhập vào PWA cùng lúc không, hay triển khai riêng từ ngày vận hành mới? | E97: A. Chuyển toàn bộ; B. Chỉ phiên đang cắm/chưa thu; C. Bắt đầu mới và lưu lịch sử cũ. | F97: Khác | G97: CHưa có những sẽ chuyneenr 1 số cái tồn | H97: Đã chốt | I97: CNTT + CCKB | M97: Trao đổi nghiệp vụ Sơn Cảng, 10-11/10/2026 | N97: Cần làm rõ | O97: G: chưa có nhiều dữ liệu điện, sẽ chuyển một số phiên đang tồn; cần tiêu chí nhận diện các phiên phải chuyển.
A98: U01 | B98: 10. Nghiệm thu / triển khai | C98: P0 | D98: Ai đại diện mỗi bộ phận ký nghiệm thu và xác nhận nghiệp vụ chuẩn trước chuyển hệ thống? | E98: A. 3 TBP + CNTT; B. Có Ban quản lý/BLĐ; C. Tổ UAT chỉ định. | F98: Không áp dụng | H98: Đã chốt | I98: Ban quản lý Sơn Cảng | M98: Trao đổi nghiệp vụ Sơn Cảng, 10-11/10/2026 | N98: Cần làm rõ | O98: F=Không áp dụng nhóm ký nghiệm thu; U02 lại yêu cầu UAT trước ngừng AppSheet. Cần xác định ít nhất đầu mối duyệt nghiệm thu, không nhất thiết ký giấy.
A99: U02 | B99: 10. Nghiệm thu / triển khai | C99: P0 | D99: Điều kiện bắt buộc để ngừng AppSheet: chốt chuyển dữ liệu, đối soát tài chính, không lỗi chặn cổng ra, hoàn thành đào tạo? | E99: A. Tất cả; B. Tiêu chí chốt riêng; C. Theo giai đoạn. | F99: A | H99: Đã chốt | I99: Ban quản lý + CNTT | M99: Trao đổi nghiệp vụ Sơn Cảng, 10-11/10/2026 | N99: Đủ rõ để đặc tả | O99: Có lựa chọn được người dùng đánh dấu đã chốt; giữ nguyên câu trả lời và ghi chú.
A100: U03 | B100: 10. Nghiệm thu / triển khai | C100: P1 | D100: Nếu PWA gặp lỗi trong tuần đầu, quy trình quay lại AppSheet hoặc ghi giấy tạm thời và đồng bộ lại dữ liệu thế nào? | E100: A. Quy trình dự phòng bằng giấy; B. Tạm quay về AppSheet có kế hoạch hòa giải; C. Khác. | F100: A | H100: Đã chốt | I100: CNTT + An ninh + CCKB | M100: Trao đổi nghiệp vụ Sơn Cảng, 10-11/10/2026 | N100: Đủ rõ để đặc tả | O100: Có lựa chọn được người dùng đánh dấu đã chốt; giữ nguyên câu trả lời và ghi chú.
A101: U04 | B101: 10. Nghiệm thu / triển khai | C101: P1 | D101: Đào tạo nhân viên theo bộ phận, cần thao tác thử trước khi cấp quyền thật và phân công người hỗ trợ ca đêm không? | E101: A. Có đào tạo + UAT; B. Chỉ hướng dẫn nhanh; C. Kế hoạch riêng. | F101: A | H101: Đã chốt | I101: CNTT + Các TBP | M101: Trao đổi nghiệp vụ Sơn Cảng, 10-11/10/2026 | N101: Đủ rõ để đặc tả | O101: Có lựa chọn được người dùng đánh dấu đã chốt; giữ nguyên câu trả lời và ghi chú.
...

Sheet 02_DA_CHOT
A1: QUYẾT ĐỊNH ĐÃ XÁC NHẬN — BAO GỒM PHẢN HỒI V1
A2: Các mục còn cần điều kiện chi tiết được ghi rõ trong cột Quy tắc; không suy diễn là hoàn thành mọi phân quyền và ngoại lệ.
A4: STT | B4: Nhóm | C4: Quyết định đã xác nhận | D4: Giá trị / Quy tắc | E4: Trách nhiệm | F4: Trạng thái | G4: Nguồn xác nhận
A5: 1 | B5: Phạm vi | C5: PWA/Web thay thế AppSheet Sơn Cảng sau nghiệm thu | D5: V1 có kiểm soát cổng, container, phí và cắm điện | E5: CNTT / Các BP | F5: Đã chốt | G5: Trao đổi do Sơn Cảng xác nhận, tháng 10/2026
A6: 2 | B6: Phạm vi | C6: Xây phân hệ cắm điện container ngay trong V1 | D6: Dùng chung dữ liệu container và cơ chế thanh toán | E6: CCKB / An ninh | F6: Đã chốt | G6: Trao đổi do Sơn Cảng xác nhận, tháng 10/2026
A7: 3 | B7: Nghiệp vụ | C7: Xe/container quản lý tách lượt, có thể khác xe vào/xe ra | D7: Xe hạ container rồi ra; container tiếp tục ở trong bãi | E7: An ninh / Điều phối | F7: Đã chốt | G7: Trao đổi do Sơn Cảng xác nhận, tháng 10/2026
A8: 4 | B8: Nghiệp vụ | C8: Xe có container có thể ra cùng container hoặc hạ container | D8: Việc hạ không quyết định phát sinh phí lưu | E8: An ninh | F8: Đã chốt | G8: Trao đổi do Sơn Cảng xác nhận, tháng 10/2026
A9: 5 | B9: Thông tin xe | C9: Xe có mang container mới yêu cầu nhập SO_CONTAINER | D9: Loại xe bo không mang container không bị hỏi số container | E9: An ninh | F9: Đã chốt | G9: Trao đổi do Sơn Cảng xác nhận, tháng 10/2026
A10: 6 | B10: Thông tin xe | C10: Xe bo ba bánh không yêu cầu biển số xe | D10: Phí vé vào 40.000 đồng/lượt | E10: An ninh | F10: Đã chốt | G10: Trao đổi do Sơn Cảng xác nhận, tháng 10/2026
A11: 7 | B11: Vé xe | C11: Xe container lạnh vé vào 250.000 đồng/lượt | D11: Dùng mã CONT_LANH trong PRICE_LIST | E11: An ninh | F11: Đã chốt | G11: Trao đổi do Sơn Cảng xác nhận, tháng 10/2026
A12: 8 | B12: Vé xe | C12: Đầu kéo không container vé vào 0 đồng/lượt | D12: Dùng mã DAU_KEO trong PRICE_LIST mới | E12: An ninh | F12: Đã chốt | G12: Trao đổi do Sơn Cảng xác nhận, tháng 10/2026
A13: 9 | B13: Vé xe | C13: Xe bo 3 chân / 4 chân vé vào 200.000 đồng/lượt | D13: Dùng mã riêng theo PRICE_LIST | E13: An ninh | F13: Đã chốt | G13: Trao đổi do Sơn Cảng xác nhận, tháng 10/2026
A14: 10 | B14: Vé xe | C14: Xe bo 8 tấn/2 chân vé vào 100.000 đồng/lượt | D14: Dùng mã XE_BO_8_TAN_2_CHAN | E14: An ninh | F14: Đã chốt | G14: Trao đổi do Sơn Cảng xác nhận, tháng 10/2026
A15: 11 | B15: Vé xe | C15: Xe sang tải (tạp) vé vào 0 đồng/lượt | D15: Dùng mã XE_SANG_TAI | E15: An ninh | F15: Đã chốt | G15: Trao đổi do Sơn Cảng xác nhận, tháng 10/2026
A16: 12 | B16: Lưu container | C16: Phí lưu tính theo CONTAINER, không phải lưu XE | D16: Bắt đầu GIO_CONT_VAO, kết thúc GIO_CONT_RA | E16: CCKB | F16: Đã chốt | G16: Trao đổi do Sơn Cảng xác nhận, tháng 10/2026
... A55: 51 | B55: Hóa đơn | C55: Bước tiếp nhận vé cần lưu thông tin khách/lái xe phục vụ hóa đơn | D55: Yêu cầu công nợ/hóa đơn tích hợp Kế toán dự kiến triển khai giai đoạn sau | E55: An ninh + Kế toán | F55: Đã chốt phần nguyên tắc | G55: V1 đã trả lời: T12 (G)

Sheet 03_BANG_GIA
A1: BẢNG GIÁ HIỆN HÀNH VÀ DÒNG GIÁ BỔ SUNG
A2: Giữ nguyên 8 dòng PRICE_LIST do Sơn Cảng cung cấp; bổ sung 2 mã cắm điện và 1 mã phạt mất vé để chuẩn hóa, cần xác nhận mã mới.
A4: MA_LOAI | B4: TEN_LOAI | C4: DOI_TUONG | D4: LOAI_PHI | E4: DON_GIA (VND) | F4: DON_VI_TINH | G4: MOC_BAT_DAU | H4: MOC_KET_THUC | I4: SO_DEM_MIEN_PHI | J4: HOAT_DONG | K4: THU_TU | L4: GHI_CHU | M4: Nguồn | N4: Phê duyệt mã thêm | O4: Ghi chú cập nhật (điền)
A5: CONT_LANH | B5: Xe container lạnh | C5: Phương tiện | D5: Vé vào | E5: 250000 | F5: Lượt | I5: 0 | J5: TRUE | K5: 1 | L5: Thu vé khi xe vào có kéo container | M5: PRICE_LIST gốc | N5: Đã xác nhận
A6: DAU_KEO | B6: Đầu kéo không container | C6: Phương tiện | D6: Vé vào | E6: 0 | F6: Lượt | I6: 0 | J6: TRUE | K6: 2 | L6: Thu vé khi đầu kéo vào không có container | M6: PRICE_LIST gốc | N6: Đã xác nhận
A7: XE_BO_4_CHAN | B7: Xe bo 4 chân | C7: Phương tiện | D7: Vé vào | E7: 200000 | F7: Lượt | I7: 0 | J7: TRUE | K7: 3 | L7: Thu tiền vé khi xe vào | M7: PRICE_LIST gốc | N7: Đã xác nhận
A8: XE_BO_3_CHAN | B8: Xe bo 3 chân | C8: Phương tiện | D8: Vé vào | E8: 200000 | F8: Lượt | I8: 0 | J8: TRUE | K8: 4 | L8: Thu tiền vé khi xe vào | M8: PRICE_LIST gốc | N8: Đã xác nhận
A9: XE_BO_8_TAN_2_CHAN | B9: Xe bo 8 tấn/2 chân | C9: Phương tiện | D9: Vé vào | E9: 100000 | F9: Lượt | I9: 0 | J9: TRUE | K9: 5 | L9: Thu tiền vé khi xe vào | M9: PRICE_LIST gốc | N9: Đã xác nhận
A10: XE_BO_3_BANH | B10: Xe bo 3 bánh | C10: Phương tiện | D10: Vé vào | E10: 40000 | F10: Lượt | I10: 0 | J10: TRUE | K10: 6 | L10: Thu tiền vé khi xe vào; không yêu cầu biển số | M10: PRICE_LIST gốc | N10: Đã xác nhận
A11: XE_SANG_TAI | B11: Xe sang tải (tạp) | C11: Phương tiện | D11: Vé vào | E11: 0 | F11: Lượt | I11: 0 | J11: TRUE | K11: 7 | L11: Miễn phí, chỉ kiểm soát xe ra vào | M11: PRICE_LIST gốc | N11: Đã xác nhận
A12: LUU_CONTAINER | B12: Phí lưu container | C12: Container | D12: Lưu đêm | E12: 100000 | F12: Đêm | G12: 22:00 | H12: 06:00 | I12: 1 | J12: TRUE | K12: 8 | L12: Phí lưu bằng (số đêm trừ một) nhân 100.000; kể cả không hạ cont | M12: PRICE_LIST gốc + chốt sau | N12: Đã xác nhận
A13: DIEN_CONT_GIO | B13: Cắm điện theo giờ | C13: Container | D13: Cắm điện | E13: 100000 | F13: Giờ | I13: 0 | J13: TRUE | K13: 9 | L13: Làm tròn lên từng 15 phút; CCKB nhập giờ thực tế | M13: Bổ sung theo chốt mới | N13: Mã đề xuất cần duyệt
A14: DIEN_CONT_LIEN_TUC | B14: Cắm điện liên tục | C14: Container | D14: Cắm điện | E14: 100000 | F14: Giờ | I14: 0 | J14: TRUE | K14: 10 | L14: Làm tròn lên từng 15 phút; CCKB nhập giờ thực tế | M14: Bổ sung theo chốt mới | N14: Mã đề xuất cần duyệt
A15: PHAT_MAT_VE | B15: Phạt mất liên 02 vé xe | C15: Vé xe | D15: Phạt | E15: 250000 | F15: Trường hợp | I15: 0 | J15: TRUE | K15: 11 | L15: Mức tiền theo thông báo; người trực tiếp thu còn cần chốt | M15: Bổ sung từ thông báo | N15: Mã đề xuất cần duyệt

Sheet 17_DE_XUAT_PHAN_QUYEN
A1: MA TRẬN QUYỀN ĐỀ XUẤT — PWA SƠN CẢNG
A2: BẢN THẨM ĐỊNH: cột E–K là quyền khuyến nghị; mọi phần khác biệt được tô vàng. Tab 04_PHAN_QUYEN giữ nguyên câu trả lời của bạn.
A3: Ký hiệu quyền: Thực hiện = thao tác; Xem = xem trong phạm vi; Đề nghị = gửi yêu cầu; Phê duyệt = quyết định; Không = không truy cập. CHƯA PHẢI QUYỀN ĐÃ DUYỆT.
A4: Mã | B4: Nhóm | C4: Chức năng / thao tác | D4: Bộ phận trách nhiệm đã chốt | E4: NV An ninh | F4: TBP An ninh | G4: NV CCKB | H4: TBP CCKB | I4: NV Điều phối | J4: TBP Điều phối | K4: Quản trị | L4: Ghi chú cần xác nhận (điền) | M4: Trạng thái | N4: Đánh giá | O4: Giải pháp / điều kiện an toàn | P4: Thay đổi cột | Q4: Mức ưu tiên
A5: Q01 | B5: Cổng vào | C5: Tạo lượt xe vào và giờ vào | D5: An ninh | E5: Thực hiện | F5: Thực hiện | G5: Không | H5: Không | I5: Không | J5: Không | K5: Thực hiện | M5: Đã chốt | N5: Giữ nguyên đề xuất của bạn | O5: Giữ như bản bạn điền; vẫn phải triển khai RBAC phía server, không chỉ ẩn nút trên giao diện. | P5: Không đổi giá trị | Q5: P2
A6: Q02 | B6: Cổng vào | C6: Thu tiền vé vào, đính kèm ảnh chuyển khoản | D6: An ninh | E6: Thực hiện | F6: Thực hiện | G6: Không | H6: Không | I6: Không | J6: Không | K6: Thực hiện | M6: Đã chốt | N6: Giữ nguyên đề xuất của bạn | O6: Giữ như bản bạn điền; vẫn phải triển khai RBAC phía server, không chỉ ẩn nút trên giao diện. | P6: Không đổi giá trị | Q6: P2
A7: Q03 | B7: Cổng vào | C7: Sửa biển số / loại xe / GIO_VAO | D7: An ninh | E7: Thực hiện | F7: Thực hiện | G7: Xem | H7: Xem | I7: Xem | J7: Xem | K7: Thực hiện | M7: Tách thao tác / chờ duyệt | N7: Tách thao tác / chờ duyệt | O7: Tách sửa biển số, loại xe và GIO_VAO thành các quyền riêng. Trước khi xuất cho An ninh sửa có audit; sau khi đã thu/đã xuất phải kiểm tra ảnh hưởng phí và cho TBP xử lý. Không tự sửa chứng từ đã thu. | P7: Không đổi giá trị | Q7: P0
A8: Q04 | B8: Cổng vào | C8: Tạo/điều chỉnh số vé giấy | D8: Chưa triển khai V1 | E8: Không | F8: Không | G8: Không | H8: Không | I8: Không | J8: Không | K8: Không | M8: Đề xuất hoãn V1 | N8: Đề xuất hoãn V1 | O8: Bạn ghi hiện chưa dùng chỉnh số vé giấy; do đó tắt thao tác thay đổi số vé giấy ở V1. Nếu cần vẫn có thể nhập số vé tham chiếu tùy chọn, không cấp quyền sửa tùy ý. | P8: D, E, F, G, H, I, J, K | Q8: P2
A9: Q05 | B9: Container | C9: Tạo lượt container vào, ghi GIO_CONT_VAO | D9: An ninh | E9: Thực hiện | F9: Thực hiện | G9: Không | H9: Không | I9: Không | J9: Không | K9: Thực hiện | M9: Đã chốt | N9: Giữ nguyên đề xuất của bạn | O9: Giữ như bản bạn điền; vẫn phải triển khai RBAC phía server, không chỉ ẩn nút trên giao diện. | P9: Không đổi giá trị | Q9: P2
A10: Q06 | B10: Container | C10: Thay đổi số container sau khi lưu | D10: An ninh | E10: Thực hiện | F10: Thực hiện | G10: Xem | H10: Xem | I10: Xem | J10: Xem | K10: Thực hiện | L10: Đã xác nhận cấp quyền cho An ninh sửa số cont và báo CCKB. Các ngoại lệ đã thanh toán/đã xuất vẫn cần chốt. | M10: Giữ quyền, bổ sung điều kiện | N10: Giữ quyền, bổ sung điều kiện | O10: Giữ quyền sửa số cont cho An ninh như bạn chọn; bắt buộc ghi số trước/sau, lý do, người sửa, giờ sửa và tự gửi cảnh báo tới CCKB. Nếu đã thu thì giữ giao dịch cũ; thay đổi số cont không tự động thay tiền. | P10: Không đổi giá trị | Q10: P0
A11: Q07 | B11: Container | C11: Xác nhận hạ/xếp container (quản lý vị trí) | D11: An ninh | E11: Thực hiện | F11: Thực hiện | G11: Xem | H11: Xem | I11: Thực hiện | J11: Thực hiện | K11: Thực hiện | M11: Giữ quyền, bổ sung điều kiện | N11: Giữ quyền, bổ sung điều kiện | O11: Nghiệp vụ hạ/xếp/vị trí là thông tin vận hành, không phải điều kiện tính phí lưu. Nếu chưa áp dụng kiểm soát vị trí trong V1, ẩn phần vị trí; vẫn lưu trạng thái xe ra không container. | P11: Không đổi giá trị | Q11: P2
A12: Q08 | B12: Điều phối | C12: Cập nhật HÀNG/RỖNG | D12: Điều phối | E12: Xem | F12: Xem | G12: Xem | H12: Xem | I12: Thực hiện | J12: Thực hiện | K12: Thực hiện | M12: Đề xuất sửa quyền | N12: Đề xuất sửa quyền | O12: Chỉ Điều phối nhập HÀNG/RỖNG; An ninh xem để đối chiếu. Tránh 2 bộ phận cập nhật chéo làm mất nguồn dữ liệu chuẩn. | P12: E, F | Q12: P0
A13: Q09 | B13: Điều phối | C13: Sửa HÀNG/RỖNG sau khi đã ra | D13: Điều phối | E13: Xem | F13: Xem | G13: Xem | H13: Xem | I13: Đề nghị | J13: Phê duyệt | K13: Thực hiện | M13: Đề xuất sửa quyền | N13: Đề xuất sửa quyền | O13: Sau khi container đã xuất: NV Điều phối chỉ đề nghị sửa; TBP Điều phối/Quản trị duyệt, ghi nhật ký trước/sau. Nếu chỉ sửa chú thích không ảnh hưởng phí thì có thể đơn giản hóa. | P13: E, F, I, J | Q13: P1
A14: Q10 | B14: Cắm điện | C14: Tạo yêu cầu cắm/rút từ khách hàng | D14: CCKB | E14: Xem | F14: Xem | G14: Thực hiện | H14: Thực hiện | I14: Xem | J14: Xem | K14: Thực hiện | M14: Đã chốt | N14: Giữ nguyên đề xuất của bạn | O14: Giữ như bản bạn điền; vẫn phải triển khai RBAC phía server, không chỉ ẩn nút trên giao diện. | P14: Không đổi giá trị | Q14: P2
A15: Q11 | B15: Cắm điện | C15: Thực hiện cắm/rút điện tại hiện trường | D15: An ninh | E15: Thực hiện | F15: Thực hiện | G15: Xem | H15: Xem | I15: Xem | J15: Xem | K15: Thực hiện | M15: Đề xuất sửa quyền | N15: Đề xuất sửa quyền | O15: Thao tác cắm/rút PHYSICAL chỉ An ninh thực hiện. CCKB tiếp nhận thông báo qua Zalo, sau đó nhập giờ tại Q12/Q13. Không bắt buộc An ninh nhập giờ trên PWA. | P15: G, H | Q15: P0
A16: Q12 | B16: Cắm điện | C16: Nhập GIO_CAM_THUC_TE | D16: CCKB | E16: Xem | F16: Xem | G16: Thực hiện | H16: Thực hiện | I16: Xem | J16: Xem | K16: Thực hiện | M16: Đã chốt | N16: Giữ nguyên đề xuất của bạn | O16: Giữ như bản bạn điền; vẫn phải triển khai RBAC phía server, không chỉ ẩn nút trên giao diện. | P16: Không đổi giá trị | Q16: P2
A17: Q13 | B17: Cắm điện | C17: Nhập GIO_RUT_THUC_TE | D17: CCKB | E17: Xem | F17: Xem | G17: Thực hiện | H17: Thực hiện | I17: Xem | J17: Xem | K17: Thực hiện | M17: Đã chốt | N17: Giữ nguyên đề xuất của bạn | O17: Giữ như bản bạn điền; vẫn phải triển khai RBAC phía server, không chỉ ẩn nút trên giao diện. | P17: Không đổi giá trị | Q17: P2
A18: Q14 | B18: Cắm điện | C18: Sửa giờ cắm/rút trước khi thu | D18: CCKB | E18: Xem | F18: Xem | G18: Thực hiện | H18: Thực hiện | I18: Xem | J18: Xem | K18: Thực hiện | M18: Giữ quyền, bổ sung điều kiện | N18: Giữ quyền, bổ sung điều kiện | O18: CCKB sửa giờ cắm/rút trước thu, hệ thống tính lại từng phiên bằng CEILING(số phút/15)*15; bắt buộc audit khi đã lưu trước đó. | P18: Không đổi giá trị | Q18: P1
A19: Q15 | B19: Cắm điện | C19: Đề nghị sửa giờ sau khi đã thu | D19: CCKB | E19: Xem | F19: Xem | G19: Đề nghị | H19: Đề nghị | I19: Xem | J19: Xem | K19: Thực hiện | M19: Đề xuất sửa quyền | N19: Đề xuất sửa quyền | O19: Nhân viên/TBP CCKB đề nghị điều chỉnh sau thu; Trưởng BP có quyền phê duyệt theo Q16. Không ghi đè trực tiếp khoản đã thanh toán. | P19: G, H | Q19: P0
A20: Q16 | B20: Cắm điện | C20: Phê duyệt chênh lệch sau khi thu | D20: TBP CCKB / Quản trị | E20: Xem | F20: Xem | G20: Xem | H20: Phê duyệt | I20: Xem | J20: Xem | K20: Phê duyệt | M20: Đề xuất sửa quyền | N20: Đề xuất sửa quyền | O20: Chỉ TBP CCKB hoặc Quản trị phê duyệt chênh lệch sau đã thu; người vừa đề nghị KHÔNG tự duyệt. Nếu TBP tự chỉnh thì cần giải trình/audit. Bút toán chênh lệch/hoàn tiền giữ nguyên chứng từ gốc. | P20: D, G, H, K | Q20: P0
A21: Q17 | B21: Cắm điện | C21: Quản lý danh mục giá điện và ngày hiệu lực | D21: Quản trị | E21: Xem | F21: Xem | G21: Xem | H21: Xem | I21: Xem | J21: Xem | K21: Thực hiện | M21: Đã chốt | N21: Giữ nguyên đề xuất của bạn | O21: Giữ như bản bạn điền; vẫn phải triển khai RBAC phía server, không chỉ ẩn nút trên giao diện. | P21: Không đổi giá trị | Q21: P2
A22: Q18 | B22: Thanh toán | C22: Tính/thu phí lưu container | D22: An ninh | E22: Thực hiện | F22: Thực hiện | G22: Xem | H22: Xem | I22: Xem | J22: Xem | K22: Thực hiện | M22: Giữ quyền, bổ sung điều kiện | N22: Giữ quyền, bổ sung điều kiện | O22: An ninh thu PHÍ LƯU CONTAINER đúng lúc GIO_CONT_RA thực tế được xác nhận, không khóa phí trước 22:00. Nếu chưa thu, phải ghi rõ nợ/ngoại lệ và kiểm tra quyền cho ra. | P22: Không đổi giá trị | Q22: P0
... A34: Q30 | B34: Báo cáo | C34: Xuất Excel/báo cáo phục vụ kiểm toán | D34: Quản trị (toàn bộ) / TBP (bộ phận) | E34: Không | F34: Thực hiện | G34: Không | H34: Thực hiện | I34: Không | J34: Không | K34: Thực hiện | M34: Đề xuất sửa quyền | N34: Đề xuất sửa quyền | O34: Cho TBP An ninh/CCKB xuất báo cáo thuộc BP để bàn giao đối soát. Báo cáo kiểm toán toàn bộ dữ liệu chỉ Quản trị. | P34: D, F, H | Q34: P2
A35: Q31 | B35: Cắm điện dự kiến | C35: Tạo yêu cầu cắm điện cho cont chưa vào (một hoặc nhiều số) | D35: CCKB | E35: Xem | F35: Xem | G35: Thực hiện | H35: Thực hiện | I35: Xem | J35: Xem | K35: Thực hiện | L35: Đề xuất NV/TBP CCKB thực hiện; chưa chốt chi tiết vai trò. | M35: Đề xuất sửa quyền | N35: Đề xuất sửa quyền | O35: CCKB nhập yêu cầu cho từng cont trước khi cont đến; An ninh phải nhìn thấy yêu cầu chờ để nhận diện lúc vào. Chưa có cont visit thì không tính phí lưu. | P35: E, F, G, H, I, J | Q35: P0
A36: Q32 | B36: Cắm điện dự kiến | C36: Sửa hoặc hủy yêu cầu điện dự kiến khi khách đổi số cont | D36: CCKB | E36: Xem | F36: Xem | G36: Thực hiện | H36: Thực hiện | I36: Xem | J36: Xem | K36: Thực hiện | L36: Cần chốt quyền, lưu lịch sử và thông báo An ninh. | M36: Đề xuất sửa quyền | N36: Đề xuất sửa quyền | O36: CCKB sửa/hủy yêu cầu dự kiến khi KH báo nhầm; phải lưu lịch sử và gửi thông báo lại An ninh. Không xóa mất bằng chứng đã nhận từ khách. | P36: E, F, G, H, I, J | Q36: P0
A37: Q33 | B37: Cổng vào | C37: Xem cảnh báo danh sách cont có yêu cầu cắm điện dự kiến | D37: An ninh | E37: Xem | F37: Xem | G37: Xem | H37: Xem | I37: Không | J37: Không | K37: Thực hiện | L37: Đã chốt An ninh cần nhìn thấy khi nhập container. | M37: Đề xuất sửa quyền | N37: Đề xuất sửa quyền | O37: An ninh phải THẤY cảnh báo cont có yêu cầu cắm điện dự kiến khi nhập tại cổng. Không chờ Quản trị mới xem được. | P37: E, F, G, H, I, J | Q37: P0
A38: Q34 | B38: Cổng vào | C38: Xác nhận ghép số cont dự kiến với lượt cont vào thực tế | D38: An ninh + CCKB | E38: Thực hiện | F38: Thực hiện | G38: Thực hiện | H38: Thực hiện | I38: Xem | J38: Xem | K38: Thực hiện | L38: Quy tắc ghép tự động/thủ công chưa chốt. | M38: Đề xuất sửa quyền | N38: Đề xuất sửa quyền | O38: An ninh đối chiếu cont thực vào với danh sách dự kiến và xác nhận ghép; CCKB kiểm tra/chỉnh phiếu theo kết quả. Gợi ý 7 số cuối/gần giống chỉ hỗ trợ, KHÔNG tự ghép. | P38: E, F, G, H, I, J | Q38: P0
A39: Q35 | B39: Container | C39: Sửa số cont đã nhập sai và ghi nhận đã báo CCKB | D39: An ninh | E39: Thực hiện | F39: Thực hiện | G39: Xem | H39: Xem | I39: Xem | J39: Xem | K39: Thực hiện | L39: Đã chốt bộ phận; cần quy định khi đã thu tiền. | M39: Đề xuất sửa quyền | N39: Đề xuất sửa quyền | O39: Tương đồng Q06: giữ AN được sửa đúng cont tại hiện trường và bấm Đã báo CCKB; số cũ, số mới, ảnh/video nếu có, lý do và audit bắt buộc. Nên gộp chức năng với Q06 trong UI. | P39: E, F, G, H, I, J | Q39: P0
A40: Q36 | B40: Container | C40: Tiếp nhận cảnh báo sửa số cont, kiểm tra và cập nhật yêu cầu dự kiến | D40: CCKB | E40: Xem | F40: Xem | G40: Thực hiện | H40: Thực hiện | I40: Xem | J40: Xem | K40: Thực hiện | L40: Quy trình xác nhận và phương thức báo lại cần chốt. | M40: Đề xuất sửa quyền | N40: Đề xuất sửa quyền | O40: CCKB tiếp nhận cảnh báo AN sửa số cont và được cập nhật phiếu dự kiến; lưu trạng thái đã xem/đã xử lý. Không tạo thêm phiên mới ngoài ý muốn. | P40: E, F, G, H, I, J | Q40: P0
A41: Q37 | B41: Chứng cứ | C41: Đính kèm ảnh/video nhận diện sai số container | D41: An ninh / CCKB | E41: Thực hiện | F41: Thực hiện | G41: Thực hiện | H41: Thực hiện | I41: Xem | J41: Xem | K41: Thực hiện | L41: Cần chốt bắt buộc hay không, kích thước và lưu trữ. | M41: Đề xuất sửa quyền | N41: Đề xuất sửa quyền | O41: AN hoặc CCKB được đính kèm ảnh/video đối chiếu. Khuyến khích ảnh/video; khi không có phải có lý do, không chặn thao tác nếu nguồn thực tế không cho chụp. | P41: E, F, G, H, I, J | Q41: P0
A42: Q38 | B42: Ngoại lệ | C42: Đối soát chênh lệch tiền sau khi sửa số container đã thu/đã ra | D42: TBP CCKB / Quản trị | E42: Xem | F42: Xem | G42: Đề nghị | H42: Phê duyệt | I42: Xem | J42: Xem | K42: Phê duyệt | L42: Không được tự động đổi lịch sử khoản thu đã chốt. | M42: Đề xuất tách nghiệp vụ | N42: Đề xuất tách nghiệp vụ | O42: SỬA MÃ CONTAINER luôn theo Q06/Q35 (AN được sửa có nhật ký). Q38 chỉ dùng khi phải ĐIỀU CHỈNH TIỀN đã thu do sửa số; cần TBP CCKB/Quản trị duyệt giao dịch điều chỉnh, không thay khoản đã thu gốc. | P42: C, D, E, F, G, H, I, J, K | Q42: P0
A43: Q39 | B43: Đối soát | C43: Xem và xác nhận đã xử lý cảnh báo sai số cont/không ghép được yêu cầu dự kiến | D43: CCKB + An ninh | E43: Thực hiện | F43: Thực hiện | G43: Thực hiện | H43: Thực hiện | I43: Xem | J43: Xem | K43: Thực hiện | L43: Cần trạng thái giao việc và phản hồi đóng thông báo. | M43: Đề xuất sửa quyền | N43: Đề xuất sửa quyền | O43: An ninh ghi đã báo/chụp hiện trường; CCKB đánh dấu đã kiểm tra/đối soát và đóng cảnh báo; trạng thái riêng từng BP, ai hoàn tất thao tác của mình. | P43: E, F, G, H, I, J | Q43: P0

Sheet 18_KET_LUAN_RUI_RO
A1: KẾT LUẬN THẨM ĐỊNH — BẢN PHÂN QUYỀN BẠN ĐÃ ĐIỀN
A2: ĐÁNH GIÁ: Cơ cấu 3 bộ phận đúng; cần sửa những quyền đang nhầm người, những thao tác admin-only và quyền tài chính nhạy cảm trước khi dùng làm mã nguồn.
A3: Bản gốc ở 04_PHAN_QUYEN; quyền sửa đề xuất ở 17_DE_XUAT_PHAN_QUYEN. Chưa tự ý xác nhận thay người dùng.
A5: STT | B5: Mã liên quan | C5: Mức | D5: Nhận xét kiểm tra | E5: Rủi ro nếu giữ nguyên | F5: Hướng xử lý khuyến nghị | G5: Loại quyết định | H5: Trạng thái rà soát
A6: 1 | B6: Q31–Q39 | C6: P0 | D6: 9 chức năng mới chỉ có Quản trị được thao tác; NV/TBP An ninh và CCKB để trống. | E6: Nghiệp vụ điện dự kiến và báo sai số cont không hoạt động đúng thực tế. | F6: Giao quyền tạo/sửa phiếu dự kiến cho CCKB; AN xem cảnh báo, xác nhận ghép và sửa số cont; CCKB tiếp nhận cảnh báo; AN/CCKB đính kèm bằng chứng. | G6: BẮT BUỘC SỬA | H6: Đề xuất / chờ duyệt
A7: 2 | B7: Q08–Q09 | C7: P0 | D7: An ninh được sửa trạng thái HÀNG/RỖNG, kể cả khi cont đã ra. | E7: Không còn một bộ phận sở hữu dữ liệu chuẩn; khó điều tra sai trạng thái. | F7: Điều phối nhập và chịu trách nhiệm; An ninh/CCKB xem; sửa sau khi ra phải có TBP phê duyệt/audit. | G7: BẮT BUỘC SỬA | H7: Đề xuất / chờ duyệt
A8: 3 | B8: Q11, Q12–Q13 | C8: P0 | D8: CCKB được ghi “Thực hiện cắm/rút điện tại hiện trường”. | E8: Trộn người thực hiện thực tế với người nhập giờ vào ứng dụng. | F8: An ninh trực tiếp cắm/rút; CCKB chỉ ghi giờ và quản lý tiền theo thông tin An ninh báo. | G8: BẮT BUỘC SỬA | H8: Đề xuất / chờ duyệt
A9: 4 | B9: Q15–Q16 | C9: P0 | D9: Nhân viên CCKB vừa được đề nghị vừa được phê duyệt chênh lệch sau thu. | E9: Có thể tự sửa giảm tiền đã thu mà không có kiểm tra độc lập. | F9: NV CCKB gửi đề nghị; TBP CCKB/Quản trị phê duyệt. Giữ bút toán tiền gốc và ghi chênh lệch. | G9: BẮT BUỘC SỬA | H9: Đề xuất / chờ duyệt
A10: 5 | B10: Q03,Q06,Q35,Q38 | C10: P0 | D10: Sửa giờ vào/số cont vẫn quá rộng; Q38 chồng chéo quyền sửa số cont và chỉnh tiền. | E10: Tiền lưu, tiền điện, lịch sử container và giao dịch đã thu có thể sai. | F10: Giữ AN quyền sửa số cont có audit/báo CCKB. Khi chỉnh tiền đã thu, TBP CCKB duyệt riêng; tách quyền sửa giờ ra/vào sau khi thu. | G10: BẮT BUỘC SỬA | H10: Đề xuất / chờ duyệt
A11: 6 | B11: Q18,Q24–Q25 | C11: P0 | D11: CCKB duyệt tài chính trước, trong khi AN chỉ tính phí lưu khi ghi giờ cont ra thật. | E11: Xuất container khi chưa ghi nhận/thu phí lưu phát sinh ở cổng. | F11: CCKB duyệt tiền điện + cảnh báo nợ; AN nhập giờ ra thật, tính/thu lưu; hệ thống kiểm tra thu hoặc ngoại lệ rồi mới ghi nhận ra. | G11: CẦN ĐIỀU KIỆN | H11: Áp dụng quy trình hai bước
A12: 7 | B12: Q26 | C12: P1 | D12: NV CCKB có thể hủy duyệt ra không tách trước/sau khi đã thực tế xuất. | E12: Lịch sử duyệt ra và công nợ có thể mâu thuẫn trạng thái cổng. | F12: Trước khi AN xác nhận ra: NV đề nghị, TBP/Quản trị hủy; sau khi ra: chỉ lập nghiệp vụ điều chỉnh có lịch sử. | G12: NÊN SỬA | H12: Đề xuất / chờ duyệt
A13: 8 | B13: Q28–Q30 | C13: P1 | D13: TBP An ninh và CCKB không được xem nhật ký, báo cáo doanh thu và xuất báo cáo. | E13: Không chủ động giám sát ca, đối soát hoặc điều tra sai sót. | F13: Cấp quyền theo phạm vi bộ phận; nhân viên chỉ xem khoản của mình; Quản trị được xem toàn bộ. | G13: NÊN SỬA | H13: Đề xuất / chờ duyệt
A14: 9 | B14: Q21 | C14: P1 | D14: Chỉ Quản trị được đối soát chứng từ chuyển khoản; người trực thu không tham gia quy trình kiểm tra. | E14: Mất khả năng giám sát tiền thực nhận hằng ngày tại An ninh/CCKB. | F14: TBP mỗi bộ phận đối soát các khoản thuộc phạm vi, có thể kết nối Kế toán ở giai đoạn sau. | G14: NÊN SỬA | H14: Đề xuất / chờ duyệt
A15: 10 | B15: Q04 | C15: P2 | D15: Không gán quyền nào và ghi “không sử dụng chỉnh vé giấy”, nhưng trạng thái vẫn “Đã chốt”. | E15: Nhóm lập trình có thể hiểu vẫn phải xây thao tác chỉnh vé giấy ngay V1. | F15: Gắn nhãn “Không triển khai V1”; chỉ lưu số vé nếu thực tế có, chức năng in/QR sau. | G15: GHI RÕ PHẠM VI | H15: Đề xuất / chờ duyệt
A16: 11 | B16: 15_V4_DIEM_CAN_KIEM | C16: P1 | D16: 12 điểm rà soát V4 chưa được bạn điền kết luận. | E16: Một số quy tắc kỹ thuật quan trọng vẫn là đề xuất. | F16: Ưu tiên RV03 giá điện đổi giữa phiên, RV05 điện đang cắm nhưng thực tế rút, RV06 phí lưu chưa thu, RV09 tài khoản chung bốt. | G16: CHƯA ĐỦ UAT | H16: Mở trong giai đoạn thiết kế
A17: 12 | B17: 14_V4_KICH_BAN | C17: P1 | D17: 44 kịch bản UAT vẫn ghi Chưa kiểm thử, chưa có kết quả chạy thực tế. | E17: Chưa có chứng cứ kiểm thử PWA hoặc nghiệm thu thay AppSheet. | F17: Sau khi có bản demo, chạy các kịch bản P0 trước; hiện chỉ có bảng yêu cầu và phân quyền. | G17: CHƯA ĐỦ UAT | H17: Để lúc có phần mềm

Sheet 04_PHAN_QUYEN
A1: MA TRẬN QUYỀN THEO 07 VAI TRÒ — CẦN XÁC NHẬN
A2: Các cột quyền đang để trống vì đã chốt TRÁCH NHIỆM BỘ PHẬN nhưng chưa chốt từng quyền. Chọn Thực hiện / Xem / Phê duyệt / Không.
A4: Mã | B4: Nhóm | C4: Chức năng / thao tác | D4: Bộ phận trách nhiệm đã chốt | E4: NV An ninh | F4: TBP An ninh | G4: NV CCKB | H4: TBP CCKB | I4: NV Điều phối | J4: TBP Điều phối | K4: Quản trị | L4: Ghi chú cần xác nhận (điền) | M4: Trạng thái
A5: Q01 | B5: Cổng vào | C5: Tạo lượt xe vào và giờ vào | D5: An ninh | E5: Thực hiện | F5: Thực hiện | G5: Không | H5: Không | I5: Không | J5: Không | K5: Thực hiện | M5: Đã chốt
A6: Q02 | B6: Cổng vào | C6: Thu tiền vé vào, đính kèm ảnh chuyển khoản | D6: An ninh | E6: Thực hiện | F6: Thực hiện | G6: Không | H6: Không | I6: Không | J6: Không | K6: Thực hiện | M6: Đã chốt
A7: Q03 | B7: Cổng vào | C7: Sửa biển số / loại xe / GIO_VAO | D7: An ninh | E7: Thực hiện | F7: Thực hiện | G7: Xem | H7: Xem | I7: Xem | J7: Xem | K7: Thực hiện | M7: Đã chốt
A8: Q04 | B8: Cổng vào | C8: Tạo/điều chỉnh số vé giấy | D8: An ninh | M8: Đã chốt | N8: k sử dụng điều chỉnh vé giấy mjes
A9: Q05 | B9: Container | C9: Tạo lượt container vào, ghi GIO_CONT_VAO | D9: An ninh | E9: Thực hiện | F9: Thực hiện | G9: Không | H9: Không | I9: Không | J9: Không | K9: Thực hiện | M9: Đã chốt
A10: Q06 | B10: Container | C10: Thay đổi số container sau khi lưu | D10: An ninh | E10: Thực hiện | F10: Thực hiện | G10: Xem | H10: Xem | I10: Xem | J10: Xem | K10: Thực hiện | L10: Đã xác nhận cấp quyền cho An ninh sửa số cont và báo CCKB. Các ngoại lệ đã thanh toán/đã xuất vẫn cần chốt. | M10: Đã chốt
A11: Q07 | B11: Container | C11: Xác nhận hạ/xếp container (quản lý vị trí) | D11: An ninh | E11: Thực hiện | F11: Thực hiện | G11: Xem | H11: Xem | I11: Thực hiện | J11: Thực hiện | K11: Thực hiện | M11: Đã chốt
A12: Q08 | B12: Điều phối | C12: Cập nhật HÀNG/RỖNG | D12: Điều phối | E12: Thực hiện | F12: Thực hiện | G12: Xem | H12: Xem | I12: Thực hiện | J12: Thực hiện | K12: Thực hiện | M12: Đã chốt
A13: Q09 | B13: Điều phối | C13: Sửa HÀNG/RỖNG sau khi đã ra | D13: Điều phối | E13: Thực hiện | F13: Thực hiện | G13: Xem | H13: Xem | I13: Thực hiện | J13: Thực hiện | K13: Thực hiện | M13: Đã chốt
A14: Q10 | B14: Cắm điện | C14: Tạo yêu cầu cắm/rút từ khách hàng | D14: CCKB | E14: Xem | F14: Xem | G14: Thực hiện | H14: Thực hiện | I14: Xem | J14: Xem | K14: Thực hiện | M14: Đã chốt
A15: Q11 | B15: Cắm điện | C15: Thực hiện cắm/rút điện tại hiện trường | D15: An ninh | E15: Thực hiện | F15: Thực hiện | G15: Thực hiện | H15: Thực hiện | I15: Xem | J15: Xem | K15: Thực hiện | M15: Đã chốt
A16: Q12 | B16: Cắm điện | C16: Nhập GIO_CAM_THUC_TE | D16: CCKB | E16: Xem | F16: Xem | G16: Thực hiện | H16: Thực hiện | I16: Xem | J16: Xem | K16: Thực hiện | M16: Đã chốt
A17: Q13 | B17: Cắm điện | C17: Nhập GIO_RUT_THUC_TE | D17: CCKB | E17: Xem | F17: Xem | G17: Thực hiện | H17: Thực hiện | I17: Xem | J17: Xem | K17: Thực hiện | M17: Đã chốt
A18: Q14 | B18: Cắm điện | C18: Sửa giờ cắm/rút trước khi thu | D18: CCKB | E18: Xem | F18: Xem | G18: Thực hiện | H18: Thực hiện | I18: Xem | J18: Xem | K18: Thực hiện | M18: Đã chốt
A19: Q15 | B19: Cắm điện | C19: Đề nghị sửa giờ sau khi đã thu | D19: CCKB | E19: Xem | F19: Xem | G19: Thực hiện | H19: Thực hiện | I19: Xem | J19: Xem | K19: Thực hiện | M19: Đã chốt
A20: Q16 | B20: Cắm điện | C20: Phê duyệt chênh lệch sau khi thu | D20: Quản trị | E20: Xem | F20: Xem | G20: Thực hiện | H20: Thực hiện | I20: Xem | J20: Xem | K20: Thực hiện | M20: Đã chốt
A21: Q17 | B21: Cắm điện | C21: Quản lý danh mục giá điện và ngày hiệu lực | D21: Quản trị | E21: Xem | F21: Xem | G21: Xem | H21: Xem | I21: Xem | J21: Xem | K21: Thực hiện | M21: Đã chốt
A22: Q18 | B22: Thanh toán | C22: Tính/thu phí lưu container | D22: An ninh | E22: Thực hiện | F22: Thực hiện | G22: Xem | H22: Xem | I22: Xem | J22: Xem | K22: Thực hiện | M22: Đã chốt
... A34: Q30 | B34: Báo cáo | C34: Xuất Excel/báo cáo phục vụ kiểm toán | D34: Chờ phân quyền | E34: Không | F34: Không | G34: Không | H34: Không | I34: Không | J34: Không | K34: Thực hiện | M34: Đã chốt
A35: Q31 | B35: Cắm điện dự kiến | C35: Tạo yêu cầu cắm điện cho cont chưa vào (một hoặc nhiều số) | D35: CCKB | K35: Thực hiện | L35: Đề xuất NV/TBP CCKB thực hiện; chưa chốt chi tiết vai trò. | M35: Đã chốt
A36: Q32 | B36: Cắm điện dự kiến | C36: Sửa hoặc hủy yêu cầu điện dự kiến khi khách đổi số cont | D36: CCKB | K36: Thực hiện | L36: Cần chốt quyền, lưu lịch sử và thông báo An ninh. | M36: Đã chốt
A37: Q33 | B37: Cổng vào | C37: Xem cảnh báo danh sách cont có yêu cầu cắm điện dự kiến | D37: An ninh | K37: Thực hiện | L37: Đã chốt An ninh cần nhìn thấy khi nhập container. | M37: Đã chốt
A38: Q34 | B38: Cổng vào | C38: Xác nhận ghép số cont dự kiến với lượt cont vào thực tế | D38: An ninh + CCKB | K38: Thực hiện | L38: Quy tắc ghép tự động/thủ công chưa chốt. | M38: Đã chốt
A39: Q35 | B39: Container | C39: Sửa số cont đã nhập sai và ghi nhận đã báo CCKB | D39: An ninh | K39: Thực hiện | L39: Đã chốt bộ phận; cần quy định khi đã thu tiền. | M39: Đã chốt
A40: Q36 | B40: Container | C40: Tiếp nhận cảnh báo sửa số cont, kiểm tra và cập nhật yêu cầu dự kiến | D40: CCKB | K40: Thực hiện | L40: Quy trình xác nhận và phương thức báo lại cần chốt. | M40: Đã chốt
A41: Q37 | B41: Chứng cứ | C41: Đính kèm ảnh/video nhận diện sai số container | D41: An ninh / CCKB | K41: Thực hiện | L41: Cần chốt bắt buộc hay không, kích thước và lưu trữ. | M41: Đã chốt
A42: Q38 | B42: Ngoại lệ | C42: Duyệt sửa số cont sau thanh toán/đã ra và đối soát phí | D42: Chờ phân quyền | K42: Thực hiện | L42: Không được tự động đổi lịch sử khoản thu đã chốt. | M42: Đã chốt
A43: Q39 | B43: Đối soát | C43: Xem và xác nhận đã xử lý cảnh báo sai số cont/không ghép được yêu cầu dự kiến | D43: CCKB + An ninh | K43: Thực hiện | L43: Cần trạng thái giao việc và phản hồi đóng thông báo. | M43: Đã chốt

Sheet 05_KICH_BAN
A1: BỘ TÌNH HUỐNG ĐỂ XÁC NHẬN QUY TẮC VÀ NGHIỆM THU
A2: Kịch bản chưa được chốt được ghi rõ là “Cần xác nhận”; ô màu vàng để bộ phận điền kết quả chuẩn trước khi kiểm thử.
A4: Mã | B4: Phân hệ | C4: Tình huống nghiệp vụ | D4: Dữ liệu đầu vào minh họa | E4: Kỳ vọng hiện có / cần xác nhận | F4: Mức độ | G4: Kết quả chuẩn Sơn Cảng (điền) | H4: Tình trạng | I4: Ghi chú kiểm thử (điền)
A5: TC01 | B5: Vé | C5: Xe container lạnh có cont vào bãi | D5: Loại CONT_LANH, có SO_CONTAINER | E5: Vé vào 250.000đ; An ninh thu | F5: P1 | H5: Có quy tắc
A6: TC02 | B6: Vé | C6: Đầu kéo vào không cont, ra không cont | D6: DAU_KEO | E6: Vé vào 0đ; không phí lưu cont | F6: P1 | H6: Có quy tắc
A7: TC03 | B7: Vé | C7: Đầu kéo vào không cont, ra kéo cont lưu trong bãi | D7: DAU_KEO + SO_CONTAINER_RA | E7: ĐÃ CHỐT V01: không thu thêm 250.000đ ở lượt ra; container vẫn được tính phí lưu theo lượt. | F7: P0 | H7: Có quy tắc
A8: TC04 | B8: Vé | C8: Xe bo ba bánh không có biển số | D8: XE_BO_3_BANH, BIEN_SO_XE rỗng | E8: Tạo mã lượt; tiền vé 40.000đ | F8: P1 | H8: Có quy tắc
A9: TC05 | B9: Vé | C9: Xe bo 3 chân vào không cont | D9: XE_BO_3_CHAN | E9: Vé vào 200.000đ; không phí lưu cont | F9: P1 | H9: Có quy tắc
A10: TC06 | B10: Vé | C10: Lái xe không xuất trình được liên 02 | D10: Vé đã phát, liên 02 mất | E10: Mức phạt 250.000đ; người xác nhận/thu CHƯA CHỐT | F10: P0 | H10: Chờ duyệt
A11: TC07 | B11: Lưu cont | C11: Cont ở trên xe, không hạ, ở qua 3 kỳ đêm | D11: 10/10 20:00 → 13/10 08:00 | E11: 3 đêm; miễn 1; thu 200.000đ | F11: P1 | H11: Có quy tắc
A12: TC08 | B12: Lưu cont | C12: Cont đã hạ, xe đầu vào ra một mình | D12: Xe A ra; cont còn trong bãi | E12: Cont vẫn tiếp tục tính phí đến GIO_CONT_RA | F12: P1 | H12: Có quy tắc
A13: TC09 | B13: Lưu cont | C13: Xe B đến kéo cont đã do xe A đưa vào | D13: ID_VEHICLE_VAO khác ID_VEHICLE_RA | E13: Phí tính cho cùng lượt cont, không khởi tạo lại GIO_CONT_VAO | F13: P1 | H13: Có quy tắc
A14: TC10 | B14: Lưu cont | C14: Cont vào và ra trong ngày, trước 22:00 | D14: 10/10 08:00 → 10/10 20:00 | E14: ĐÃ CHỐT L05=B: SO_DEM_LUU hiển thị tối thiểu 1 (miễn phí); tiền lưu 0đ. | F14: P0 | H14: Có quy tắc
A15: TC11 | B15: Lưu cont | C15: Ra đúng mốc 22:00 | D15: 10/10 20:00 → 10/10 22:00 | E15: ĐÃ CHỐT L01=A: ra đúng 22:00 ghi nhận một kỳ đêm (miễn đêm đầu). | F15: P0 | H15: Có quy tắc
A16: TC12 | B16: Lưu cont | C16: Ra đúng mốc 06:00 | D16: 10/10 23:00 → 11/10 06:00 | E16: ĐÃ CHỐT L02=A: ra đúng 06:00 vẫn tính thuộc kỳ đêm vừa kết thúc. | F16: P0 | H16: Có quy tắc
... A31: TC27 | B31: Mất mạng | C31: An ninh cho xe ra khi PWA offline | D31: Điện thoại không có internet | E31: ĐÃ CHỐT K03=A: offline cho phép ghi nhận chờ đồng bộ; không tự xác nhận ra cổng offline. | F31: P0 | H31: Có quy tắc
A32: TC28 | B32: Yêu cầu điện dự kiến | C32: CCKB tiếp nhận trước yêu cầu cắm A, B, C; chưa xe nào vào | D32: CCKB tạo yêu cầu cho A/B/C | E32: Đã chốt: ghi danh sách dự kiến; không tạo lượt cont vào và không tính tiền điện/lưu trước khi có sự kiện thực tế. | F32: P0 | H32: Có quy tắc | I32: Bổ sung nghiệp vụ mới ngày 11/10/2026
A33: TC29 | B33: Yêu cầu điện dự kiến | C33: Chỉ container A trong danh sách A,B,C đi vào cổng | D33: A vào trước, B/C chưa tới | E33: Đã chốt: An ninh thấy cảnh báo yêu cầu dự kiến. Đề xuất: chỉ A ghép lượt thực tế, B/C vẫn chờ. | F33: P0 | H33: Chờ duyệt | I33: Bổ sung nghiệp vụ mới ngày 11/10/2026
A34: TC30 | B34: Yêu cầu điện dự kiến | C34: An ninh gõ trùng số container trong yêu cầu dự kiến | D34: CCKB dự kiến ABCU1234567, thực tế ABCU1234567 | E34: Đã chốt: hiển thị yêu cầu dự kiến để đối chiếu. Cơ chế ghép tự động/chọn tay cần xác nhận PR04. | F34: P0 | H34: Chờ duyệt | I34: Bổ sung nghiệp vụ mới ngày 11/10/2026
A35: TC31 | B35: Đối chiếu số cont | C35: Số container khách báo trước sai 1 ký tự so với số thực tế | D35: ABCU1234567 vs ACBU1234567 | E35: Đề xuất: cảnh báo mã gần giống, không tự ghép/đổi số khi khác; An ninh xác minh thực tế. | F35: P0 | H35: Chờ duyệt | I35: Bổ sung nghiệp vụ mới ngày 11/10/2026
A36: TC32 | B36: Sửa số cont | C36: An ninh thấy số đã nhập nhầm sau khi chụp ảnh hiện trường | D36: Số dự kiến/nhập khác ảnh cont thực tế | E36: Đã chốt: An ninh có thể sửa và báo lại CCKB; đề xuất giữ giá trị cũ/mới, người sửa, lý do và chứng cứ. | F36: P0 | H36: Có quy tắc | I36: Bổ sung nghiệp vụ mới ngày 11/10/2026
A37: TC33 | B37: Sửa số cont | C37: Khách ban đầu báo sai số cont, CCKB nhập sai yêu cầu dự kiến | D37: Khách nhắn A, thực tế B | E37: Đề xuất: CCKB cập nhật yêu cầu dự kiến theo số thực tế; không tạo trùng lượt cont. | F37: P0 | H37: Chờ duyệt | I37: Bổ sung nghiệp vụ mới ngày 11/10/2026
A38: TC34 | B38: Liên kết điện | C38: Sau khi đã nhập giờ cắm, An ninh phát hiện video chụp cont khác số đã liên kết | D38: Phiên điện nối nhầm cont A thay vì B | E38: Đề xuất: quy trình sửa liên kết phiên điện có kiểm soát; audit, thông báo CCKB và tính lại liên quan. | F38: P0 | H38: Chờ duyệt | I38: Bổ sung nghiệp vụ mới ngày 11/10/2026
A39: TC35 | B39: Sau khi thu tiền | C39: Sửa số cont sau khi phí điện/lưu đã thu hoặc CCKB đã duyệt cho ra | D39: Trạng thái tiền đã thu/đã duyệt | E39: Đề xuất: không thay ngầm giao dịch tài chính; cần tái kiểm tra và xác nhận ngoại lệ. | F39: P0 | H39: Chờ duyệt | I39: Bổ sung nghiệp vụ mới ngày 11/10/2026
A40: TC36 | B40: Dữ liệu trùng | C40: Có hai yêu cầu dự kiến cùng số cont nhưng khác khách hàng hoặc 2 cont cùng mã đang trong bãi | D40: ABCU1234567 lặp trong hai yêu cầu | E40: Đề xuất: cảnh báo trùng và yêu cầu phân định đúng lượt thực tế; không tự nhập/thu trùng. | F40: P0 | H40: Chờ duyệt | I40: Bổ sung nghiệp vụ mới ngày 11/10/2026
A41: TC37 | B41: Yêu cầu điện dự kiến | C41: Container đã được đăng ký dự kiến nhưng khách hủy/không đến | D41: Dự kiến A/B/C, hủy C | E41: Đề xuất: cho hủy dòng C, giữ lịch sử; không thay dữ liệu A/B và không tạo phí. | F41: P1 | H41: Chờ duyệt | I41: Bổ sung nghiệp vụ mới ngày 11/10/2026
A42: TC38 | B42: Tình huống mạng | C42: An ninh tra cứu yêu cầu dự kiến nhưng mất Internet tại cổng | D42: PWA offline, cần xác nhận cont | E42: Cần chốt: thông báo dữ liệu có thể chưa cập nhật; không tự ghép hay xác nhận tài chính/cho ra khi offline. | F42: P0 | H42: Chờ duyệt | I42: Bổ sung nghiệp vụ mới ngày 11/10/2026
A43: TC39 | B43: Thanh toán | C43: CCKB duyệt cho container ra dù chưa ghi nhận đủ tiền | D43: Container còn 200.000đ tiền điện; CCKB cho phép ra | E43: Cho thao tác duyệt thủ công với cảnh báo Chưa thu; quyền/lý do/nhật ký còn cần chốt OUT01 | F43: P0 | H43: Chờ duyệt | I43: V1 T08, OUT01
... A48: TC44 | B48: Sai số cont | C48: An ninh phát hiện số cont sai sau khi CCKB đã duyệt ra tay | D48: Sai một số; trước đó CCKB duyệt chưa thu đủ | E48: Giữ cảnh báo, thông báo CCKB đối chiếu khoản thu/trạng thái ra; phương thức chặn hoặc cho ra cần chốt SC08 | F48: P0 | H48: Chờ duyệt | I48: V1 T08/D06 + SC08

Sheet 06_MAPPING_V1
A1: DANH MỤC CỘT DỮ LIỆU APPSHEET V1 — ĐỐI CHIẾU PWA
A2: 32 cột VEHICLE + 25 cột CONTAINER từ tệp gốc. Ánh xạ PWA là đề xuất kỹ thuật, không tự coi là đã phê duyệt.
A4: STT | B4: Bảng V1 | C4: Cột gốc V1 | D4: Hướng lưu trên PWA (đề xuất) | E4: Cách chuyển dữ liệu | F4: Mức ưu tiên | G4: Quyết định ánh xạ (điền) | H4: Ghi chú chuyển đổi (điền)
A5: 1 | B5: VEHICLE | C5: ID | D5: VEHICLE | E5: Giữ khóa nguồn/legacy ID; kiểm tra trùng. | F5: P0
A6: 2 | B6: VEHICLE | C6: BIEN_SO_XE | D6: VEHICLE_VISITS | E6: Giữ thời điểm thực tế, nguồn người thao tác; tách trạng thái tài chính và ra cổng. | F6: P1
A7: 3 | B7: VEHICLE | C7: LOAI_XE | D7: VEHICLE_VISITS | E7: Giữ thời điểm thực tế, nguồn người thao tác; tách trạng thái tài chính và ra cổng. | F7: P1
A8: 4 | B8: VEHICLE | C8: SO_CONTAINER_VAO | D8: CONTAINER / CONTAINER_VISITS | E8: Lưu lượt container độc lập, liên kết lượt xe; kiểm tra lịch sử nhiều lượt. | F8: P1
A9: 5 | B9: VEHICLE | C9: ID_CONTAINER_VAO | D9: Ghi chú nghiệp vụ / audit | E9: Cần xem ý nghĩa và ánh xạ theo hồ sơ nguồn. | F9: P1
A10: 6 | B10: VEHICLE | C10: GIO_VAO | D10: VEHICLE_VISITS | E10: Giữ thời điểm thực tế, nguồn người thao tác; tách trạng thái tài chính và ra cổng. | F10: P0
A11: 7 | B11: VEHICLE | C11: NGUOI_VAO | D11: VEHICLE_VISITS | E11: Giữ thời điểm thực tế, nguồn người thao tác; tách trạng thái tài chính và ra cổng. | F11: P1
A12: 8 | B12: VEHICLE | C12: SO_CONTAINER_RA | D12: CONTAINER / CONTAINER_VISITS | E12: Lưu lượt container độc lập, liên kết lượt xe; kiểm tra lịch sử nhiều lượt. | F12: P1
A13: 9 | B13: VEHICLE | C13: ID_CONTAINER_RA | D13: Ghi chú nghiệp vụ / audit | E13: Cần xem ý nghĩa và ánh xạ theo hồ sơ nguồn. | F13: P1
A14: 10 | B14: VEHICLE | C14: GIO_RA | D14: VEHICLE_VISITS | E14: Giữ thời điểm thực tế, nguồn người thao tác; tách trạng thái tài chính và ra cổng. | F14: P0
A15: 11 | B15: VEHICLE | C15: NGUOI_RA | D15: VEHICLE_VISITS | E15: Giữ thời điểm thực tế, nguồn người thao tác; tách trạng thái tài chính và ra cổng. | F15: P1
A16: 12 | B16: VEHICLE | C16: TIEN_VE_GOC | D16: CHARGES / PAYMENTS / AUDIT_LOG | E16: Tách số tiền phải thu và tiền thực nhận, giữ bằng chứng và lịch sử. | F16: P1
... A61: 57 | B61: CONTAINER | C61: TINH_TRANG_HANG_CONT | D61: CONTAINER / CONTAINER_VISITS | E61: Lưu lượt container độc lập, liên kết lượt xe; kiểm tra lịch sử nhiều lượt. | F61: P1

Sheet 07_TAI_KHOAN
A1: DANH SÁCH USERS APPSHEET — PHỤC VỤ ÁNH XẠ PHÂN QUYỀN
A2: Giữ nguyên EMAIL / HO_TEN / VAI_TRO / HOAT_DONG người dùng đã cung cấp. Cột mới để Sơn Cảng nhập, không tự cấp thêm quyền.
A4: STT | B4: EMAIL V1 | C4: HỌ TÊN V1 | D4: VAI_TRÒ V1 | E4: HOẠT ĐỘNG V1 | F4: Bộ phận PWA (điền) | G4: Vai trò PWA (điền) | H4: Hoạt động mới (điền) | I4: Ghi chú xác nhận (điền)
A5: 1 | B5: thanhngx12@gmail.com | C5: Nguyễn Xuân Thành | D5: Quản trị | E5: TRUE
A6: 2 | B6: anninh.talunglogistics@gmail.com | C6: Nhân viên An ninh 01 | D6: Nhân viên An ninh | E6: TRUE
A7: 3 | B7: thaild@talunglogistics.com | C7: Trưởng bộ phận An ninh | D7: Trưởng bộ phận An ninh | E7: TRUE
A8: 4 | B8: vietnq.talunglogistics@gmail.com | C8: Nhân viên An ninh 02 | D8: Nhân viên An ninh | E8: TRUE
A9: 5 | B9: dieuphoi.talunglogistics@gmail.com | C9: Điều phối | D9: Điều phối | E9: TRUE
A10: 6 | B10: gate.talunglogistics@gmail.com | C10: Điều phối | D10: Điều phối | E10: TRUE

Sheet 08_DOI_SOAT
A1: CÁC MẪU DỮ LIỆU CŨ CẦN ĐỐI CHIẾU TRƯỚC CHUYỂN ĐỔI
A2: Dấu hiệu chưa nhất quán chỉ là mục cần xác minh, KHÔNG tự kết luận đã thu thiếu hoặc nhập sai. Không tự sửa chứng từ gốc.
A4: STT | B4: Đối tượng | C4: ID / Số container | D4: Dữ liệu trong bảng | E4: Dấu hiệu cần kiểm tra | F4: Tác động tiềm ẩn | G4: Bộ phận đối chiếu | H4: Kết luận đối chiếu (điền) | I4: Trạng thái
A5: 1 | B5: CONTAINER | C5: CCLU8578039 | D5: TIEN_LUU_PHAI_THU = 1.000.000đ; GHI_CHU_THU_LUU = "900k" | E5: Cần xác nhận số tiền thực nhận là 900k hay 1 triệu; không suy ra từ trạng thái Đã thu. | F5: Tránh xuất sai doanh thu/công nợ khi chuyển. | G5: CCKB + Kế toán | I5: Chưa đối soát
A6: 2 | B6: CONTAINER | C6: KKFU2636586 | D6: TIEN_LUU_PHAI_THU = 2.900.000đ; ghi chú 2.700.000đ; GIO_CONT_RA 26/09/2026 | E6: Ghi chú nêu "ra 20:20 23/9" khác ngày ra trong cột; cần đối chiếu vé và tiền nhận. | F6: Sai mốc ra có thể thay đổi số đêm và phí. | G6: An ninh + CCKB + Kế toán | I6: Chưa đối soát
A7: 3 | B7: CONTAINER | C7: WHLU7751030 | D7: TIEN_LUU_PHAI_THU = 900.000đ; ghi chú "Hùng thu 800k k ghi sổ" | E7: Cần kiểm tra tiền đã thu nhưng chưa vào sổ hay mới là ghi chú ngoài hệ thống. | F7: Tránh ghi nhận trùng hoặc bỏ sót khoản thu. | G7: CCKB + Kế toán | I7: Chưa đối soát
A8: 4 | B8: VEHICLE | C8: 15C09113 / ID 43da6325 | D8: SO_CONTAINER_VAO = TDRU0708408; SO_CONTAINER_RA = TDRU0708407 | E8: Số container vào và ra lệch 1 chữ số; cần xác nhận thay cont thực tế hay nhập nhầm. | F8: Ảnh hưởng liên kết lượt cont và thu phí. | G8: An ninh + Điều phối | I8: Chưa đối soát
A9: 5 | B9: VEHICLE | C9: ID 71562ccf | D9: XE_BO_3_BANH, BIEN_SO_XE để trống | E9: Dữ liệu chứng minh cần xử lý xe không có biển số thật. | F9: PWA không bắt buộc biển số và cần mã lượt độc lập. | G9: An ninh | I9: Chưa đối soát
A10: 6 | B10: VEHICLE | C10: ID ee310485, 2beb741a | D10: XE_BO_3_BANH, BIEN_SO_XE là "BO BA BANH" / "XE BA BANH" | E10: Bản ghi loại xe chứa mô tả thay biển số; khi chuyển cần chuẩn hóa rỗng, nhưng chỉ sau kiểm tra. | F10: Tránh coi chữ tự do là biển số phương tiện. | G10: An ninh + CNTT | I10: Chưa đối soát
A11: 7 | B11: VEHICLE | C11: Các dòng ghi "Khắc phục đồng bộ" | D11: Xe ra đã được cập nhật giờ ra sau dữ liệu container | E11: Cần phát hiện xe và cont đã ra thực tế nhưng không đồng nhất thời gian/bản ghi. | F11: PWA phải khóa giao dịch ra xe/cont đồng bộ. | G11: An ninh + CNTT | I11: Chưa đối soát

Sheet 09_TINH_DIEN
A1: MÔ PHỎNG QUY TẮC TIỀN ĐIỆN — LÀM TRÒN 15 PHÚT
A2: Thay đổi đơn giá và bước làm tròn trong ô vàng để kiểm thử. Đây là bản mô phỏng; không phải bảng thu tiền thực tế.
A4: Đơn giá (VND/giờ) | B4: 100000
A5: Bước làm tròn (phút) | B5: 15
A8: STT | B8: Giờ cắm thực tế (điền) | C8: Giờ rút thực tế (điền) | D8: Số phút thực tế | E8: Số phút tính tiền | F8: Giờ tính tiền | G8: Đơn giá (VNĐ/giờ) | H8: Thành tiền (VND)
A9: 1 | B9: 46306.354 | C9: 46306.558 | D9: =IF(OR(B9="",C9="",C9<=B9),"",ROUND((C9-B9)*1440,0)) | E9: =IF(D9="","",ROUNDUP(D9/$B$5,0)*$B$5) | F9: =IF(E9="","",E9/60) | G9: =IF($B$4="","",$B$4) | H9: =IF(OR(F9="",G9=""),"",ROUND(F9*G9,0))
A10: 2 | B10: 46306.354 | C10: 46306.365 | D10: =IF(OR(B10="",C10="",C10<=B10),"",ROUND((C10-B10)*1440,0)) | E10: =IF(D10="","",ROUNDUP(D10/$B$5,0)*$B$5) | F10: =IF(E10="","",E10/60) | G10: =IF($B$4="","",$B$4) | H10: =IF(OR(F10="",G10=""),"",ROUND(F10*G10,0))
A11: 3 | B11: 46306.354 | C11: 46306.365 | D11: =IF(OR(B11="",C11="",C11<=B11),"",ROUND((C11-B11)*1440,0)) | E11: =IF(D11="","",ROUNDUP(D11/$B$5,0)*$B$5) | F11: =IF(E11="","",E11/60) | G11: =IF($B$4="","",$B$4) | H11: =IF(OR(F11="",G11=""),"",ROUND(F11*G11,0))
A12: 4 | B12: 46306.354 | C12: 46306.396 | D12: =IF(OR(B12="",C12="",C12<=B12),"",ROUND((C12-B12)*1440,0)) | E12: =IF(D12="","",ROUNDUP(D12/$B$5,0)*$B$5) | F12: =IF(E12="","",E12/60) | G12: =IF($B$4="","",$B$4) | H12: =IF(OR(F12="",G12=""),"",ROUND(F12*G12,0))
A13: 5 | B13: 46306.354 | C13: 46306.397 | D13: =IF(OR(B13="",C13="",C13<=B13),"",ROUND((C13-B13)*1440,0)) | E13: =IF(D13="","",ROUNDUP(D13/$B$5,0)*$B$5) | F13: =IF(E13="","",E13/60) | G13: =IF($B$4="","",$B$4) | H13: =IF(OR(F13="",G13=""),"",ROUND(F13*G13,0))
A14: 6 | B14: 46306.354 | C14: 46306.542 | D14: =IF(OR(B14="",C14="",C14<=B14),"",ROUND((C14-B14)*1440,0)) | E14: =IF(D14="","",ROUNDUP(D14/$B$5,0)*$B$5) | F14: =IF(E14="","",E14/60) | G14: =IF($B$4="","",$B$4) | H14: =IF(OR(F14="",G14=""),"",ROUND(F14*G14,0))
A15: 7 | B15: 46306.944 | C15: 46307.153 | D15: =IF(OR(B15="",C15="",C15<=B15),"",ROUND((C15-B15)*1440,0)) | E15: =IF(D15="","",ROUNDUP(D15/$B$5,0)*$B$5) | F15: =IF(E15="","",E15/60) | G15: =IF($B$4="","",$B$4) | H15: =IF(OR(F15="",G15=""),"",ROUND(F15*G15,0))
A16: 8 | B16: 46306.354 | C16: 46306.522 | D16: =IF(OR(B16="",C16="",C16<=B16),"",ROUND((C16-B16)*1440,0)) | E16: =IF(D16="","",ROUNDUP(D16/$B$5,0)*$B$5) | F16: =IF(E16="","",E16/60) | G16: =IF($B$4="","",$B$4) | H16: =IF(OR(F16="",G16=""),"",ROUND(F16*G16,0))
A19: Nguyên tắc: | B19: CCKB nhập giờ thực tế; hệ thống tính thời lượng và làm tròn LÊN theo từng 15 phút, tính theo đơn giá phiên cắm.
A21: CHÚ Ý: các câu hỏi về giây, thời lượng tối thiểu, sửa sau khi thu và thay đổi giá trong khi cắm vẫn nằm trong tab 01_CAU_HOI.

Sheet 10_DU_KIEN_SUA_SO_CONT
A1: YÊU CẦU ĐIỆN TRƯỚC KHI CONTAINER VÀO & SỬA SỐ CONTAINER
A2: Phân tách thông tin khách hàng thông báo trước, container đã vào thật và thao tác sửa sai — chỉ các mục ghi ĐÃ CHỐT mới là yêu cầu xác nhận.
A4: I. QUYẾT ĐỊNH MỚI VÀ PHẠM VI
A5: Mã | B5: Nội dung | C5: Trạng thái | D5: Quy tắc nghiệp vụ | E5: Giải pháp triển khai đề xuất | F5: Cần xác nhận thêm
A6: CN-01 | B6: Có yêu cầu điện dự kiến trước khi container vào | C6: Đã chốt | D6: CCKB nhận từ khách trước danh sách cont A/B/C, được ghi yêu cầu ngay. | E6: Lưu bản ghi dự kiến, không tự tạo lượt container vào, không ghi giờ vào và không tính phí. | F6: Cách nhóm A/B/C vào phiếu
A7: CN-02 | B7: An ninh nhìn thấy dự kiến lúc tiếp nhận | C7: Đã chốt | D7: Khi nhập số cont tại cổng, An ninh phải chú ý thông tin yêu cầu điện dự kiến. | E7: Hiển thị thẻ Chờ cắm điện / Đã đặt trước; gợi ý ghép và đối chiếu số thật. | F7: Quy tắc ghép số đầy đủ/7 số cuối
A8: CN-03 | B8: An ninh sửa số cont sai và báo lại CCKB | C8: Đã chốt | D8: Sai có thể xuất phát từ khách, CCKB hoặc hiện trường. Ảnh/video giúp phát hiện sai. | E8: Thao tác Sửa số container, ghi cũ/mới/lý do/người sửa; tạo cảnh báo CCKB. | F8: Quy trình sau khi thu/đã ra, bằng chứng bắt buộc?
A9: CN-04 | B9: Tách dự kiến khỏi thực tế | C9: Đề xuất chờ chốt | D9: Tạo yêu cầu điện trước không được làm tăng số cont thật đang nằm bãi. | E9: Mỗi dòng dự kiến chỉ liên kết tới ID lượt container khi xe/cont được ghi nhận vào cổng. | F9: Cách xác nhận liên kết và hết hạn dự kiến
A12: II. LUỒNG NHẬN YÊU CẦU ĐIỆN TRƯỚC KHI XE VÀO
A13: Bước | B13: Bộ phận | C13: Trạng thái đề xuất | D13: Thao tác nghiệp vụ | E13: Dữ liệu hiển thị/được lưu | F13: Lưu ý
A14: 1 | B14: CCKB | C14: Dự kiến / Chờ container vào | D14: Nhận thông tin khách hàng cho A, B, C; tạo yêu cầu cắm điện dự kiến. | E14: Số cont dự kiến, khách hàng, hình thức, người ghi nhận, giờ tiếp nhận; giờ dự kiến nếu có. | F14: Không cần GIO_CONT_VAO
A15: 2 | B15: An ninh | C15: Kiểm tra yêu cầu dự kiến | D15: Nhập loại xe, biển số, số cont thực tế lúc xe đến; xem cảnh báo các yêu cầu chờ. | E15: Hiển thị đúng số cont và các mã gần giống; tránh nhầm lẫn khi nhập 11 ký tự. | F15: Khi mã khác nhau phải đối chiếu ảnh/video timestamp; không tự ghép hai mã gần giống.
A16: 3 | B16: An ninh + CCKB | C16: Đã vào / Chờ cắm | D16: Đối chiếu số cont thực tế, xác nhận ghép với dòng dự kiến A (nếu phù hợp). | E16: ID lượt cont thực tế được liên kết với dòng yêu cầu A; B/C vẫn chờ. | F16: Chỉ tạo giờ vào khi cont thực vào
A17: 4 | B17: An ninh | C17: Đã thực hiện cắm (ngoài hiện trường) | D17: Thực hiện cắm theo yêu cầu; báo giờ thực tế qua Zalo/nhóm. | E17: Ảnh/video nếu có; người thực hiện thực tế; giờ báo. | F17: Không ép An ninh tự nhập giờ cắm PWA
A18: 5 | B18: CCKB | C18: Đang cắm / Đã rút / Chờ thu | D18: Nhập giờ cắm/rút từ thông tin An ninh báo, sửa được khi xác minh sai. | E18: Phiên điện liên kết với ID lượt cont, tính phí tròn mỗi 15 phút. | F18: Thu sau rút hoặc khi cont xuất theo phương án C
A19: 6 | B19: CCKB + An ninh | C19: Đủ điều kiện thanh toán → Đã xuất | D19: CCKB chốt phí hợp lệ, An ninh xác nhận xe/container thực ra. | E19: Chốt GIO_CONT_RA, lịch sử phí điện/lưu và người thực hiện. | F19: Tách duyệt tài chính và xác nhận thực ra
A22: III. LUỒNG SỬA SAI SỐ CONTAINER KHI CÓ ẢNH/VIDEO HOẶC KHÁCH BÁO NHẦM
A23: Bước | B23: Người phát hiện | C23: Trạng thái đề xuất | D23: Thao tác sửa/xác minh | E23: Dữ liệu bắt buộc đề xuất | F23: Điểm kiểm soát
A24: 1 | B24: An ninh / CCKB | C24: Phát hiện sai | D24: Đối chiếu mã 11 ký tự trên container hoặc chứng cứ hiện trường với dữ liệu dự kiến/đang lưu. | E24: Số cũ, số quan sát, nguồn đối chiếu; ảnh/video nếu có. | F24: Không âm thầm đổi liên kết sang container khác
A25: 2 | B25: An ninh | C25: Báo sửa số cont | D25: Chọn lượt cont đang có; nhập số đúng + lý do; lưu và báo CCKB. | E25: Người sửa, thời gian, số trước/sau, nguồn báo. | F25: V1 D06: TBP sửa trực tiếp; người dùng yêu cầu An ninh sửa và báo CCKB, nhưng quyền sửa sau thu còn mở.
A26: 3 | B26: PWA | C26: Chờ CCKB kiểm tra | D26: Sinh thông báo trong PWA về số cont đã sửa cho CCKB; gắn với yêu cầu điện/phiên điện. | E26: Mã cảnh báo, số cũ/mới, ID lượt cont, ảnh/video, người sửa. | F26: Zalo tự động là tính năng phải chốt riêng
A27: 4 | B27: CCKB | C27: Đã xác minh / Cần bổ sung | D27: Đối chiếu yêu cầu khách, cập nhật số cont dự kiến và liên kết đúng phiên điện. | E27: Người xác minh, ghi chú, lịch sử thay đổi. | F27: Không tạo lượt lưu/phiên cắm trùng
A28: 5 | B28: TBP có thẩm quyền | C28: Ngoại lệ sau thu / đã xuất | D28: Nếu tiền đã thu hoặc đã phê duyệt ra, tạo xử lý chênh lệch/đối soát. | E28: Giữ giao dịch cũ; ghi bút toán điều chỉnh nếu có. | F28: T08 cho duyệt xuất ngoại lệ khi chưa thu; nếu sai cont phải báo CCKB đối chiếu, không tự đổi khoản đã thu.
A31: IV. MÔ HÌNH DỮ LIỆU GỢI Ý — KHÔNG TẠO CONTAINER GIẢ
A32: Bảng / đối tượng | B32: Vai trò | C32: Trạng thái | D32: Liên kết | E32: Các trường trọng yếu | F32: Lưu ý
A33: CAM_DIEN_REQUESTS | B33: Phiếu khách yêu cầu điện | C33: Dự kiến | D33: Yêu cầu chung của khách hàng | E33: ID, khách hàng, người tiếp nhận, giờ tiếp nhận, yêu cầu chung | F33: Có thể có nhiều container A/B/C
A34: CAM_DIEN_REQUEST_ITEMS | B34: Các dòng container dự kiến | C34: Chờ vào / Đã vào / Hủy | D34: ID_REQUEST; ID_CONTAINER_VISIT có thể rỗng trước khi cont vào | E34: SO_CONTAINER_DU_KIEN, loại cắm, ghi chú, trạng thái khớp | F34: Một dòng dự kiến không phải một lượt cont vào thật
A35: CONTAINER / CONTAINER_VISITS | B35: Container và lượt vào thực tế | C35: Đang trong bãi / Đã xuất | D35: ID lượt xe vào/ra + ID lượt container | E35: SO_CONTAINER_THUC_TE, GIO_CONT_VAO, GIO_CONT_RA | F35: Dùng giờ thực tế để tính phí lưu
A36: CAM_DIEN_CONT | B36: Phiên cắm/rút thực tế | C36: Tiếp nhận / Đang cắm / Đã rút | D36: ID_CONTAINER_VISIT; có thể biết yêu cầu điện nguồn | E36: GIO_CAM_THUC_TE, GIO_RUT_THUC_TE, TONG_PHUT_TINH_TIEN | F36: CCKB nhập/sửa; làm tròn lên 15 phút
A37: CONTAINER_CORRECTIONS | B37: Đề nghị/sự kiện sửa số cont | C37: Báo sửa / Chờ xác minh / Đã xác minh | D37: ID_CONTAINER_VISIT, ID_REQUEST_ITEM | E37: SO_CU, SO_MOI, LY_DO, NGUOI_SUA, THOI_GIAN, BANG_CHUNG | F37: Giữ lịch sử & phản hồi CCKB
A38: APP_NOTIFICATIONS | B38: Thông báo liên bộ phận | C38: Chưa xem / Đã xem / Đã xử lý | D38: Tham chiếu sự kiện cont/yêu cầu | E38: Nguồn thông báo, người nhận, loại cảnh báo, giờ đọc | F38: Không tự coi tin nhắn Zalo là đồng bộ PWA
A41: V. DANH SÁCH CÂU HỎI CẦN TRẢ LỜI Ở TAB 01_CAU_HOI
A42: PR01/PR02/SC01 đã xác nhận. PR03–PR07, SC02–SC08 vẫn mở. D06/V09/T08/T15 ở bản V1 đã trả lời và cần đối chiếu khi xử lý sửa số cont.
A44: Nguyên tắc an toàn: sửa số container không làm thay đổi ID lượt; tiền đã thu không bị ghi đè âm thầm; thông báo CCKB cần có trạng thái đã xem/đã xử lý.

Sheet 11_RA_SOAT_V1
A1: CÁC ĐIỂM CẦN LÀM RÕ SAU KHI ĐỌC FILE V1 ĐÃ TRẢ LỜI
A2: Không tự sửa câu trả lời của người dùng. Lọc P0 để ưu tiên những điểm ảnh hưởng tiền, quyền ra cổng và điều chỉnh số container.
A4: STT | B4: Mã câu hỏi | C4: Ưu tiên | D4: Nhóm nghiệp vụ | E4: Nội dung cần chốt | F4: Người dùng đã chọn | G4: Ghi chú trả lời nguyên văn | H4: Điểm cần làm rõ / mâu thuẫn | I4: Ý kiến bổ sung (điền) | J4: Trạng thái rà soát (điền)
A5: 1 | B5: CNT01 | C5: P0 | D5: 02. Lưu container | E5: Phí lưu chốt theo giờ CCKB duyệt/thu hay giờ container ra thật? Ai kiểm tra tiền cuối cùng: An ninh hay CCKB? | H5: Câu hỏi mới từ phần nghiệp vụ phát sinh; chờ bạn trả lời. | J5: Chờ bổ sung
A6: 2 | B6: D06 | C6: P0 | D6: 06. Điều phối / container | E6: Khi số container gõ nhầm hoặc khác so với trên vé, người nào được xác nhận sửa thông tin? | F6: A | G6: TBP thì sửa trực tiếp | H6: F=A NV An ninh sửa; G TBP được sửa trực tiếp; yêu cầu mới An ninh sửa và báo CCKB. Cần ngưỡng quyền sau thu/ra. | J6: Chờ bổ sung
A7: 3 | B7: E06 | C7: P0 | D7: 03. Cắm/rút điện | E7: Sau khi đã thu tiền điện, CCKB được sửa giờ tới mức nào và quy trình phê duyệt chênh lệch? | F7: B | G7: A Và B | H7: F=B nhưng G=A và B: vừa NV đề nghị/TBP duyệt vừa TBP sửa trực tiếp; cần điều kiện khi nào mỗi cách. | J7: Chờ bổ sung
A8: 4 | B8: E07 | C8: P0 | D8: 03. Cắm/rút điện | E8: Phiên điện còn trạng thái Đang cắm trên PWA nhưng thực tế đã rút, container có được xuất không? | F8: A | G8: Làm cách nào thoai r mái hon, CCKB cứ xác định xe đã được ra thì ra, nếu xe ra đến cổng mà chưa thấy được ra thì gọi hoặc nhắn nhóm có CCKB | H8: F=A buộc cập nhật xong trước ra, nhưng G ưu tiên CCKB xác nhận bằng tay và Zalo khi cần; cần cơ chế override có audit. | J8: Chờ bổ sung
A9: 5 | B9: E08 | C9: P0 | D9: 03. Cắm/rút điện | E9: Khi không có mạng/không thể cập nhật giờ rút, cần quy trình bàn giao ngoài hệ thống và bổ sung dữ liệu như thế nào? | F9: A | G9: chỗ này chưa hiểu | H9: G ghi “chỗ này chưa hiểu”; không thể coi là quyết định đã chốt dù F=A. Cần giải thích quy trình offline và nhập bù. | J9: Chờ bổ sung
A10: 6 | B10: E09 | C10: P0 | D10: 03. Cắm/rút điện | E10: Tổng thời gian thực tế tính bằng giây hay phút? Ví dụ 4 giờ 00 phút 01 giây có làm tròn thành 4 giờ 15 phút không? | F10: Khác | G10: Hieện tại CCKB tự làm tròn | H10: G: CCKB tự làm tròn, trong khi đã chốt tính tròn lên mỗi 15 phút. Cần xác nhận tự tính mặc định + cho điều chỉnh thủ công. | J10: Chờ bổ sung
A11: 7 | B11: INV01 | C11: P0 | D11: 04. Thanh toán | E11: Khi An ninh nhận thông tin xuất hóa đơn tại cổng vào, những trường nào bắt buộc theo từng loại khách hàng? | H11: Câu hỏi mới từ phần nghiệp vụ phát sinh; chờ bạn trả lời. | J11: Chờ bổ sung
A12: 8 | B12: K01 | C12: P0 | D12: 08. Kỹ thuật / bảo mật | E12: Phần mềm chạy trên tên miền/subdomain nào và ai chịu trách nhiệm quản trị máy chủ? | H12: K01: ô lựa chọn thật sự để trống trong file V1, dù cột H được đánh dấu Đã chốt. Cần chọn tên miền/subdomain. | J12: Chờ bổ sung
A13: 9 | B13: L04 | C13: P0 | D13: 02. Lưu container | E13: CCKB đã duyệt thanh toán trước 22:00, nhưng container thực tế xuất sau 22:00 và phát sinh thêm kỳ đêm: quy trình cập nhật phí? | F13: B | G13: Vì nhiều lúc thanh toán và rút rồi nhưng chưa ra nhé | H13: F=B khóa phí tại giờ CCKB duyệt; T09 lại chọn tính lại tại lúc cont thực ra. Cần xác định mốc chốt phí sau 22:00. | J13: Chờ bổ sung
A14: 10 | B14: M03 | C14: P0 | D14: 09. Chuyển dữ liệu | E14: Các dòng dữ liệu cũ có ghi chú tiền thực thu khác tiền phải thu: ai là người kiểm tra, xác nhận kết quả trước chuyển? | F14: Khác | G14: Tiền thì tạm thời bỏ qua vò giờ trên hệ thống nhiều xe quên chưa cho ra lắ | H14: G: tạm bỏ qua đối soát tài chính lịch sử do còn nhiều xe quên chốt ra; cần đánh dấu dữ liệu cũ chưa xác minh, không đưa vào công nợ V1. | J14: Chờ bổ sung
A15: 11 | B15: M04 | C15: P0 | D15: 09. Chuyển dữ liệu | E15: Giờ ra xe/container thực tế khác dữ liệu nhập do bổ sung muộn: dùng mốc nào làm dữ liệu gốc khi chuyển? | F15: A | G15: quan trị viên cấp cao có thể sửa trực tiếp hết nhé, vì hiện tại tôi thấy lỗi nhieuf chính trên GG sheets đang đễ sau này sửa thì vào db sửa lại khó hơn | H15: G: Quản trị cấp cao được sửa mọi dữ liệu sai, nhưng cần công cụ sửa trong app kèm audit, tránh sửa DB trực tiếp không lưu lịch sử. | J15: Chờ bổ sung
A16: 12 | B16: OUT01 | C16: P0 | D16: 04. Thanh toán | E16: Khi CCKB xác nhận cho container ra dù chưa ghi nhận đủ tiền, ai có quyền và có bắt buộc ghi lý do/cảnh báo công nợ không? | H16: Câu hỏi mới từ phần nghiệp vụ phát sinh; chờ bạn trả lời. | J16: Chờ bổ sung
A17: 13 | B17: P07 | C17: P0 | D17: 05. Phân quyền | E17: Một nhân viên có thể kiêm 2 bộ phận/vai trò trên một tài khoản không? | F17: Khác | G17: Cài này có lúc theo ca có lúc 1 tk nhiêu role nhưng cứ xây dựng giai đoạn đầu máy sẽ cố định tại bốt cont CCKB thì sẽ đăng nhập tk cá nhân(Sau này muốn phát triển ai có ca mới được vào) | H17: PWA tại bốt An ninh có thể dùng thiết bị cố định; CCKB dùng tài khoản cá nhân, phân vai theo ca sau. Cần audit cá nhân khi dùng thiết bị chung. | J17: Chờ bổ sung
A18: 14 | B18: PR03 | C18: P0 | D18: 03. Cắm/rút điện | E18: Khách gửi một yêu cầu gồm 3 container A, B, C: tạo một phiếu chung có 3 dòng container hay 3 phiếu riêng? | H18: Câu hỏi mới từ phần nghiệp vụ phát sinh; chờ bạn trả lời. | J18: Chờ bổ sung
A19: 15 | B19: PR04 | C19: P0 | D19: 03. Cắm/rút điện | E19: Khi An ninh ghi số cont lúc vào, hệ thống ghép yêu cầu dự kiến và lượt cont thực tế theo cách nào? | H19: Câu hỏi mới từ phần nghiệp vụ phát sinh; chờ bạn trả lời. | J19: Chờ bổ sung
A20: 16 | B20: PR07 | C20: P0 | D20: 03. Cắm/rút điện | E20: Khi khách đổi số cont A thành B trước khi xe vào, ai được phép sửa thông tin dự kiến và có thông báo An ninh không? | H20: Câu hỏi mới từ phần nghiệp vụ phát sinh; chờ bạn trả lời. | J20: Chờ bổ sung
A21: 17 | B21: SC02 | C21: P0 | D21: 06. Điều phối / container | E21: Nếu phát hiện sai số container SAU khi cắm/rút điện hoặc đã thu tiền, có cho sửa trực tiếp hay phải trình duyệt? | H21: Câu hỏi mới từ phần nghiệp vụ phát sinh; chờ bạn trả lời. | J21: Chờ bổ sung
A22: 18 | B22: SC04 | C22: P0 | D22: 06. Điều phối / container | E22: Sau khi An ninh sửa số cont, CCKB nhận thông báo và xác nhận lại bằng cách nào? | H22: Câu hỏi mới từ phần nghiệp vụ phát sinh; chờ bạn trả lời. | J22: Chờ bổ sung
A23: 19 | B23: SC05 | C23: P0 | D23: 06. Điều phối / container | E23: Khi cont thực tế khác số cont CCKB đã ghi dự kiến, cần cập nhật phiếu dự kiến hay tạo yêu cầu mới? | H23: Câu hỏi mới từ phần nghiệp vụ phát sinh; chờ bạn trả lời. | J23: Chờ bổ sung
A24: 20 | B24: SC06 | C24: P0 | D24: 06. Điều phối / container | E24: Nếu số cont sửa thành số đang thuộc một lượt container khác đang trong bãi, có cho lưu không? | H24: Câu hỏi mới từ phần nghiệp vụ phát sinh; chờ bạn trả lời. | J24: Chờ bổ sung
A25: 21 | B25: SC08 | C25: P0 | D25: 06. Điều phối / container | E25: Nếu đã cấp đủ điều kiện tài chính rồi phát hiện sai số cont, cần thu hồi duyệt xuất và kiểm tra lại phí không? | H25: Câu hỏi mới từ phần nghiệp vụ phát sinh; chờ bạn trả lời. | J25: Chờ bổ sung
A26: 22 | B26: T03 | C26: P0 | D26: 04. Thanh toán | E26: Xác nhận chuyển khoản dựa trên ảnh khách gửi hay bắt buộc kiểm tra tài khoản công ty thực nhận? | F26: A | G26: CCKB tự xác định tiền cắm còn Lưu đêm và vé vào thì an ninh | H26: G: CCKB kiểm tra tiền cắm, AN NINH nhận lưu đêm và vé; mâu thuẫn phân công CCKB thu phí lưu đã nói trước. | J26: Chờ bổ sung
A27: 23 | B27: T08 | C27: P0 | D27: 04. Thanh toán | E27: Có cho xuất container khi còn nợ phí hoặc đã gửi chứng từ nhưng chưa xác minh nhận tiền không? | F27: Khác | G27: CCKB sẽ xác nhận cho ra hay k và có thể báo cho ra nhưng tiền chưa thusex hiện cảnh báo, 1 là tự động nếu cckb đã điền đủ thanh toán và có cái xác nhận cho xe ra bằng tay mà tiền chưa ghi nhận | H27: Cho CCKB duyệt xuất khi chưa thu tiền bằng tay và cảnh báo; cần vai trò, lý do và xử lý khoản nợ sau ra. | J27: Chờ bổ sung
A28: 24 | B28: T09 | C28: P0 | D28: 04. Thanh toán | E28: Tại cổng ra, trạng thái tài chính hợp lệ có thời hạn bao lâu trước khi phải tính lại phí lưu? | F28: A | G28: Phí lưu chỉ có AN ninh tính tại lúc ra | H28: G: An ninh tính phí lưu khi ra, trong khi phân công CCKB tính/thu phí lưu. Đồng thời mâu thuẫn L04. | J28: Chờ bổ sung
A29: 25 | B29: T12 | C29: P0 | D29: 04. Thanh toán | E29: Khi có khách hàng thường xuyên: có quản lý hồ sơ khách, mã số thuế, công nợ/hóa đơn không? | F29: Không áp dụng | G29: Sau này có nhé, vì bên Kế toán cũng muốn joint vào hệ thông này ví dụ ở trên vé vào hienejt ại an ninh điền thông tin lái xe hoặc thông tin công ty để xuất hóa đơn, có cái xuất có cái k xuất nhé, xong kế toán cũng cần tổng hợp và điền báo cáo nữa.) Các thông tin cần điền(Họ tên/Tên công ty, Mã só thuế/số CCCD, thương trú, có thể sđt n, e mail nữa | H29: Chọn Không áp dụng nhưng G yêu cầu nhập thông tin lái xe/công ty để phục vụ hóa đơn; Kế toán phát triển sau. Cần tách V1/V2. | J29: Chờ bổ sung
A30: 26 | B30: T15 | C30: P0 | D30: 04. Thanh toán | E30: Sau khi CCKB đã cấp đủ điều kiện thanh toán, An ninh phát hiện sai số cont/biển số: có quyền hủy xác nhận và gửi duyệt lại không? | F30: Không áp dụng | H30: F=Không áp dụng việc thu hồi duyệt khi phát hiện sai cont; SC08 cần cơ chế xử lý khi sai cont sau duyệt. | J30: Chờ bổ sung
A31: 27 | B31: V02 | C31: P0 | D31: 01. Vé xe / cổng | E31: Vé vào có bắt buộc thu ngay trước khi cho xe qua cổng vào, hay được phép ghi Chưa thu để bổ sung sau? | F31: A | G31: Nhưng cũng có trường họp thu sau(ít) | H31: Thu vé ngay là mặc định, nhưng ghi chú cho phép thu sau (ít). Cần xác định ai cho phép và cách báo Chưa thu. | J31: Chờ bổ sung
A32: 28 | B32: V04 | C32: P0 | D32: 01. Vé xe / cổng | E32: Xe bo ba bánh không có biển số được phân biệt lượt bằng mã vé; có cần thêm tên lái xe/đặc điểm xe/ảnh xe không? | F32: A | G32: chỉ sinh cũng được nhưng đến lúc ra cũng chịu à, hoặc có thể sinh mã r điền vào vé thôi | H32: Không có biển số; người dùng lo không biết đối chiếu khi ra. Cần quy trình mã vé/tìm lượt. | J32: Chờ bổ sung
A33: 29 | B33: V09 | C33: P0 | D33: 01. Vé xe / cổng | E33: Khi xe vào có kéo container, được phép nhập số container tạm/chưa rõ chính xác hay luôn bắt buộc số hợp lệ? | F33: A | H33: Chọn số container chính xác khi vào, nhưng nghiệp vụ thực tế thường nhập nhầm; cần cơ chế sửa có lịch sử và đối chiếu. | J33: Chờ bổ sung
A34: 30 | B34: V12 | C34: P0 | D34: 01. Vé xe / cổng | E34: Sửa GIO_VAO/GIO_RA, biển số hoặc loại xe: ai được sửa, giới hạn thời gian và cần bằng chứng gì? | F34: C | G34: cho phép sửa linh hoạt nhưng có log | H34: F=C (mọi sửa qua TBP) nhưng G=cho sửa linh hoạt, có log; cần chốt quyền riêng trước và sau khi xe đã ra. | J34: Chờ bổ sung
A35: 31 | B35: D02 | C35: P1 | D35: 06. Điều phối / container | E35: Nếu Điều phối thay đổi HÀNG thành RỖNG (hoặc ngược lại), có cần ghi lý do/người xác nhận không? | F35: A | G35: ghi lí do k bắt bược | H35: F=A ghi lý do nhưng G nói không bắt buộc. Chốt việc đổi HÀNG/RỖNG có bắt buộc lý do hay chỉ lưu audit. | J35: Chờ bổ sung
A36: 32 | B36: E02 | C36: P1 | D36: 03. Cắm/rút điện | E36: Trường hợp khách yêu cầu cắm/rút trực tiếp với An ninh mà chưa báo CCKB: xử lý nhập và xác minh ra sao? | F36: Khác | G36: A và B | H36: G=A và B: yêu cầu khách đi thẳng tới An ninh, vừa cho làm trước vừa muốn chờ CCKB; cần luồng ngoại lệ rõ. | J36: Chờ bổ sung
A37: 33 | B37: E03 | C37: P1 | D37: 03. Cắm/rút điện | E37: Hình thức Theo giờ và Cắm liên tục có khác nhau ở cách vận hành/thanh toán hay hiện chỉ khác danh mục yêu cầu? | F37: A | G37: CHỉ khác là 1 cái biết giờ rút 1 cái chưa | H37: G xác định theo giờ biết giờ rút dự kiến, liên tục chưa biết; trước đó form không yêu cầu giờ rút dự kiến. Cần là trường tùy chọn. | J37: Chờ bổ sung
A38: 34 | B38: E10 | C38: P1 | D38: 03. Cắm/rút điện | E38: Phiên cắm ngắn dưới 15 phút hoặc vô tình cắm 0 phút: tính tối thiểu 15 phút khi có cắm thực tế không? | F38: Khác | G38: Hieện tại CCKB tự làm tròn | H38: G: CCKB tự làm tròn; chưa khóa khoản phí tối thiểu cho phiên ngắn dưới 15 phút và 0 phút. | J38: Chờ bổ sung
A39: 35 | B39: E13 | C39: P1 | D39: 03. Cắm/rút điện | E39: Khi cập nhật giá điện trong lúc phiên cắm đang chạy: giữ giá lúc bắt đầu hay áp giá mới khi rút? | F39: B | G39: tùy A và B | H39: F=B tính giá mới khi rút, nhưng G “tùy A và B”; cần chính sách mặc định theo phiên và lựa chọn điều chỉnh giá. | J39: Chờ bổ sung
A40: 36 | B40: INV02 | C40: P1 | D40: 04. Thanh toán | E40: V1 cần chuyển yêu cầu xuất hóa đơn sang Kế toán và thống kê báo cáo hay chỉ lưu thông tin để làm sau? | H40: Câu hỏi mới từ phần nghiệp vụ phát sinh; chờ bạn trả lời. | J40: Chờ bổ sung
A41: 37 | B41: K04 | C41: P1 | D41: 08. Kỹ thuật / bảo mật | E41: PWA dùng điện thoại cá nhân hay thiết bị công ty? Có yêu cầu camera chụp chứng từ/quét QR số container không? | F41: A | G41: A và B | H41: F=A, G=A và B: hỗ trợ điện thoại/PC và cả thiết bị công ty; cần phân biệt cấu hình ưu tiên. | J41: Chờ bổ sung
A42: 38 | B42: K06 | C42: P1 | D42: 08. Kỹ thuật / bảo mật | E42: Ảnh thu tiền và chứng từ cần lưu bao lâu, dung lượng giới hạn, ai có quyền xem/xóa? | F42: A | G42: Chưa áp dụng, lưu trên đâu đó free, cloudflrae R2 10G | H42: G: “chưa áp dụng”, muốn lưu rẻ/miễn phí, gợi ý Cloudflare R2 10GB; thời gian giữ file và quota còn mở. | J42: Chờ bổ sung
A43: 39 | B43: L06 | C43: P1 | D43: 02. Lưu container | E43: Ai được sửa GIO_CONT_VAO/GIO_CONT_RA khi nhập muộn hoặc phát hiện sai? Việc sửa đã thu cần xử lý ra sao? | F43: A | G43: A và B luôn | H43: G=A và B: NV đề xuất/TBP duyệt hoặc TBP sửa trực tiếp; cần tách quyền theo trạng thái đã thu/chưa thu. | J43: Chờ bổ sung
A44: 40 | B44: L09 | C44: P1 | D44: 02. Lưu container | E44: Đơn giá phí lưu khi thay PRICE_LIST trong thời gian một container đang lưu: giữ giá lúc vào hay áp dụng theo từng kỳ ngày? | F44: B | G44: Cái này khó nhỉ? A và B đi cho linh hoạt | H44: F=B tính giá theo từng đêm nhưng G muốn cả A và B linh hoạt; cần chính sách mặc định và ngoại lệ theo quyền. | J44: Chờ bổ sung
A45: 41 | B45: M08 | C45: P1 | D45: 09. Chuyển dữ liệu | E45: Dữ liệu cắm điện AppSheet trước đây có nhập vào PWA cùng lúc không, hay triển khai riêng từ ngày vận hành mới? | F45: Khác | G45: CHưa có những sẽ chuyneenr 1 số cái tồn | H45: G: chưa có nhiều dữ liệu điện, sẽ chuyển một số phiên đang tồn; cần tiêu chí nhận diện các phiên phải chuyển. | J45: Chờ bổ sung
A46: 42 | B46: P01 | C46: P1 | D46: 05. Phân quyền | E46: Các vai trò chính xác cần tạo là 6 vai trò NV/TBP của 3 bộ phận + Quản trị, hay bổ sung Nhà cân/Kế toán? | F46: C | H46: F=C đề xuất thêm Kế toán, nhưng các tính năng Kế toán ghi giai đoạn sau. Cần xác định vai trò kế toán có ở V1 không. | J46: Chờ bổ sung
A47: 43 | B47: PR05 | C47: P1 | D47: 03. Cắm/rút điện | E47: Yêu cầu cắm điện dự kiến bắt buộc nhập những trường nào khi cont chưa vào bãi? | H47: Câu hỏi mới từ phần nghiệp vụ phát sinh; chờ bạn trả lời. | J47: Chờ bổ sung
A48: 44 | B48: PR06 | C48: P1 | D48: 03. Cắm/rút điện | E48: Nếu container dự kiến không tới, tới muộn nhiều ngày hoặc khách hủy, xử lý yêu cầu dự kiến ra sao? | H48: Câu hỏi mới từ phần nghiệp vụ phát sinh; chờ bạn trả lời. | J48: Chờ bổ sung
A49: 45 | B49: SC03 | C49: P1 | D49: 06. Điều phối / container | E49: Khi An ninh sửa số cont vì ảnh/video tại hiện trường cho thấy sai, có bắt buộc đính kèm ảnh hoặc video không? | H49: Câu hỏi mới từ phần nghiệp vụ phát sinh; chờ bạn trả lời. | J49: Chờ bổ sung
A50: 46 | B50: SC07 | C50: P1 | D50: 06. Điều phối / container | E50: An ninh/CCKB cần hỗ trợ tra cứu số cont bằng 7 số cuối và gợi ý mã gần giống (không tự thay mã) không? | H50: Câu hỏi mới từ phần nghiệp vụ phát sinh; chờ bạn trả lời. | J50: Chờ bổ sung
A51: 47 | B51: T01 | C51: P1 | D51: 04. Thanh toán | E51: Có cho thanh toán từng phần phí điện/lưu hoặc nộp trước khi container xuất không? | F51: B | G51: Linh hoạt thu cả hoặc thu từng phần | H51: F=B chỉ cho trả một phần, G cho cả trả đủ và trả một phần; cần xác định dữ liệu phân bổ giao dịch. | J51: Chờ bổ sung
A52: 48 | B52: T04 | C52: P1 | D52: 04. Thanh toán | E52: Ảnh bằng chứng thu tiền cần bắt buộc với giao dịch nào (vé, lưu cont, điện, mất vé)? | F52: Khác | G52: Xây dưng nhưng chưa ap dụng | H52: G: “Xây dựng nhưng chưa áp dụng”; cần tách tính năng ảnh chứng từ triển khai V1 hay để tùy chọn. | J52: Chờ bổ sung
A53: 49 | B53: T06 | C53: P1 | D53: 04. Thanh toán | E53: Nếu đã thu thiếu hoặc thừa tiền so với hệ thống: cách điều chỉnh/hoàn trả, ai duyệt? | F53: Khác | G53: Xây dưng nhưng chưa ap dụng | H53: G: xây dựng nhưng chưa áp dụng; hệ thống thu/hoàn tiền cần quy định tối thiểu để không mất dấu chênh lệch. | J53: Chờ bổ sung
A54: 50 | B54: T07 | C54: P1 | D54: 04. Thanh toán | E54: Có được miễn/giảm giá vé, phí lưu, tiền điện? Ai là người có quyền duyệt? | F54: Khác | G54: Xây dưng nhưng chưa ap dụng | H54: G: xây dựng nhưng chưa áp dụng; xác định có cho phát sinh ngoại lệ ngay V1 không. | J54: Chờ bổ sung
A55: 51 | B55: T14 | C55: P1 | D55: 04. Thanh toán | E55: Doanh thu vé An ninh thu và doanh thu phí CCKB thu được đối soát cuối ca như thế nào? | F55: Khác | G55: theo ca nhé, ca lammf việc của an ninh hiện tại là 6H-18H nhưng chốt doanh thu có thẻ là 16H và 8h30 9H kiểu vậy | H55: Chốt doanh thu không trùng giờ ca 06–18, ví dụ 16:00 hoặc 08:30–09:00; cần cấu hình kỳ chốt và người chịu trách nhiệm. | J55: Chờ bổ sung
A56: 52 | B56: U01 | C56: P1 | D56: 10. Nghiệm thu / triển khai | E56: Ai đại diện mỗi bộ phận ký nghiệm thu và xác nhận nghiệp vụ chuẩn trước chuyển hệ thống? | F56: Không áp dụng | H56: F=Không áp dụng nhóm ký nghiệm thu; U02 lại yêu cầu UAT trước ngừng AppSheet. Cần xác định ít nhất đầu mối duyệt nghiệm thu, không nhất thiết ký giấy. | J56: Chờ bổ sung
A57: 53 | B57: V03 | C57: P1 | D57: 01. Vé xe / cổng | E57: Xe container KHÔNG lạnh/container khô hiện có được tiếp nhận không? Nếu có mã xe và đơn giá vé nào? | F57: Khác | G57: Chỉ có xe cont(250K) và xe đầu kéo k còn(0Đ) | H57: Người dùng dùng tên “xe cont” chung; PRICE_LIST hiện ghi CONT_LANH. Cần rà nhãn hiển thị, không đổi mã giá đã chốt. | J57: Chờ bổ sung
A58: 54 | B58: V05 | C58: P1 | D58: 01. Vé xe / cổng | E58: Vé giấy 2 liên có cần nhập/kiểm soát SỐ VÉ GIẤY bắt buộc khi ghi nhận xe vào không? | F58: B | G58: sau này sẽ in | H58: Số vé giấy hiện không bắt buộc; người dùng nói “sau này sẽ in”. Cần xác định thuộc giai đoạn nào. | J58: Chờ bổ sung
A59: 55 | B59: K05 | C59: P2 | D59: 08. Kỹ thuật / bảo mật | E59: Có cần bắt buộc đăng nhập 2 yếu tố với quản trị/TBP, phân quyền theo phiên đăng nhập/thiết bị không? | F59: Khác | G59: Chưa áp dụng nhưng có thì tốt | H59: G: 2FA chưa áp dụng nhưng có thì tốt; cần ghi đúng là nâng cấp sau, không coi là bắt buộc V1. | J59: Chờ bổ sung
A60: 56 | B60: K09 | C60: P2 | D60: 08. Kỹ thuật / bảo mật | E60: Giai đoạn đầu có cần tích hợp Zalo thông báo lệnh cắm/rút tự động không? | F60: A | G60: A B C | H60: F=A không gửi Zalo tự động trong V1 nhưng G “A B C”; cần tách thông báo PWA/gửi thủ công và tích hợp sau. | J60: Chờ bổ sung

Sheet 12_TRA_LOI_V1_GOC
A1: BẢN LƯU CHIẾU CÂU HỎI & CÂU TRẢ LỜI V1 (KHÔNG SỬA)
A2: Sao chép nguyên giá trị 13 cột từ file Untitled spreadsheet (1).xlsx do bạn gửi ngày 11/10/2026.
A4: Mã | B4: Nhóm nghiệp vụ | C4: Ưu tiên | D4: Câu hỏi cần chốt | E4: Phương án gợi ý / cách điền | F4: Lựa chọn (điền) | G4: Quyết định/Thông số cụ thể (điền) | H4: Trạng thái (điền) | I4: Đơn vị xác nhận đề xuất | J4: Người xác nhận (điền) | K4: Ngày chốt (điền) | L4: Ghi chú bổ sung (điền) | M4: Căn cứ / nguồn
A5: V01 | B5: 01. Vé xe / cổng | C5: P0 | D5: Đầu kéo vào KHÔNG có container (vé vào 0đ), sau đó kéo container ra: có thu thêm 250.000đ ở lượt ra không? | E5: A. Không, giữ giá tại cổng vào; B. Có, bổ sung phí khi ra có kéo cont; C. Chính sách khác. | F5: A | H5: Đã chốt | I5: Ban quản lý Sơn Cảng | M5: PRICE_LIST + luồng xe nhận container
A6: V02 | B6: 01. Vé xe / cổng | C6: P0 | D6: Vé vào có bắt buộc thu ngay trước khi cho xe qua cổng vào, hay được phép ghi Chưa thu để bổ sung sau? | E6: A. Bắt buộc thu đủ; B. Cho ghi Chưa thu có điều kiện; C. Chỉ ngoại lệ cần phê duyệt. | F6: A | G6: Nhưng cũng có trường họp thu sau(ít) | H6: Đã chốt | I6: Trưởng BP An ninh + CCKB | M6: Trao đổi nghiệp vụ Sơn Cảng, 10-11/10/2026
A7: V03 | B7: 01. Vé xe / cổng | C7: P0 | D7: Xe container KHÔNG lạnh/container khô hiện có được tiếp nhận không? Nếu có mã xe và đơn giá vé nào? | E7: A. Dùng CONT_LANH nếu chung 250.000đ; B. Tạo mã giá xe container khác; C. Không sử dụng loại này. | F7: Khác | G7: Chỉ có xe cont(250K) và xe đầu kéo k còn(0Đ) | H7: Đã chốt | I7: Trưởng BP An ninh | M7: Trao đổi nghiệp vụ Sơn Cảng, 10-11/10/2026
A8: V04 | B8: 01. Vé xe / cổng | C8: P1 | D8: Xe bo ba bánh không có biển số được phân biệt lượt bằng mã vé; có cần thêm tên lái xe/đặc điểm xe/ảnh xe không? | E8: A. Chỉ mã vé tự sinh; B. Thêm thông tin nhận diện; C. Có thể nhập biển số khi có. | F8: A | G8: chỉ sinh cũng được nhưng đến lúc ra cũng chịu à, hoặc có thể sinh mã r điền vào vé thôi | H8: Đã chốt | I8: Trưởng BP An ninh | M8: Trao đổi nghiệp vụ Sơn Cảng, 10-11/10/2026
A9: V05 | B9: 01. Vé xe / cổng | C9: P0 | D9: Vé giấy 2 liên có cần nhập/kiểm soát SỐ VÉ GIẤY bắt buộc khi ghi nhận xe vào không? | E9: A. Bắt buộc; B. Khuyến khích, không bắt buộc; C. Chuyển sang in/QR từ PWA. | F9: B | G9: sau này sẽ in | H9: Đã chốt | I9: Trưởng BP An ninh | M9: Trao đổi nghiệp vụ Sơn Cảng, 10-11/10/2026
A10: V06 | B10: 01. Vé xe / cổng | C10: P0 | D10: Mất liên 02, phạt 250.000đ: bộ phận nào xác nhận, thu tiền và đánh dấu đã xử lý? | E10: A. An ninh nhận phạt; B. CCKB thu; C. An ninh xác nhận mất, CCKB thu; ghi rõ ngoại lệ. | F10: A | H10: Đã chốt | I10: Trưởng BP An ninh + CCKB | M10: Thông báo vé giấy Sơn Cảng
A11: V07 | B11: 01. Vé xe / cổng | C11: P1 | D11: Trường hợp khách có vé nhưng số vé/biển số không khớp: cho sửa vé tại cổng hay báo Trưởng BP xử lý? | E11: A. Chặn và yêu cầu phê duyệt; B. Cho xác minh bằng chứng từ; C. Quy trình khác. | F11: A | H11: Đã chốt | I11: Trưởng BP An ninh | M11: Trao đổi nghiệp vụ Sơn Cảng, 10-11/10/2026
A12: V08 | B12: 01. Vé xe / cổng | C12: P1 | D12: Xe sang tải (tạp), đầu kéo 0đ có cần ghi nhận phiếu/vé giấy và xác nhận trạng thái Miễn phí hay không? | E12: A. Có kiểm soát đủ; B. Chỉ ghi lượt; C. Trường hợp khác. | F12: A | H12: Đã chốt | I12: Trưởng BP An ninh | M12: Trao đổi nghiệp vụ Sơn Cảng, 10-11/10/2026
A13: V09 | B13: 01. Vé xe / cổng | C13: P1 | D13: Khi xe vào có kéo container, được phép nhập số container tạm/chưa rõ chính xác hay luôn bắt buộc số hợp lệ? | E13: A. Bắt buộc mã chính xác; B. Cho tạo tạm có phê duyệt; C. Được sửa trong thời hạn. | F13: A | H13: Đã chốt | I13: Trưởng BP An ninh + Điều phối | M13: Trao đổi nghiệp vụ Sơn Cảng, 10-11/10/2026
A14: V10 | B14: 01. Vé xe / cổng | C14: P0 | D14: Một lượt xe có thể chở trên 01 container cùng lúc không, đặc biệt với xe nhỏ hoặc phương tiện đặc biệt? | E14: A. Chỉ 01; B. Cho nhiều container; C. Tùy loại xe. | F14: A | H14: Đã chốt | I14: Trưởng BP An ninh + Điều phối | M14: Trao đổi nghiệp vụ Sơn Cảng, 10-11/10/2026
A15: V11 | B15: 01. Vé xe / cổng | C15: P1 | D15: Khi xe ra không kéo container (đã hạ), có yêu cầu xác nhận riêng tại cổng hay chỉ chọn phương án ra không cont? | E15: A. Bắt buộc xác nhận; B. Theo trạng thái cont thực tế; C. Quy trình khác. | F15: A | H15: Đã chốt | I15: Trưởng BP An ninh | M15: Trao đổi nghiệp vụ Sơn Cảng, 10-11/10/2026
A16: V12 | B16: 01. Vé xe / cổng | C16: P1 | D16: Sửa GIO_VAO/GIO_RA, biển số hoặc loại xe: ai được sửa, giới hạn thời gian và cần bằng chứng gì? | E16: A. Nhân viên sửa trước ra; B. TBP duyệt khi đã ra; C. Mọi sửa phải TBP duyệt. | F16: C | G16: cho phép sửa linh hoạt nhưng có log | H16: Đã chốt | I16: Trưởng BP An ninh | M16: Trao đổi nghiệp vụ Sơn Cảng, 10-11/10/2026
A17: L01 | B17: 02. Lưu container | C17: P0 | D17: Nếu container vào trước 22:00 và ra đúng 22:00, có ghi nhận 1 đêm hay chưa? | E17: A. Tính 1 đêm (>=22:00); B. Chưa tính nếu ra đúng 22:00; C. Theo công thức AppSheet V1 đã nghiệm thu. | F17: A | H17: Đã chốt | I17: Trưởng BP CCKB | M17: Thông báo 22:00–06:00
A18: L02 | B18: 02. Lưu container | C18: P0 | D18: Nếu container vào đúng 06:00 hoặc ra đúng 06:00, quy tắc gán cho kỳ đêm nào? | E18: A. Kỳ đêm kết thúc tại 06:00, ra 06:00 có tính; B. Kết thúc trước 06:00 mới tính; C. Theo V1. | F18: A | H18: Đã chốt | I18: Trưởng BP CCKB | M18: Trao đổi nghiệp vụ Sơn Cảng, 10-11/10/2026
A19: L03 | B19: 02. Lưu container | C19: P0 | D19: Xe vào sau 22:00 (ví dụ 23:30) và ra trước 06:00 (02:00), đêm đó vẫn là 1 đêm miễn phí đúng không? | E19: A. Đúng; B. Chỉ khi qua mốc 06:00; C. Khác. | F19: A | H19: Đã chốt | I19: Trưởng BP CCKB | M19: Trao đổi nghiệp vụ Sơn Cảng, 10-11/10/2026
A20: L04 | B20: 02. Lưu container | C20: P0 | D20: CCKB đã duyệt thanh toán trước 22:00, nhưng container thực tế xuất sau 22:00 và phát sinh thêm kỳ đêm: quy trình cập nhật phí? | E20: A. Hủy hiệu lực xác nhận cũ, tính và thu thêm; B. Khóa phí tại giờ CCKB duyệt; C. Trường hợp ngoại lệ riêng. | F20: B | G20: Vì nhiều lúc thanh toán và rút rồi nhưng chưa ra nhé | H20: Đã chốt | I20: Trưởng BP CCKB + An ninh | M20: Trao đổi nghiệp vụ Sơn Cảng, 10-11/10/2026
A21: L05 | B21: 02. Lưu container | C21: P1 | D21: Container vào ra trong cùng ngày, chưa qua 22:00: SO_DEM_LUU hiển thị 0 hay tối thiểu 1 (miễn phí)? | E21: A. Hiển thị 0; B. Hiển thị 1 (miễn); C. Tách đêm thực tế / đêm tính tiền. | F21: B | H21: Đã chốt | I21: Trưởng BP CCKB | M21: Trao đổi nghiệp vụ Sơn Cảng, 10-11/10/2026
A22: L06 | B22: 02. Lưu container | C22: P1 | D22: Ai được sửa GIO_CONT_VAO/GIO_CONT_RA khi nhập muộn hoặc phát hiện sai? Việc sửa đã thu cần xử lý ra sao? | E22: A. Nhân viên đề xuất/TBP duyệt sau thu; B. TBP tự sửa có lý do; C. Quy trình khác. | F22: A | G22: A và B luôn | H22: Đã chốt | I22: Trưởng BP CCKB + An ninh | M22: Trao đổi nghiệp vụ Sơn Cảng, 10-11/10/2026
A23: L07 | B23: 02. Lưu container | C23: P0 | D23: Xe gốc đã ra nhưng container còn lại: CCKB duyệt tài chính cho lượt xe ra không kéo cont như thế nào? | E23: A. Chỉ cần vé xe; B. Cần xác nhận container tiếp tục ở bãi; C. Cần thêm xác nhận riêng. | F23: Khác | G23: duyệt theo container CCKB k quan tâ tới biểu số xe chỉ số cont | H23: Đã chốt | I23: Trưởng BP CCKB + An ninh | M23: Trao đổi nghiệp vụ Sơn Cảng, 10-11/10/2026
A24: L08 | B24: 02. Lưu container | C24: P1 | D24: Nếu khách muốn trả trước một phần phí lưu container trong khi cont còn ở bãi, có cho phép ghi nhận không? | E24: A. Không; B. Có thanh toán trước, đối trừ khi ra; C. Chỉ nếu TBP duyệt. | F24: A | H24: Đã chốt | I24: Trưởng BP CCKB | M24: Trao đổi nghiệp vụ Sơn Cảng, 10-11/10/2026
A25: L09 | B25: 02. Lưu container | C25: P1 | D25: Đơn giá phí lưu khi thay PRICE_LIST trong thời gian một container đang lưu: giữ giá lúc vào hay áp dụng theo từng kỳ ngày? | E25: A. Chốt tại GIO_CONT_VAO; B. Mỗi kỳ đêm theo bảng giá hiệu lực; C. Điều chỉnh bằng quyết định cụ thể. | F25: B | G25: Cái này khó nhỉ? A và B đi cho linh hoạt | H25: Đã chốt | I25: Trưởng BP CCKB + Quản trị | M25: Trao đổi nghiệp vụ Sơn Cảng, 10-11/10/2026
A26: L10 | B26: 02. Lưu container | C26: P1 | D26: Có cần tính phí lưu cho container chưa xác định HÀNG/RỖNG, hay phải chờ Điều phối xác nhận? | E26: A. Vẫn tính; B. Chặn thanh toán đến khi rõ trạng thái; C. Khác. | F26: A | G26: Vẫn tính, có thể phân quyền lại cho user nào đó đi đếm nhé k nhất thiết điều phôi | H26: Đã chốt | I26: Trưởng BP CCKB + Điều phối | M26: Trao đổi nghiệp vụ Sơn Cảng, 10-11/10/2026
A27: E01 | B27: 03. Cắm/rút điện | C27: P0 | D27: CCKB được tạo phiên cắm/rút và nhập giờ sau khi An ninh báo qua Zalo mà KHÔNG lập trước lệnh trong PWA chứ? | E27: A. Có, được nhập hồi tố và ghi giờ báo; B. Luôn phải lập yêu cầu trước; C. Kết hợp cả hai. | F27: C | G27: Cả 2 đi cho thoải mái | H27: Đã chốt | I27: Trưởng BP CCKB + An ninh | M27: Trao đổi nghiệp vụ Sơn Cảng, 10-11/10/2026
A28: E02 | B28: 03. Cắm/rút điện | C28: P0 | D28: Trường hợp khách yêu cầu cắm/rút trực tiếp với An ninh mà chưa báo CCKB: xử lý nhập và xác minh ra sao? | E28: A. An ninh báo CCKB, nhập sau; B. Không làm khi chưa có CCKB; C. Ngoại lệ theo ca. | F28: Khác | G28: A và B | H28: Đã chốt | I28: Trưởng BP CCKB + An ninh | M28: Trao đổi nghiệp vụ Sơn Cảng, 10-11/10/2026
A29: E03 | B29: 03. Cắm/rút điện | C29: P1 | D29: Hình thức Theo giờ và Cắm liên tục có khác nhau ở cách vận hành/thanh toán hay hiện chỉ khác danh mục yêu cầu? | E29: A. Chỉ khác tên; B. Có quy tắc riêng, ghi cụ thể; C. Sẽ phân biệt ở giai đoạn sau. | F29: A | G29: CHỉ khác là 1 cái biết giờ rút 1 cái chưa | H29: Đã chốt | I29: Trưởng BP CCKB | M29: Trao đổi nghiệp vụ Sơn Cảng, 10-11/10/2026
A30: E04 | B30: 03. Cắm/rút điện | C30: P0 | D30: CCKB nhập GIO_CAM_THUC_TE khi container đã rút rồi: cho phép nhập cả giờ cắm và rút trong một biểu mẫu không? | E30: A. Có; B. Tách thành hai bước bắt buộc; C. Chỉ TBP nhập hồi tố. | F30: A | G30: có cho thoải mái giờ chưa kiểm soát chặt lắm | H30: Đã chốt | I30: Trưởng BP CCKB | M30: Trao đổi nghiệp vụ Sơn Cảng, 10-11/10/2026
A31: E05 | B31: 03. Cắm/rút điện | C31: P0 | D31: Khi An ninh báo giờ cắm/rút không chính xác, CCKB xác minh bằng cách nào trước khi sửa? | E31: A. CCKB chỉnh có ghi chú; B. Cần ảnh tin nhắn Zalo; C. Phải có TBP xác nhận khi chênh lệch lớn. | F31: Khác | G31: Hienj tại khi cắm rút thì an ninh sẽ quay bằng camera time stamp, rồi gửi nhóm | H31: Đã chốt | I31: Trưởng BP CCKB | M31: Trao đổi nghiệp vụ Sơn Cảng, 10-11/10/2026
A32: E06 | B32: 03. Cắm/rút điện | C32: P0 | D32: Sau khi đã thu tiền điện, CCKB được sửa giờ tới mức nào và quy trình phê duyệt chênh lệch? | E32: A. NV tạo đề nghị/TBP CCKB duyệt; B. TBP sửa trực tiếp có nhật ký; C. NV được sửa và ghi lý do (không duyệt). | F32: B | G32: A Và B | H32: Đã chốt | I32: Trưởng BP CCKB | M32: Đồng thuận sơ bộ: cần phê duyệt điều chỉnh sau thu
A33: E07 | B33: 03. Cắm/rút điện | C33: P0 | D33: Phiên điện còn trạng thái Đang cắm trên PWA nhưng thực tế đã rút, container có được xuất không? | E33: A. CCKB bắt buộc hoàn thành ghi nhận trước khi ra; B. TBP duyệt xuất ngoại lệ; C. Khác. | F33: A | G33: Làm cách nào thoai r mái hon, CCKB cứ xác định xe đã được ra thì ra, nếu xe ra đến cổng mà chưa thấy được ra thì gọi hoặc nhắn nhóm có CCKB | H33: Đã chốt | I33: Trưởng BP CCKB + An ninh | M33: Trao đổi nghiệp vụ Sơn Cảng, 10-11/10/2026
A34: E08 | B34: 03. Cắm/rút điện | C34: P1 | D34: Khi không có mạng/không thể cập nhật giờ rút, cần quy trình bàn giao ngoài hệ thống và bổ sung dữ liệu như thế nào? | E34: A. Nhật ký giấy/Zalo rồi nhập lại có giờ nguồn; B. Không cho xuất cho đến khi hệ thống hoạt động; C. Ngoại lệ TBP. | F34: A | G34: chỗ này chưa hiểu | H34: Đã chốt | I34: Trưởng BP CCKB + Quản trị | M34: Trao đổi nghiệp vụ Sơn Cảng, 10-11/10/2026
A35: E09 | B35: 03. Cắm/rút điện | C35: P1 | D35: Tổng thời gian thực tế tính bằng giây hay phút? Ví dụ 4 giờ 00 phút 01 giây có làm tròn thành 4 giờ 15 phút không? | E35: A. Bỏ giây/lấy phút; B. Giữ giây rồi làm tròn block 15 phút; C. Khác. | F35: Khác | G35: Hieện tại CCKB tự làm tròn | H35: Đã chốt | I35: Trưởng BP CCKB | M35: Trao đổi nghiệp vụ Sơn Cảng, 10-11/10/2026
A36: E10 | B36: 03. Cắm/rút điện | C36: P1 | D36: Phiên cắm ngắn dưới 15 phút hoặc vô tình cắm 0 phút: tính tối thiểu 15 phút khi có cắm thực tế không? | E36: A. >0 phút tính 15 phút; B. Có mức tối thiểu khác; C. Không thu dưới ngưỡng. | F36: Khác | G36: Hieện tại CCKB tự làm tròn | H36: Đã chốt | I36: Trưởng BP CCKB | M36: Trao đổi nghiệp vụ Sơn Cảng, 10-11/10/2026
A37: E11 | B37: 03. Cắm/rút điện | C37: P1 | D37: Một container cắm/rút nhiều phiên trong cùng một lần vào bãi: làm tròn 15 phút riêng mỗi phiên hay gộp trước khi làm tròn? | E37: A. Riêng từng phiên; B. Gộp thời gian nhiều phiên; C. Theo hình thức dịch vụ. | F37: A | H37: Đã chốt | I37: Trưởng BP CCKB | M37: Trao đổi nghiệp vụ Sơn Cảng, 10-11/10/2026
A38: E12 | B38: 03. Cắm/rút điện | C38: P1 | D38: Có cho một container ghi nhận hai phiên cắm điện đồng thời hay bắt buộc mỗi thời điểm chỉ có một phiên? | E38: A. Chỉ một phiên hoạt động; B. Có nhiều ổ cắm/điểm cấp điện song song; C. Ngoại lệ. | F38: A | H38: Đã chốt | I38: Trưởng BP CCKB | M38: Trao đổi nghiệp vụ Sơn Cảng, 10-11/10/2026
A39: E13 | B39: 03. Cắm/rút điện | C39: P1 | D39: Khi cập nhật giá điện trong lúc phiên cắm đang chạy: giữ giá lúc bắt đầu hay áp giá mới khi rút? | E39: A. Giữ giá lúc cắm; B. Theo giá lúc rút; C. Chia theo thời điểm đổi giá. | F39: B | G39: tùy A và B | H39: Đã chốt | I39: Trưởng BP CCKB + Quản trị | M39: Trao đổi nghiệp vụ Sơn Cảng, 10-11/10/2026
A40: E14 | B40: 03. Cắm/rút điện | C40: P1 | D40: Có yêu cầu lưu vị trí/ổ cắm/số công tơ/ảnh khi cắm, hay chỉ theo container và giờ thực tế? | E40: A. Chỉ cont và giờ; B. Thêm vị trí ổ cắm; C. Thêm ảnh/công tơ; ghi rõ. | F40: A | G40: có thể cho an ninh điền cái này cx được để họ nhớ, sau này làm sơ đồ cũng dễ | H40: Đã chốt | I40: Trưởng BP CCKB + An ninh | M40: Trao đổi nghiệp vụ Sơn Cảng, 10-11/10/2026
A41: E15 | B41: 03. Cắm/rút điện | C41: P1 | D41: Ai là người được phép sửa danh mục đơn giá cắm điện và có cần TBP/BLĐ phê duyệt mức giá mới? | E41: A. Quản trị; B. Trưởng BP CCKB; C. CCKB đề xuất, Quản trị duyệt; khác. | F41: A | H41: Đã chốt | I41: Trưởng BP CCKB + Quản trị | M41: Trao đổi nghiệp vụ Sơn Cảng, 10-11/10/2026
A42: E16 | B42: 03. Cắm/rút điện | C42: P1 | D42: CCKB có cần chọn người An ninh đã trực tiếp cắm/rút, dù người nhập giờ là CCKB không? | E42: A. Có, bắt buộc chọn; B. Ghi chú tự do; C. Không cần. | F42: B | H42: Đã chốt | I42: Trưởng BP CCKB + An ninh | M42: Trao đổi nghiệp vụ Sơn Cảng, 10-11/10/2026
A43: T01 | B43: 04. Thanh toán | C43: P0 | D43: Có cho thanh toán từng phần phí điện/lưu hoặc nộp trước khi container xuất không? | E43: A. Không, thanh toán đủ theo khoản; B. Có, cho thanh toán một phần; C. Chỉ theo phê duyệt. | F43: B | G43: Linh hoạt thu cả hoặc thu từng phần | H43: Đã chốt | I43: Trưởng BP CCKB | M43: Trao đổi nghiệp vụ Sơn Cảng, 10-11/10/2026
A44: T02 | B44: 04. Thanh toán | C44: P0 | D44: Một lần thanh toán có thể kết hợp tiền mặt và chuyển khoản không? | E44: A. Có, ghi mỗi phương thức một phần; B. Không, một giao dịch một phương thức; C. Tùy khoản. | F44: A | H44: Đã chốt | I44: Trưởng BP CCKB | M44: Trao đổi nghiệp vụ Sơn Cảng, 10-11/10/2026
A45: T03 | B45: 04. Thanh toán | C45: P0 | D45: Xác nhận chuyển khoản dựa trên ảnh khách gửi hay bắt buộc kiểm tra tài khoản công ty thực nhận? | E45: A. Kiểm tra tiền về; B. Ảnh biên lai được chấp nhận; C. Theo ngưỡng tiền và quyền. | F45: A | G45: CCKB tự xác định tiền cắm còn Lưu đêm và vé vào thì an ninh | H45: Đã chốt | I45: Trưởng BP CCKB + Kế toán | M45: Trao đổi nghiệp vụ Sơn Cảng, 10-11/10/2026
A46: T04 | B46: 04. Thanh toán | C46: P0 | D46: Ảnh bằng chứng thu tiền cần bắt buộc với giao dịch nào (vé, lưu cont, điện, mất vé)? | E46: A. Mọi chuyển khoản; B. Mọi giao dịch; C. Chỉ theo quy định từng loại. | F46: Khác | G46: Xây dưng nhưng chưa ap dụng | H46: Đã chốt | I46: Trưởng BP An ninh + CCKB | M46: Trao đổi nghiệp vụ Sơn Cảng, 10-11/10/2026
A47: T05 | B47: 04. Thanh toán | C47: P1 | D47: Khoản phạt mất vé được thanh toán và đối soát như một dòng phí riêng hay gộp cùng tiền vé ban đầu? | E47: A. Tách khoản phí riêng; B. Gộp vào vé; C. Tùy thời điểm phát hiện. | F47: A | H47: Đã chốt | I47: Trưởng BP An ninh + CCKB | M47: Trao đổi nghiệp vụ Sơn Cảng, 10-11/10/2026
A48: T06 | B48: 04. Thanh toán | C48: P0 | D48: Nếu đã thu thiếu hoặc thừa tiền so với hệ thống: cách điều chỉnh/hoàn trả, ai duyệt? | E48: A. NV lập phiếu, TBP duyệt; B. Chỉ Quản trị; C. Quy trình khác. | F48: Khác | G48: Xây dưng nhưng chưa ap dụng | H48: Đã chốt | I48: Trưởng BP CCKB | M48: Trao đổi nghiệp vụ Sơn Cảng, 10-11/10/2026
A49: T07 | B49: 04. Thanh toán | C49: P0 | D49: Có được miễn/giảm giá vé, phí lưu, tiền điện? Ai là người có quyền duyệt? | E49: A. TBP theo bộ phận; B. Quản trị; C. Ban lãnh đạo; tùy loại phí. | F49: Khác | G49: Xây dưng nhưng chưa ap dụng | H49: Đã chốt | I49: Ban quản lý Sơn Cảng | M49: Trao đổi nghiệp vụ Sơn Cảng, 10-11/10/2026
A50: T08 | B50: 04. Thanh toán | C50: P0 | D50: Có cho xuất container khi còn nợ phí hoặc đã gửi chứng từ nhưng chưa xác minh nhận tiền không? | E50: A. Không; B. Cho phép nếu TBP phê duyệt; C. Công nợ khách hàng theo danh sách. | F50: Khác | G50: CCKB sẽ xác nhận cho ra hay k và có thể báo cho ra nhưng tiền chưa thusex hiện cảnh báo, 1 là tự động nếu cckb đã điền đủ thanh toán và có cái xác nhận cho xe ra bằng tay mà tiền chưa ghi nhận | H50: Đã chốt | I50: Trưởng BP CCKB | M50: Trao đổi nghiệp vụ Sơn Cảng, 10-11/10/2026
A51: T09 | B51: 04. Thanh toán | C51: P0 | D51: Tại cổng ra, trạng thái tài chính hợp lệ có thời hạn bao lâu trước khi phải tính lại phí lưu? | E51: A. Luôn tính lại lúc xe/cont thực ra; B. CCKB xác nhận hiệu lực n phút; C. Chốt theo giờ duyệt. | F51: A | G51: Phí lưu chỉ có AN ninh tính tại lúc ra | H51: Đã chốt | I51: Trưởng BP CCKB + An ninh | M51: Trao đổi nghiệp vụ Sơn Cảng, 10-11/10/2026
A52: T10 | B52: 04. Thanh toán | C52: P1 | D52: Khi xe ra không kéo container, An ninh có cần CCKB xác nhận tài chính riêng cho LƯỢT XE không? | E52: A. Chỉ kiểm tra vé đã thu; B. CCKB duyệt tất cả lượt ra; C. Chỉ duyệt xe có cont. | F52: A | G52: K cần xác nhận nếu k có cont ra vì CCKB chỉ quan tâm cont chứ xe k quan tâm | H52: Đã chốt | I52: Trưởng BP CCKB + An ninh | M52: Trao đổi nghiệp vụ Sơn Cảng, 10-11/10/2026
A53: T11 | B53: 04. Thanh toán | C53: P1 | D53: CCKB có được thu hộ nhiều container/xe trong một lần chuyển khoản và phân bổ vào nhiều khoản phí không? | E53: A. Có, phân bổ khoản; B. Không, mỗi lần cho một đối tượng; C. Có điều kiện. | F53: A | G53: Linh hoạt như nào dễ cho ng dùng thì làm | H53: Đã chốt | I53: Trưởng BP CCKB | M53: Trao đổi nghiệp vụ Sơn Cảng, 10-11/10/2026
A54: T12 | B54: 04. Thanh toán | C54: P1 | D54: Khi có khách hàng thường xuyên: có quản lý hồ sơ khách, mã số thuế, công nợ/hóa đơn không? | E54: A. V1 chỉ tên/số điện thoại; B. Quản lý danh mục khách hàng; C. Thêm công nợ/hóa đơn. | F54: Không áp dụng | G54: Sau này có nhé, vì bên Kế toán cũng muốn joint vào hệ thông này ví dụ ở trên vé vào hienejt ại an ninh điền thông tin lái xe hoặc thông tin công ty để xuất hóa đơn, có cái xuất có cái k xuất nhé, xong kế toán cũng cần tổng hợp và điền báo cáo nữa.) Các thông tin cần điền(Họ tên/Tên công ty, Mã só thuế/số CCCD, thương trú, có thể sđt n, e mail nữa | H54: Đã chốt | I54: Trưởng BP CCKB + Kế toán | M54: Trao đổi nghiệp vụ Sơn Cảng, 10-11/10/2026
A55: T13 | B55: 04. Thanh toán | C55: P1 | D55: Có cho hủy giao dịch thu tiền do nhập nhầm? Yêu cầu lý do/phê duyệt và xử lý dòng đối ứng? | E55: A. Chỉ tạo giao dịch đảo; B. Cho hủy với duyệt; C. Khác. | F55: B | G55: Linh hoạt như nào dễ cho ng dùng thì làm | H55: Đã chốt | I55: Trưởng BP CCKB | M55: Trao đổi nghiệp vụ Sơn Cảng, 10-11/10/2026
A56: T14 | B56: 04. Thanh toán | C56: P1 | D56: Doanh thu vé An ninh thu và doanh thu phí CCKB thu được đối soát cuối ca như thế nào? | E56: A. Theo cá nhân/ca; B. Theo bộ phận/ngày; C. Hai cấp đối soát; ghi quy định. | F56: Khác | G56: theo ca nhé, ca lammf việc của an ninh hiện tại là 6H-18H nhưng chốt doanh thu có thẻ là 16H và 8h30 9H kiểu vậy | H56: Đã chốt | I56: Trưởng BP An ninh + CCKB + Kế toán | M56: Trao đổi nghiệp vụ Sơn Cảng, 10-11/10/2026
A57: T15 | B57: 04. Thanh toán | C57: P1 | D57: Sau khi CCKB đã cấp đủ điều kiện thanh toán, An ninh phát hiện sai số cont/biển số: có quyền hủy xác nhận và gửi duyệt lại không? | E57: A. Tự hủy và yêu cầu kiểm tra; B. Chỉ CCKB thu hồi; C. TBP duyệt. | F57: Không áp dụng | H57: Đã chốt | I57: Trưởng BP An ninh + CCKB | M57: Trao đổi nghiệp vụ Sơn Cảng, 10-11/10/2026
A58: P01 | B58: 05. Phân quyền | C58: P0 | D58: Các vai trò chính xác cần tạo là 6 vai trò NV/TBP của 3 bộ phận + Quản trị, hay bổ sung Nhà cân/Kế toán? | E58: A. 7 vai trò; B. Thêm Nhà cân; C. Thêm Kế toán; ghi rõ. | F58: C | H58: Đã chốt | I58: Quản trị + Các TBP | M58: Trao đổi nghiệp vụ Sơn Cảng, 10-11/10/2026
A59: P02 | B59: 05. Phân quyền | C59: P0 | D59: TBP An ninh có được sửa GIO_VAO/GIO_RA và xuất xe thay NV An ninh không? | E59: A. Có; B. Chỉ duyệt sửa, không thực hiện; C. Tùy chức năng. | F59: A | G59: ghi lại audit | H59: Đã chốt | I59: Trưởng BP An ninh | M59: Trao đổi nghiệp vụ Sơn Cảng, 10-11/10/2026
A60: P03 | B60: 05. Phân quyền | C60: P0 | D60: TBP CCKB có quyền duyệt điều chỉnh sau thu, duyệt miễn giảm và duyệt xuất ngoại lệ đến hạn mức nào? | E60: A. Toàn bộ; B. Giới hạn theo số tiền; C. Phải chuyển Quản trị/BLĐ. | F60: A | G60: ghi lại audit | H60: Đã chốt | I60: Trưởng BP CCKB | M60: Trao đổi nghiệp vụ Sơn Cảng, 10-11/10/2026
A61: P04 | B61: 05. Phân quyền | C61: P1 | D61: NV CCKB có được sửa giờ điện trước thanh toán không giới hạn hay chỉ trong ca/24 giờ? | E61: A. Không giới hạn trước thu; B. Trong ca; C. Theo thời hạn khác. | F61: A | G61: được | H61: Đã chốt | I61: Trưởng BP CCKB | M61: Trao đổi nghiệp vụ Sơn Cảng, 10-11/10/2026
A62: P05 | B62: 05. Phân quyền | C62: P1 | D62: TBP Điều phối có được sửa HÀNG/RỖNG sau khi container xuất bãi không? | E62: A. Có, kèm lý do; B. Chỉ trước khi xuất; C. Quản trị sửa sau xuất. | F62: A | H62: Đã chốt | I62: Trưởng BP Điều phối | M62: Trao đổi nghiệp vụ Sơn Cảng, 10-11/10/2026
A63: P06 | B63: 05. Phân quyền | C63: P1 | D63: Ai có quyền mở khóa/xử lý dữ liệu đã chốt sau ra cổng mà không làm thay đổi lịch sử thu tiền? | E63: A. Quản trị; B. TBP liên quan + xác nhận; C. Quy trình 2 cấp. | F63: B | H63: Đã chốt | I63: Quản trị + Các TBP | M63: Trao đổi nghiệp vụ Sơn Cảng, 10-11/10/2026
A64: P07 | B64: 05. Phân quyền | C64: P1 | D64: Một nhân viên có thể kiêm 2 bộ phận/vai trò trên một tài khoản không? | E64: A. Một tài khoản nhiều vai trò; B. Một vai trò; C. Theo ca. | F64: Khác | G64: Cài này có lúc theo ca có lúc 1 tk nhiêu role nhưng cứ xây dựng giai đoạn đầu máy sẽ cố định tại bốt cont CCKB thì sẽ đăng nhập tk cá nhân(Sau này muốn phát triển ai có ca mới được vào) | H64: Đã chốt | I64: Quản trị | M64: Trao đổi nghiệp vụ Sơn Cảng, 10-11/10/2026
A65: P08 | B65: 05. Phân quyền | C65: P1 | D65: Cần tạo tài khoản mới bằng email công ty hay dùng email Gmail hiện có để đăng nhập? | E65: A. Google login email sẵn có; B. Email công ty; C. Email/mật khẩu độc lập. | F65: C | H65: Đã chốt | I65: Quản trị | M65: Trao đổi nghiệp vụ Sơn Cảng, 10-11/10/2026
A66: P09 | B66: 05. Phân quyền | C66: P1 | D66: Người dùng bị khóa/nghỉ việc thì dữ liệu lịch sử và quyền đăng nhập được xử lý thế nào? | E66: A. Vô hiệu hóa, giữ lịch sử; B. Quy trình khác. | F66: A | H66: Đã chốt | I66: Quản trị | M66: Trao đổi nghiệp vụ Sơn Cảng, 10-11/10/2026
A67: P10 | B67: 05. Phân quyền | C67: P1 | D67: CCKB có quyền xem và điều chỉnh trạng thái vé An ninh thu hay chỉ đọc? | E67: A. Chỉ xem; B. Có quyền báo sai lệch; C. Được chỉnh sau duyệt. | F67: A | H67: Đã chốt | I67: Trưởng BP An ninh + CCKB | M67: Trao đổi nghiệp vụ Sơn Cảng, 10-11/10/2026
A68: D01 | B68: 06. Điều phối / container | C68: P0 | D68: Điều phối nhập HÀNG/RỖNG lúc nào và có được để trống khi container vừa vào không? | E68: A. Bắt buộc trước khi tiếp nhận; B. Được trống, hoàn thiện trước ra; C. Linh hoạt theo ca. | F68: B | G68: được trống | H68: Đã chốt | I68: Trưởng BP Điều phối | M68: Trao đổi nghiệp vụ Sơn Cảng, 10-11/10/2026
A69: D02 | B69: 06. Điều phối / container | C69: P1 | D69: Nếu Điều phối thay đổi HÀNG thành RỖNG (hoặc ngược lại), có cần ghi lý do/người xác nhận không? | E69: A. Có; B. Chỉ khi đã chốt; C. Khác. | F69: A | G69: ghi lí do k bắt bược | H69: Đã chốt | I69: Trưởng BP Điều phối | M69: Trao đổi nghiệp vụ Sơn Cảng, 10-11/10/2026
A70: D03 | B70: 06. Điều phối / container | C70: P0 | D70: Xe vào mang container A, ra nhận container B: ai ghép ID_CONTAINER_RA với lượt xe ở bước cuối? | E70: A. An ninh chọn; B. Điều phối chỉ định, An ninh xác nhận; C. CCKB chọn. | F70: A | H70: Đã chốt | I70: Trưởng BP An ninh + Điều phối | M70: Trao đổi nghiệp vụ Sơn Cảng, 10-11/10/2026
A71: D04 | B71: 06. Điều phối / container | C71: P1 | D71: Có quản lý vị trí container (khu/bãi/dãy/ô) khi hạ, khi xếp lên xe hay chỉ kiểm soát có/không trong bãi? | E71: A. Chỉ trong bãi; B. Khu vực; C. Định vị ô/kệ. | F71: Khác | G71: Cả 3 luôn nhưng giai đoạn đâu chưa, phát triển phase sau | H71: Đã chốt | I71: Trưởng BP Điều phối | M71: Trao đổi nghiệp vụ Sơn Cảng, 10-11/10/2026
A72: D05 | B72: 06. Điều phối / container | C72: P1 | D72: Một số container có thể vào/ra bãi nhiều lần: hệ thống có cần hiển thị lịch sử theo số cont và phân biệt bằng lượt ID không? | E72: A. Có, lịch sử nhiều lượt; B. Quy tắc khác. | F72: A | H72: Đã chốt | I72: Trưởng BP Điều phối + Quản trị | M72: Trao đổi nghiệp vụ Sơn Cảng, 10-11/10/2026
A73: D06 | B73: 06. Điều phối / container | C73: P1 | D73: Khi số container gõ nhầm hoặc khác so với trên vé, người nào được xác nhận sửa thông tin? | E73: A. An ninh sửa trước ra; B. Điều phối duyệt; C. TBP An ninh duyệt. | F73: A | G73: TBP thì sửa trực tiếp | H73: Đã chốt | I73: Trưởng BP Điều phối + An ninh | M73: Trao đổi nghiệp vụ Sơn Cảng, 10-11/10/2026
A74: R01 | B74: 07. Báo cáo / đối soát | C74: P1 | D74: Báo cáo doanh thu yêu cầu chi tiết theo ca, ngày, tháng, loại phí, nhân viên, bộ phận hay tổng hợp nào? | E74: A. Tất cả; B. Theo nhóm được chọn; C. Báo cáo mẫu riêng. | F74: A | H74: Đã chốt | I74: Các TBP + Kế toán | M74: Trao đổi nghiệp vụ Sơn Cảng, 10-11/10/2026
A75: R02 | B75: 07. Báo cáo / đối soát | C75: P1 | D75: Cần giao ca trên PWA với số dư tiền mặt, biên bản đối soát, người bàn giao/người nhận không? | E75: A. Có; B. Chỉ báo cáo cuối ca; C. Giao ca ngoài hệ thống. | F75: C | G75: Trc mắt ngoài hệ thống | H75: Đã chốt | I75: Trưởng BP An ninh + CCKB | M75: Trao đổi nghiệp vụ Sơn Cảng, 10-11/10/2026
A76: R03 | B76: 07. Báo cáo / đối soát | C76: P1 | D76: Cần bảng theo dõi xe quá hạn, container còn lưu nhiều ngày, điện chưa rút, chưa thu tiền và thông báo tự động không? | E76: A. Có tất cả; B. Chỉ danh sách; C. Chọn cảnh báo cụ thể. | F76: A | H76: Đã chốt | I76: Các TBP | M76: Trao đổi nghiệp vụ Sơn Cảng, 10-11/10/2026
A77: R04 | B77: 07. Báo cáo / đối soát | C77: P2 | D77: Các báo cáo xuất Excel/PDF có cần theo mẫu nội bộ và phân quyền người tải xuống? | E77: A. Excel; B. Excel + PDF; C. Có mẫu ban hành. | F77: B | H77: Đã chốt | I77: Các TBP | M77: Trao đổi nghiệp vụ Sơn Cảng, 10-11/10/2026
A78: R05 | B78: 07. Báo cáo / đối soát | C78: P1 | D78: Người quản lý muốn dashboard thời gian thực chỉ số nào: xe trong bãi, cont trong bãi, cont đang cắm, doanh thu, công nợ? | E78: A. Tất cả; B. Chọn KPI cụ thể; C. Xem theo bộ phận. | F78: A | H78: Đã chốt | I78: Ban quản lý Sơn Cảng | M78: Trao đổi nghiệp vụ Sơn Cảng, 10-11/10/2026
A79: R06 | B79: 07. Báo cáo / đối soát | C79: P1 | D79: Có bắt buộc đối chiếu sao kê chuyển khoản với chứng từ và ghi lịch sử xác minh trên PWA không? | E79: A. Có; B. Đối soát ngoài hệ thống; C. Theo hạn mức. | F79: B | H79: Đã chốt | I79: Trưởng BP CCKB + Kế toán | M79: Trao đổi nghiệp vụ Sơn Cảng, 10-11/10/2026
A80: R07 | B80: 07. Báo cáo / đối soát | C80: P2 | D80: Các báo cáo cần tự động gửi qua email/Zalo theo lịch hay chỉ xem khi đăng nhập? | E80: A. Chỉ trong app; B. Gửi email; C. Tích hợp Zalo sau. | F80: B | G80: cả 3, zalo thì sau | H80: Đã chốt | I80: Ban quản lý Sơn Cảng | M80: Trao đổi nghiệp vụ Sơn Cảng, 10-11/10/2026
A81: K01 | B81: 08. Kỹ thuật / bảo mật | C81: P0 | D81: Phần mềm chạy trên tên miền/subdomain nào và ai chịu trách nhiệm quản trị máy chủ? | E81: A. Subdomain talunglogistics.com; B. Domain riêng; C. Chưa quyết. | H81: Đã chốt | I81: Quản trị + CNTT | M81: Trao đổi nghiệp vụ Sơn Cảng, 10-11/10/2026
A82: K02 | B82: 08. Kỹ thuật / bảo mật | C82: P0 | D82: Cơ sở dữ liệu, backend, hosting chọn theo phương án nào? Có yêu cầu dữ liệu lưu tại Việt Nam không? | E82: A. Đề xuất Next.js + PostgreSQL; B. Hạ tầng đang có; C. Phương án khác (cần thẩm định). | F82: A | G82: công cụ free supabase, vercel | H82: Đã chốt | I82: CNTT + Ban quản lý | M82: Trao đổi nghiệp vụ Sơn Cảng, 10-11/10/2026
A83: K03 | B83: 08. Kỹ thuật / bảo mật | C83: P0 | D83: Khi mất Internet tại cổng: cho phép nhập lượt xe offline nhưng chặn xác nhận xuất, hay cho phép xuất theo quy trình ngoại lệ? | E83: A. Offline chỉ nhập/đợi đồng bộ; B. Cho xuất ngoại lệ có chứng từ/TBP; C. Chỉ online. | F83: A | H83: Đã chốt | I83: CNTT + Trưởng BP An ninh + CCKB | M83: Trao đổi nghiệp vụ Sơn Cảng, 10-11/10/2026
A84: K04 | B84: 08. Kỹ thuật / bảo mật | C84: P0 | D84: PWA dùng điện thoại cá nhân hay thiết bị công ty? Có yêu cầu camera chụp chứng từ/quét QR số container không? | E84: A. Điện thoại + PC; B. Thiết bị công ty; C. Cần đầu đọc/QR. | F84: A | G84: A và B | H84: Đã chốt | I84: CNTT + Các TBP | M84: Trao đổi nghiệp vụ Sơn Cảng, 10-11/10/2026
A85: K05 | B85: 08. Kỹ thuật / bảo mật | C85: P1 | D85: Có cần bắt buộc đăng nhập 2 yếu tố với quản trị/TBP, phân quyền theo phiên đăng nhập/thiết bị không? | E85: A. 2FA cho TBP/Quản trị; B. Toàn bộ; C. SSO Google. | F85: Khác | G85: Chưa áp dụng nhưng có thì tốt | H85: Đã chốt | I85: CNTT | M85: Trao đổi nghiệp vụ Sơn Cảng, 10-11/10/2026
A86: K06 | B86: 08. Kỹ thuật / bảo mật | C86: P1 | D86: Ảnh thu tiền và chứng từ cần lưu bao lâu, dung lượng giới hạn, ai có quyền xem/xóa? | E86: A. Theo thời hạn công ty; B. Tối thiểu 3 năm; C. Theo quy định cụ thể. | F86: A | G86: Chưa áp dụng, lưu trên đâu đó free, cloudflrae R2 10G | H86: Đã chốt | I86: CNTT + Kế toán | M86: Trao đổi nghiệp vụ Sơn Cảng, 10-11/10/2026
A87: K07 | B87: 08. Kỹ thuật / bảo mật | C87: P1 | D87: Tần suất sao lưu, khôi phục sau sự cố và lưu bản sao dữ liệu ở đâu? | E87: A. Hằng ngày; B. Nhiều lần/ngày; C. Yêu cầu cụ thể. | F87: A | H87: Đã chốt | I87: CNTT | M87: Trao đổi nghiệp vụ Sơn Cảng, 10-11/10/2026
A88: K08 | B88: 08. Kỹ thuật / bảo mật | C88: P1 | D88: Cần môi trường thử nghiệm và chính thức riêng biệt, đồng thời có nhật ký thao tác chi tiết không? | E88: A. Có cả hai + audit; B. Một môi trường; C. Lộ trình khác. | F88: A | H88: Đã chốt | I88: CNTT | M88: Trao đổi nghiệp vụ Sơn Cảng, 10-11/10/2026
A89: K09 | B89: 08. Kỹ thuật / bảo mật | C89: P2 | D89: Giai đoạn đầu có cần tích hợp Zalo thông báo lệnh cắm/rút tự động không? | E89: A. Không, tiếp tục Zalo thủ công; B. Nhắc qua kênh khác; C. Tích hợp khi khả thi. | F89: A | G89: A B C | H89: Đã chốt | I89: CNTT + CCKB | M89: Trao đổi nghiệp vụ Sơn Cảng, 10-11/10/2026
A90: M01 | B90: 09. Chuyển dữ liệu | C90: P0 | D90: Phạm vi chuyển dữ liệu AppSheet: toàn bộ lịch sử VEHICLE/CONTAINER hay chỉ bản ghi đang hoạt động + lưu kho lịch sử? | E90: A. Toàn bộ; B. Đang hoạt động + kho lưu lịch sử; C. Từ một mốc ngày. | F90: A | H90: Đã chốt | I90: CNTT + Các TBP | M90: Tập dữ liệu AppSheet do Sơn Cảng cung cấp
A91: M02 | B91: 09. Chuyển dữ liệu | C91: P0 | D91: Ngày/giờ chốt dữ liệu và đóng AppSheet để chuyển sang PWA là khi nào? | E91: A. Sau UAT; B. Chạy song song ngắn hạn; C. Cần kế hoạch chi tiết. | F91: A | H91: Đã chốt | I91: CNTT + Ban quản lý | M91: Trao đổi nghiệp vụ Sơn Cảng, 10-11/10/2026
A92: M03 | B92: 09. Chuyển dữ liệu | C92: P0 | D92: Các dòng dữ liệu cũ có ghi chú tiền thực thu khác tiền phải thu: ai là người kiểm tra, xác nhận kết quả trước chuyển? | E92: A. TBP CCKB; B. Kế toán + CCKB; C. Nhóm đối soát liên BP. | F92: Khác | G92: Tiền thì tạm thời bỏ qua vò giờ trên hệ thống nhiều xe quên chưa cho ra lắ | H92: Đã chốt | I92: Trưởng BP CCKB + Kế toán | M92: CONTAINER V1: xem 08_DOI_SOAT
A93: M04 | B93: 09. Chuyển dữ liệu | C93: P0 | D93: Giờ ra xe/container thực tế khác dữ liệu nhập do bổ sung muộn: dùng mốc nào làm dữ liệu gốc khi chuyển? | E93: A. Giờ hệ thống; B. Giờ trên chứng từ đã xác minh; C. Tùy từng dòng có xác nhận. | F93: A | G93: quan trị viên cấp cao có thể sửa trực tiếp hết nhé, vì hiện tại tôi thấy lỗi nhieuf chính trên GG sheets đang đễ sau này sửa thì vào db sửa lại khó hơn | H93: Đã chốt | I93: An ninh + CCKB + CNTT | M93: Dữ liệu VEHICLE/CONTAINER có ghi chú chỉnh ngày
A94: M05 | B94: 09. Chuyển dữ liệu | C94: P1 | D94: Mã ID cũ trong AppSheet cần giữ làm khóa tham chiếu hay chỉ lưu LEGACY_ID để tra cứu? | E94: A. Giữ ID cũ; B. Sinh ID mới và lưu LEGACY_ID; C. Khác. | F94: A | H94: Đã chốt | I94: CNTT | M94: Trao đổi nghiệp vụ Sơn Cảng, 10-11/10/2026
A95: M06 | B95: 09. Chuyển dữ liệu | C95: P1 | D95: Tài khoản Google cũ cần phân sang 7 vai trò PWA như thế nào và có vô hiệu hóa tài khoản nào không? | E95: A. Map theo bảng 07_TAI_KHOAN; B. Tạo tài khoản mới; C. Kết hợp. | F95: B | H95: Đã chốt | I95: Quản trị + Các TBP | M95: Trao đổi nghiệp vụ Sơn Cảng, 10-11/10/2026
A96: M07 | B96: 09. Chuyển dữ liệu | C96: P1 | D96: Các container cùng SO_CONTAINER xuất hiện ở nhiều lượt: muốn lưu lịch sử theo mỗi lượt hay hồ sơ container dùng lại nhiều lần? | E96: A. Hồ sơ container + lượt ra/vào; B. Mỗi lượt là một bản ghi; C. Thiết kế lai. | F96: A | H96: Đã chốt | I96: CNTT + Điều phối | M96: Trao đổi nghiệp vụ Sơn Cảng, 10-11/10/2026
A97: M08 | B97: 09. Chuyển dữ liệu | C97: P1 | D97: Dữ liệu cắm điện AppSheet trước đây có nhập vào PWA cùng lúc không, hay triển khai riêng từ ngày vận hành mới? | E97: A. Chuyển toàn bộ; B. Chỉ phiên đang cắm/chưa thu; C. Bắt đầu mới và lưu lịch sử cũ. | F97: Khác | G97: CHưa có những sẽ chuyneenr 1 số cái tồn | H97: Đã chốt | I97: CNTT + CCKB | M97: Trao đổi nghiệp vụ Sơn Cảng, 10-11/10/2026
A98: U01 | B98: 10. Nghiệm thu / triển khai | C98: P0 | D98: Ai đại diện mỗi bộ phận ký nghiệm thu và xác nhận nghiệp vụ chuẩn trước chuyển hệ thống? | E98: A. 3 TBP + CNTT; B. Có Ban quản lý/BLĐ; C. Tổ UAT chỉ định. | F98: Không áp dụng | H98: Đã chốt | I98: Ban quản lý Sơn Cảng | M98: Trao đổi nghiệp vụ Sơn Cảng, 10-11/10/2026
A99: U02 | B99: 10. Nghiệm thu / triển khai | C99: P0 | D99: Điều kiện bắt buộc để ngừng AppSheet: chốt chuyển dữ liệu, đối soát tài chính, không lỗi chặn cổng ra, hoàn thành đào tạo? | E99: A. Tất cả; B. Tiêu chí chốt riêng; C. Theo giai đoạn. | F99: A | H99: Đã chốt | I99: Ban quản lý + CNTT | M99: Trao đổi nghiệp vụ Sơn Cảng, 10-11/10/2026
A100: U03 | B100: 10. Nghiệm thu / triển khai | C100: P1 | D100: Nếu PWA gặp lỗi trong tuần đầu, quy trình quay lại AppSheet hoặc ghi giấy tạm thời và đồng bộ lại dữ liệu thế nào? | E100: A. Quy trình dự phòng bằng giấy; B. Tạm quay về AppSheet có kế hoạch hòa giải; C. Khác. | F100: A | H100: Đã chốt | I100: CNTT + An ninh + CCKB | M100: Trao đổi nghiệp vụ Sơn Cảng, 10-11/10/2026
A101: U04 | B101: 10. Nghiệm thu / triển khai | C101: P1 | D101: Đào tạo nhân viên theo bộ phận, cần thao tác thử trước khi cấp quyền thật và phân công người hỗ trợ ca đêm không? | E101: A. Có đào tạo + UAT; B. Chỉ hướng dẫn nhanh; C. Kế hoạch riêng. | F101: A | H101: Đã chốt | I101: CNTT + Các TBP | M101: Trao đổi nghiệp vụ Sơn Cảng, 10-11/10/2026
...

Sheet 13_V4_QUY_TAC
A1: V4 | QUY TẮC ĐÃ CHUẨN HÓA
A2: Giữ nguyên toàn bộ 117 câu trả lời tab 01. Các mục “Đã chốt mới” phản ánh quyết định của người dùng sau khi điền Excel.
A4: Mã | B4: Phân hệ | C4: Trạng thái | D4: Quy tắc / mô tả chính thức | E4: Căn cứ | F4: Ưu tiên | G4: Phạm vi
A5: BG-01 | B5: Phạm vi | C5: Đã chốt | D5: Website + PWA thay AppSheet sau UAT và chuyển dữ liệu; triển khai cả cổng, container, điện, thu tiền, báo cáo. | E5: Trao đổi; U02 | F5: P0 | G5: V1
A6: BG-02 | B6: Tên gọi | C6: Đã chốt | D6: Sử dụng thuật ngữ “Phần mềm quản lý bến bãi/cảng cạn” trong đặc tả CNTT. | E6: Quy định TLQM | F6: P1 | G6: V1
A7: GT-01 | B7: Cổng vào | C7: Đã chốt | D7: An ninh ghi nhận lượt xe vào, loại xe, biển số theo yêu cầu loại xe, container kéo theo và GIO_VAO. | E7: V09,V10, trao đổi | F7: P0 | G7: V1
A8: GT-02 | B8: Vé xe | C8: Đã chốt | D8: Xe container thu vé 250.000đ khi vào; đầu kéo không container 0đ; đầu kéo 0đ vào rồi ra kéo container KHÔNG thu bổ sung 250.000đ. | E8: PRICE_LIST,V01,V03 | F8: P0 | G8: V1
A9: GT-03 | B9: Vé xe | C9: Đã chốt | D9: Các mã/giá khác giữ PRICE_LIST gốc: bo 4 chân 200k, bo 3 chân 200k, bo 8 tấn/2 chân 100k, bo ba bánh 40k, xe sang tải 0đ. | E9: PRICE_LIST | F9: P0 | G9: V1
A10: GT-04 | B10: Kiểm soát | C10: Đã chốt | D10: Mặc định An ninh thu vé lúc xe vào, có trường hợp hiếm thu sau; khi thu sau phải để trạng thái Chưa thu. | E10: V02,T03 | F10: P0 | G10: V1
A11: GT-05 | B11: Nhận diện | C11: Đã chốt | D11: Xe bo ba bánh không bắt buộc biển số, tạo ID lượt/mã vé để tìm khi ra; xe không kéo cont không cần số container. | E11: V04, trao đổi | F11: P1 | G11: V1
A12: GT-06 | B12: Vé giấy | C12: Đã chốt | D12: Duy trì vé giấy hai liên; mất liên 02 phát sinh khoản phạt 250.000đ riêng. Việc in vé từ PWA làm giai đoạn sau. | E12: V05,V06,T05 | F12: P1 | G12: V1
A13: GT-07 | B13: Lượt xe | C13: Đã chốt | D13: Mỗi lượt xe hiện chỉ mang tối đa 01 container; lượt xe và lượt container độc lập, xe đưa vào có thể khác xe kéo ra. | E13: V10,D03 | F13: P0 | G13: V1
A14: GT-08 | B14: Số container | C14: Đã chốt | D14: Có kéo container thì nhập số cont; tìm theo đủ mã, 7 số cuối; gợi ý mã gần giống nhưng người dùng xác nhận ghép. | E14: V09,PR04,SC07 | F14: P0 | G14: V1
A15: GT-09 | B15: Xuất xe | C15: Đã chốt | D15: Xe ra không kéo cont không đòi CCKB phê duyệt tài chính riêng cho lượt xe; An ninh ghi xe ra. | E15: T10,V11 | F15: P0 | G15: V1
... A55: DL-03 | B55: Chuyển đổi | C55: Đã chốt | D55: Tạo tài khoản đăng nhập mới, map role theo chức năng; ngừng AppSheet sau UAT, có phương án vận hành giấy khi có sự cố. | E55: M06,U02,U03 | F55: P0 | G55: V1

Sheet 14_V4_KICH_BAN
A1: V4 | TÌNH HUỐNG NGHIỆM THU
A2: Tình huống minh họa nghiệp vụ đã chốt. Ô vàng cho người rà soát ghi kết quả chạy thử, không bắt buộc điền trước lập đặc tả.
A4: Mã | B4: Nhóm | C4: Tình huống | D4: Kết quả hệ thống cần đạt | E4: Tham chiếu quy tắc | F4: Mức ưu tiên | G4: Kết quả chạy thử (điền) | H4: Trạng thái kiểm thử (điền)
A5: UAT01 | B5: Vé | C5: CONT_LANH vào kéo cont A | D5: Vé 250k; tạo lượt xe và cont liên kết; bắt buộc số cont | E5: GT-01,GT-02 | F5: P0 | H5: Chưa kiểm thử
A6: UAT02 | B6: Vé | C6: Đầu kéo vào không cont sau đó kéo cont B ra | D6: Vé vào 0đ, không thu thêm 250k; cont B tính lưu riêng lúc ra | E6: GT-02,GT-10 | F6: P0 | H6: Chưa kiểm thử
A7: UAT03 | B7: Vé | C7: Xe sang tải vé 0đ ra/vào | D7: Vẫn có lượt ghi cổng, đánh dấu 0đ/không thu tiền thật | E7: GT-03 | F7: P1 | H7: Chưa kiểm thử
A8: UAT04 | B8: Vé | C8: Xe bo 3 bánh không biển số | D8: Sinh mã lượt/vé, nhập/tra cứu tại cổng ra; giá 40k | E8: GT-05 | F8: P1 | H8: Chưa kiểm thử
A9: UAT05 | B9: Vé | C9: Nhân viên thu vé vào sau do ngoại lệ | D9: Có trạng thái chưa thu và nhật ký bổ sung; không báo Đã thu giả | E9: GT-04 | F9: P0 | H9: Chưa kiểm thử
A10: UAT06 | B10: Vé | C10: Khách mất vé liên 02 | D10: Tạo phí mất vé 250k riêng, không ghi đè vé gốc | E10: GT-06,TT-04 | F10: P1 | H10: Chưa kiểm thử
A11: UAT07 | B11: Xe/cont | C11: Xe chở cont A, hạ A rồi xe ra không cont | D11: Xe ra, cont A tiếp tục trong bãi và tiếp tục tính thời gian; không yêu cầu duyệt CCKB riêng cho xe | E11: GT-07,GT-09,CT-01 | F11: P0 | H11: Chưa kiểm thử
A12: UAT08 | B12: Xe/cont | C12: Xe đem A vào rồi ra cùng A, không hạ | D12: Cont A vẫn tính số kỳ đêm theo giờ vào/ra nếu đủ thời gian | E12: CT-01,CT-02 | F12: P0 | H12: Chưa kiểm thử
A13: UAT09 | B13: Xe/cont | C13: Xe mang A vào rồi ra kéo B | D13: Giữ A trong bãi, chốt B, đúng ID lượt và xe ra | E13: GT-10,CT-01 | F13: P0 | H13: Chưa kiểm thử
A14: UAT10 | B14: Lưu cont | C14: Cont vào trước 22h và ra đúng 22h | D14: Ghi nhận kỳ đêm 22:00, miễn đầu theo giá | E14: CT-03 | F14: P0 | H14: Chưa kiểm thử
A15: UAT11 | B15: Lưu cont | C15: Cont vào 23:30, ra 02:00 sáng hôm sau | D15: Đêm đầu tiên được miễn; không phát sinh tiền lưu | E15: CT-03 | F15: P0 | H15: Chưa kiểm thử
A16: UAT12 | B16: Lưu cont | C16: Cont vào và ra trước 22h cùng ngày | D16: Hiển thị 1 đêm miễn theo L05, tiền 0đ | E16: CT-04 | F16: P1 | H16: Chưa kiểm thử
... A48: UAT44 | B48: Báo cáo | C48: Đối soát ca 06–18, chốt doanh thu khác mốc giờ ca | D48: Tách mốc vận hành ca và mốc chốt tiền; cấu hình/báo cáo riêng | E48: TT-05 | F48: P1 | H48: Chưa kiểm thử

Sheet 15_V4_DIEM_CAN_KIEM
A1: V4 | ĐIỂM CẦN KIỂM TRA
A2: Không phải câu hỏi mới cần điền ngay. Đây là các mâu thuẫn/giới hạn chưa đủ căn cứ trong 117 lựa chọn; cần xử lý trong thiết kế/UAT.
A4: Mã | B4: Vấn đề cần xử lý | C4: Đề xuất hoặc giới hạn thông tin đã có | D4: Đơn vị xác nhận | E4: Ưu tiên | F4: Trạng thái hiện tại | G4: Mã câu V3 | H4: Kết luận duyệt V4 (điền)
A5: RV01 | B5: Giờ cắm/rút chính xác tới giây hay phút? Một phiên 4h00m01s có làm tròn lên 4h15 không? | C5: ĐỀ XUẤT: form nhận phút, backend dùng timestamp thật, làm tròn theo phần lẻ; chưa có xác nhận về cách xử lý giây. | D5: Trưởng BP CCKB | E5: P1 | F5: Chưa chốt kỹ thuật biên | G5: E09
A6: RV02 | B6: Phiên điện 0 phút hoặc dưới 1 phút tính tối thiểu bao nhiêu? | C6: ĐỀ XUẤT: thời lượng >0 tính tối thiểu 15 phút; bằng 0 là dữ liệu chưa hợp lệ, yêu cầu giải trình. | D6: Trưởng BP CCKB | E6: P1 | F6: Chưa chốt kỹ thuật biên | G6: E10
A7: RV03 | B7: Giá điện thay đổi giữa phiên, lấy giá lúc bắt đầu hay lúc rút? | C7: E13 chọn B nhưng ghi chú tùy A/B. Chưa định luật giá mặc định; cần ngày hiệu lực rõ, lịch sử giá. | D7: Quản trị / CCKB | E7: P0 | F7: Cần duyệt rõ | G7: E13
A8: RV04 | B8: Đơn giá phí lưu thay đổi khi cont còn trong bãi, tính theo giờ vào hay từng kỳ đêm? | C8: L09 chọn B nhưng ghi chú A/B linh hoạt; yêu cầu chốt nguyên tắc hiệu lực chính sách. | D8: An ninh / Quản trị | E8: P1 | F8: Cần duyệt rõ | G8: L09
A9: RV05 | B9: CCKB cho ra khi điện vẫn báo Đang cắm nhưng thực tế đã rút, quy trình ghi nhật ký và khắc phục ra sao? | C9: E07 chọn A nhưng diễn giải ưu tiên linh hoạt. Thiết kế cảnh báo + CCKB xác nhận thủ công, cần phê duyệt tiêu chí sử dụng ngoại lệ. | D9: Trưởng BP CCKB | E9: P0 | F9: Cần nghiệm thu tình huống | G9: E07,T08,OUT01
A10: RV06 | B10: Tại bước An ninh ghi giờ ra và tính phí lưu, có cho ra với phí lưu chưa thu theo cơ chế ngoại lệ CCKB không? | C10: T08/OUT01 cho CCKB duyệt nợ nhưng chưa chỉ ra rõ có áp dụng phí lưu phát sinh đúng giờ ra hay không. | D10: Trưởng BP An ninh/CCKB | E10: P0 | F10: Cần xác nhận trách nhiệm | G10: CNT01,T08,OUT01
A11: RV07 | B11: Xe cont thường/cont lạnh sử dụng một mã nội bộ CONT_LANH hay đổi mã chung XE_CONTAINER? | C11: V03 ghi chỉ xe cont 250k và đầu kéo trống 0đ. Đề xuất đổi nhãn hiển thị “Xe container”, không tự thay khóa giá gốc. | D11: An ninh / Quản trị | E11: P1 | F11: Cần duyệt hiển thị | G11: V03
A12: RV08 | B12: Có cần vai trò Kế toán hoạt động V1 hay chỉ khai báo để giai đoạn sau sử dụng? | C12: P01 chọn thêm Kế toán; INV02 chỉ lưu dữ liệu hóa đơn chưa tích hợp; đề xuất tài khoản Kế toán quyền xem danh sách khi sẵn sàng. | D12: Kế toán / Quản trị | E12: P1 | F12: Chưa chốt phạm vi | G12: P01,INV01,INV02
A13: RV09 | B13: Bốt An ninh dùng chung tài khoản/thiết bị: xác định người chịu trách nhiệm mỗi thao tác bằng cơ chế nào? | C13: P07 yêu cầu giai đoạn đầu máy bốt cố định, nhưng báo cáo nhân viên/audit cần người thực hiện; đề xuất PIN ca/đổi người thao tác. | D13: Trưởng BP An ninh / CNTT | E13: P0 | F13: Cần thiết kế bảo mật | G13: P07,P08
A14: RV10 | B14: Các dữ liệu legacy sau chuyển được đánh dấu đúng trạng thái và không tự tính công nợ khi giờ ra đang thiếu. | C14: M03 không muốn đối soát toàn bộ tiền cũ, nhiều xe bỏ sót giờ ra; đề xuất nhóm dữ liệu cần kiểm tra và không phát sinh nghĩa vụ phải thu tự động. | D14: CNTT / An ninh / CCKB | E14: P0 | F14: Cần nghiệm thu kỹ thuật | G14: M01,M03,M04
A15: RV11 | B15: Tự động gửi Zalo và lưu ảnh/chứng từ đến mức nào trong V1? | C15: K09 ghi A/B/C nhưng nhu cầu thực tế Zalo thủ công; đề xuất app có thông báo nội bộ trước, Zalo tích hợp để fase sau. | D15: CNTT / CCKB | E15: P2 | F15: Định hướng giai đoạn | G15: K09,K06
A16: RV12 | B16: Thời điểm khóa chốt doanh thu ca có cố định 06–18 hay linh hoạt theo thời điểm nộp tiền? | C16: T14 cho giờ chốt tiền khác ca làm việc; đề xuất tách ca làm việc, ca thu tiền và mốc báo cáo. | D16: Trưởng BP An ninh / CCKB | E16: P1 | F16: Thiết kế biểu mẫu | G16: T14

Sheet 16_V4_CHANGELOG
A1: V4 | NHẬT KÝ ĐÍNH CHÍNH
A2: Ưu tiên diễn giải mới nhất của người dùng, KHÔNG thay đổi câu trả lời gốc trong tab 01.
A4: STT | B4: Mốc | C4: Nội dung đính chính | D4: Áp dụng từ V4 | E4: Tham chiếu
A5: 1 | B5: Đính chính L04 | C5: Loại bỏ phương án khóa/bảo lưu phí lưu trước 22:00 | D5: Phí lưu chỉ tính theo GIO_CONT_VAO và GIO_CONT_RA thực tế khi container xuất | E5: L04,T09,CNT01
A6: 2 | B6: Trách nhiệm phí lưu | C6: Đính chính người thu phí lưu: An ninh (không phải CCKB) | D6: An ninh chốt/thu phí lưu lúc ra; CCKB xác nhận tài chính cho container | E6: CNT01,T03
A7: 3 | B7: Thời điểm phí điện | C7: Giờ rút điện chốt thời lượng/tiền điện, không ảnh hưởng kỳ đêm | D7: CCKB nhập/sửa giờ cắm/rút thực tế và thu điện; điện có thể thu khi rút/ra | E7: E01,E04,E06
A8: 4 | B8: Điều chỉnh sau thu | C8: Chốt tự làm tròn lên theo 15 phút, CCKB được điều chỉnh có audit | D8: NV đề nghị/TBP phê duyệt hoặc TBP trực tiếp sau thu; giữ giao dịch thu gốc | E8: E06,E09,E10,E11
A9: 5 | B9: Điện dự kiến | C9: Cho tạo trước container vào, phiếu riêng mỗi cont | D9: Bảng yêu cầu dự kiến độc lập, An ninh đối chiếu và liên kết thủ công | E9: PR01-PR07
A10: 6 | B10: Sửa mã cont | C10: An ninh được sửa mã sai, CCKB nhận thông báo | D10: Không mất liên kết/tiền đã thu, trùng mã có cảnh báo, không tự ghép | E10: SC01-SC08
A11: 7 | B11: Cho xuất chưa đủ tiền | C11: CCKB được xác nhận thủ công có lý do khi khoản tiền điện/chung chưa ghi nhận đủ | D11: Cảnh báo công nợ; không tự xóa nợ hoặc tự xác nhận Đã thu | E11: T08,OUT01

Sheet 19_V5_VAI_TRO
A1: V5 — DANH SÁCH VAI TRÒ (ROLE)
A2: 7 vai trò V1 đang hoạt động + Kế toán dự phòng. Không dùng chuỗi tên vai trò trong code để cho phép thao tác.
A4: ROLE_CODE | B4: Tên hiển thị | C4: Bộ phận | D4: Cấp | E4: Kích hoạt V1 | F4: Giai đoạn | G4: Mô tả / phạm vi
A5: SEC_STAFF | B5: Nhân viên An ninh | C5: AN_NINH | D5: Nhân viên | E5: Có | F5: V1 | G5: Kiểm soát cổng, thu vé/phí lưu, ghi xe/cont ra, sửa mã cont có nhật ký.
A6: SEC_LEAD | B6: Trưởng bộ phận An ninh | C6: AN_NINH | D6: Trưởng bộ phận | E6: Có | F6: V1 | G6: Toàn quyền nghiệp vụ An ninh, xem thu ca/bộ phận, xử lý ngoại lệ.
A7: PORT_STAFF | B7: Nhân viên Cổng cảng kho bãi | C7: CCKB | D7: Nhân viên | E7: Có | F7: V1 | G7: Điện dự kiến, nhập/sửa giờ, thu điện, xác nhận tài chính/ngoại lệ có lý do.
A8: PORT_LEAD | B8: Trưởng bộ phận Cổng cảng kho bãi | C8: CCKB | D8: Trưởng bộ phận | E8: Có | F8: V1 | G8: Duyệt điều chỉnh tiền sau thu, xem đối soát, hỗ trợ nhân viên CCKB.
A9: DIS_STAFF | B9: Nhân viên Điều phối | C9: DIEU_PHOI | D9: Nhân viên | E9: Có | F9: V1 | G9: Cập nhật tình trạng container HÀNG/RỖNG trong bãi.
A10: DIS_LEAD | B10: Trưởng bộ phận Điều phối | C10: DIEU_PHOI | D10: Trưởng bộ phận | E10: Có | F10: V1 | G10: Xử lý thay đổi HÀNG/RỖNG sau khi cont đã ra; xem audit BP.
A11: SYS_ADMIN | B11: Quản trị hệ thống | C11: HE_THONG | D11: Quản trị | E11: Có | F11: V1 | G11: Quản trị tài khoản, gán quyền, bảng giá, bảo trì và ngoại lệ có audit.
A12: ACCOUNTING_FUTURE | B12: Kế toán (dự phòng) | C12: KE_TOAN | D12: Chuyên môn | E12: Không | F12: GĐ sau | G12: Chưa bật trong V1; lưu thông tin hóa đơn, mở rộng khi có nghiệp vụ Kế toán.

Sheet 20_V5_DANH_MUC_QUYEN
A1: V5 — DANH MỤC QUYỀN THAO TÁC
A2: Mỗi quyền có mã cố định resource.action. Thêm role/đổi quyền không sửa code; chức năng hoàn toàn mới vẫn phải lập trình.
A4: PERMISSION_CODE | B4: Phân hệ | C4: Thao tác được kiểm soát | D4: Mã câu nguồn | E4: Giai đoạn | F4: Cờ tính năng | G4: Rủi ro | H4: Quy tắc bắt buộc
A5: vehicle.visit.read | B5: Cổng xe | C5: Xem lượt xe trong bãi | D5: Q01,Q03,Q25 | E5: V1 | F5: CORE | G5: Thông thường
A6: vehicle.visit.create | B6: Cổng xe | C6: Tạo lượt xe/giờ vào | D6: Q01 | E6: V1 | F6: CORE | G6: Thông thường
A7: vehicle.visit.update_basic | B7: Cổng xe | C7: Sửa thông tin cơ bản của lượt xe | D7: Q03 | E7: V1 | F7: CORE | G7: Nhạy cảm | H7: Biển số/loại xe; audit trước/sau; không tự viết lại số tiền đã thu.
A8: vehicle.visit.time_correction.request | B8: Cổng xe | C8: Yêu cầu sửa giờ vào sau khi phát sinh tiền | D8: Q03 | E8: V1 | F8: CORE | G8: Nhạy cảm
A9: vehicle.visit.time_correction.approve | B9: Cổng xe | C9: Duyệt sửa giờ vào sau khi phát sinh tiền | D9: Q03 | E9: V1 | F9: CORE | G9: Cao | H9: Không tự duyệt yêu cầu do mình tạo; tách điều chỉnh phí.
A10: ticket.payment.collect | B10: Vé vào | C10: Ghi nhận thu tiền vé xe vào | D10: Q02 | E10: V1 | F10: CORE | G10: Tài chính
A11: ticket.lost_fee.collect | B11: Vé vào | C11: Ghi nhận và thu phạt mất vé | D11: Q20 | E11: V1 | F11: CORE | G11: Tài chính
A12: ticket.paper_number.adjust | B12: Vé vào | C12: Chỉnh số seri vé giấy / in vé | D12: Q04 | E12: GĐ sau | F12: TICKET_AUTOPRINT | G12: Thông thường | H12: Chưa xây theo quyết định V1; vẫn lưu thông tin số vé nếu có.
A13: vehicle.visit.exit_confirm | B13: Cổng ra | C13: Xác nhận lượt xe thực tế ra | D13: Q25 | E13: V1 | F13: CORE | G13: Cao | H13: Bắt buộc server xác thực và chặn bấm đúp; không xác nhận offline.
A14: container.visit.read | B14: Container | C14: Xem lượt container trong bãi | D14: Q05,Q06,Q18 | E14: V1 | F14: CORE | G14: Thông thường
A15: container.visit.create | B15: Container | C15: Tạo lượt container vào và giờ vào | D15: Q05 | E15: V1 | F15: CORE | G15: Thông thường
A16: container.number.correct | B16: Container | C16: Sửa số container trên cùng ID lượt | D16: Q06,Q35 | E16: V1 | F16: CORE | G16: Cao | H16: Ghi số cũ/mới, lý do, người sửa; tự cảnh báo CCKB; giữ nguyên charge/payment và ID.
A17: container.number.discrepancy.view | B17: Container | C17: Xem cảnh báo sai số container | D17: Q35,Q36,Q39 | E17: V1 | F17: CORE | G17: Thông thường
A18: container.number.discrepancy.sec_ack | B18: Container | C18: An ninh xác nhận đã báo CCKB | D18: Q35,Q39 | E18: V1 | F18: CORE | G18: Thông thường
A19: container.number.discrepancy.port_reconcile | B19: Container | C19: CCKB đối chiếu sai số và đóng cảnh báo | D19: Q36,Q38,Q39 | E19: V1 | F19: CORE | G19: Nhạy cảm
A20: container.number.evidence.attach | B20: Chứng từ | C20: Đính kèm ảnh/video xác minh số cont | D20: Q37 | E20: V1 | F20: CORE | G20: Thông thường
A21: container.visit.link_request | B21: Container | C21: Ghép yêu cầu dự kiến vào lượt cont vào | D21: Q34 | E21: V1 | F21: CORE | G21: Nhạy cảm | H21: Chỉ xác nhận thủ công, không auto-ghép từ mã gần giống.
A22: container.cargo.read | B22: Điều phối | C22: Xem HÀNG/RỖNG | D22: Q08,Q09 | E22: V1 | F22: CORE | G22: Thông thường
A23: container.cargo.update | B23: Điều phối | C23: Cập nhật HÀNG/RỖNG khi còn trong bãi | D23: Q08 | E23: V1 | F23: CORE | G23: Thông thường
A24: container.cargo.post_exit.request | B24: Điều phối | C24: Đề nghị sửa HÀNG/RỖNG sau ra | D24: Q09 | E24: V1 | F24: CORE | G24: Nhạy cảm
A25: container.cargo.post_exit.approve | B25: Điều phối | C25: Duyệt sửa HÀNG/RỖNG sau ra | D25: Q09 | E25: V1 | F25: CORE | G25: Cao
A26: container.handling.record | B26: Container | C26: Ghi nhận hạ/xếp, vị trí khu/dãy/ô | D26: Q07 | E26: GĐ sau | F26: YARD_SLOT_MANAGEMENT | G26: Thông thường | H26: Không dùng sự kiện hạ/xếp làm căn cứ thu phí lưu container.
A27: reefer.request.read | B27: Điện dự kiến | C27: Xem yêu cầu điện dự kiến / đang xử lý | D27: Q10,Q31,Q33 | E27: V1 | F27: CORE | G27: Thông thường
A28: reefer.request.create | B28: Điện dự kiến | C28: Tạo phiếu yêu cầu cắm/rút (kể cả cont chưa vào) | D28: Q10,Q31 | E28: V1 | F28: CORE | G28: Thông thường | H28: Một phiếu/cont, nhiều phiên; không tạo GIO_CONT_VAO khi phiếu là dự kiến.
A29: reefer.request.update | B29: Điện dự kiến | C29: Sửa thông tin yêu cầu dự kiến | D29: Q32,Q36 | E29: V1 | F29: CORE | G29: Thông thường | H29: Sửa số cont/khách/loại yêu cầu có lịch sử và báo An ninh.
A30: reefer.request.cancel | B30: Điện dự kiến | C30: Hủy phiếu điện chưa thực hiện | D30: Q32 | E30: V1 | F30: CORE | G30: Nhạy cảm | H30: Hủy mềm có lịch sử; không xóa phiếu đã phát sinh điện.
A31: reefer.request.alert.view | B31: Điện dự kiến | C31: Xem cảnh báo yêu cầu điện khi xe vào | D31: Q33 | E31: V1 | F31: CORE | G31: Thông thường
A32: reefer.request.match_confirm | B32: Điện dự kiến | C32: Xác nhận ghép phiếu dự kiến với cont thực | D32: Q34 | E32: V1 | F32: CORE | G32: Nhạy cảm
A33: reefer.field_work.note | B33: Cắm điện | C33: Ghi nhận thông tin An ninh báo cắm/rút ngoài hiện trường | D33: Q11 | E33: V1 | F33: CORE | G33: Thông thường | H33: Quyền ghi chú/bằng chứng; KHÔNG biến việc bấm nút thành điều kiện bắt buộc để cắm/rút thực tế.
A34: reefer.session.read | B34: Cắm điện | C34: Xem phiên điện/trạng thái | D34: Q12,Q13 | E34: V1 | F34: CORE | G34: Thông thường
A35: reefer.session.actual_start.record | B35: Cắm điện | C35: CCKB nhập giờ cắm thực tế | D35: Q12 | E35: V1 | F35: CORE | G35: Thông thường
A36: reefer.session.actual_end.record | B36: Cắm điện | C36: CCKB nhập giờ rút thực tế | D36: Q13 | E36: V1 | F36: CORE | G36: Thông thường
A37: reefer.session.time.edit_unpaid | B37: Cắm điện | C37: CCKB sửa giờ cắm/rút trước khi thu | D37: Q14 | E37: V1 | F37: CORE | G37: Nhạy cảm
A38: reefer.session.billable.override_unpaid | B38: Cắm điện | C38: Chỉnh thời lượng tính tiền trước khi thu | D38: Q14 | E38: V1 | F38: CORE | G38: Tài chính | H38: Tự làm tròn 15 phút mặc định; nếu chỉnh thì lưu số tính tự động, số điều chỉnh và lý do.
A39: reefer.session.amendment.request | B39: Cắm điện | C39: Đề nghị điều chỉnh giờ/tiền sau thu | D39: Q15 | E39: V1 | F39: CORE | G39: Tài chính
A40: reefer.session.amendment.approve | B40: Cắm điện | C40: Duyệt chênh lệch sau thu điện | D40: Q16 | E40: V1 | F40: CORE | G40: Cao | H40: Tài khoản duyệt phải khác người đề nghị; không ghi đè tiền đã thu.
A41: reefer.payment.collect | B41: Thanh toán | C41: Thu tiền điện từng phiên hoặc tổng hợp | D41: Q19 | E41: V1 | F41: CORE | G41: Tài chính
A42: reefer.payment.partial_collect | B42: Thanh toán | C42: Thu một phần phí điện | D42: Q19 | E42: V1 | F42: CORE | G42: Tài chính
A43: storage.payment.collect | B43: Thanh toán | C43: An ninh tính/thu phí lưu tại giờ cont ra | D43: Q18 | E43: V1 | F43: CORE | G43: Tài chính | H43: Chốt dựa GIO_CONT_VAO và GIO_CONT_RA thực tế, không khóa phí lúc rút điện.
A44: payment.bank_evidence.attach | B44: Thanh toán | C44: Đính kèm ảnh chứng từ thanh toán | D44: Q02,Q19,Q21 | E44: V1 | F44: CORE | G44: Thông thường | H44: Quy định bắt buộc chứng từ có thể cấu hình riêng theo hình thức thu.
A45: payment.bank.reconcile | B45: Thanh toán | C45: Đối soát chuyển khoản theo bộ phận | D45: Q21 | E45: V1 | F45: CORE | G45: Tài chính
A46: payment.post_correction.request | B46: Thanh toán | C46: Yêu cầu xử lý chênh lệch khi sửa mã cont đã thu | D46: Q38 | E46: V1 | F46: CORE | G46: Tài chính
A47: payment.post_correction.approve | B47: Thanh toán | C47: Duyệt chênh lệch tiền do sửa số cont | D47: Q38 | E47: V1 | F47: CORE | G47: Cao
A48: charge.adjust.request | B48: Thanh toán | C48: Gửi đề nghị miễn/giảm/điều chỉnh tiền | D48: Q22 | E48: GĐ sau | F48: CHARGE_DISCOUNT | G48: Tài chính
A49: charge.adjust.approve | B49: Thanh toán | C49: Duyệt miễn/giảm/điều chỉnh tiền | D49: Q22 | E49: GĐ sau | F49: CHARGE_DISCOUNT | G49: Cao
A50: payment.refund.request | B50: Thanh toán | C50: Đề nghị hoàn tiền | D50: Q23 | E50: GĐ sau | F50: REFUNDS | G50: Tài chính
A51: payment.refund.approve | B51: Thanh toán | C51: Duyệt hoàn tiền / hủy bút toán | D51: Q23 | E51: GĐ sau | F51: REFUNDS | G51: Cao
A52: exit.clearance.read | B52: Cổng ra | C52: Xem tình trạng tài chính và cho ra | D52: Q24,Q25 | E52: V1 | F52: CORE | G52: Thông thường
A53: exit.clearance.issue | B53: Cổng ra | C53: CCKB xác nhận điều kiện tài chính | D53: Q24 | E53: V1 | F53: CORE | G53: Cao | H53: Xác nhận điện/công nợ đã biết; KHÔNG khóa phí lưu container.
A54: exit.clearance.debt_exception | B54: Cổng ra | C54: CCKB xác nhận cho ra còn khoản chưa thu | D54: Q24 | E54: V1 | F54: CORE | G54: Cao | H54: Bắt buộc lý do, hiện cảnh báo và giữ khoản còn nợ; phải kiểm tra lại nếu phí lưu mới phát sinh.
A55: exit.clearance.revoke.request | B55: Cổng ra | C55: Đề nghị thu hồi chấp thuận xuất trước khi xe ra | D55: Q26 | E55: V1 | F55: CORE | G55: Nhạy cảm
A56: exit.clearance.revoke.approve | B56: Cổng ra | C56: Thu hồi chấp thuận cho ra trước khi thực xuất | D56: Q26 | E56: V1 | F56: CORE | G56: Cao
A57: exit.actual.confirm | B57: Cổng ra | C57: An ninh xác nhận cont/xe ra thật | D57: Q25 | E57: V1 | F57: CORE | G57: Cao | H57: Server transaction và idempotency; không được tự hoàn tất nếu offline.
A58: exit.reefer_state.exception | B58: Cổng ra | C58: CCKB ghi ngoại lệ trạng thái điện chưa cập nhật | D58: Q24 | E58: V1 | F58: CORE | G58: Cao | H58: Phải có An ninh xác minh ngoài hiện trường đã rút điện, không được cho cont rời bãi khi còn kết nối điện thực tế.
A59: report.revenue.read | B59: Báo cáo | C59: Xem doanh thu và khoản thu theo phạm vi | D59: Q29 | E59: V1 | F59: CORE | G59: Tài chính
A60: report.revenue.export | B60: Báo cáo | C60: Xuất báo cáo doanh thu theo bộ phận | D60: Q30 | E60: V1 | F60: CORE | G60: Tài chính
A61: audit.read | B61: Giám sát | C61: Xem lịch sử thao tác thuộc phạm vi | D61: Q28 | E61: V1 | F61: CORE | G61: Thông thường
A62: audit.export_all | B62: Giám sát | C62: Xuất nhật ký kiểm toán toàn hệ thống | D62: Q30 | E62: V1 | F62: CORE | G62: Cao
A63: tariff.read | B63: Bảng giá | C63: Xem giá dịch vụ theo hiệu lực | D63: Q17 | E63: V1 | F63: CORE | G63: Thông thường
A64: tariff.change.request | B64: Bảng giá | C64: Gửi đề nghị thay đổi bảng giá | D64: Q17 | E64: V1 | F64: CORE | G64: Tài chính
A65: tariff.change.publish | B65: Bảng giá | C65: Ban hành mức giá và ngày hiệu lực | D65: Q17 | E65: V1 | F65: CORE | G65: Cao | H65: Thay đổi giá qua bảng tariff_versions, không sửa code/giá lịch sử.
A66: admin.users.manage | B66: Quản trị | C66: Tạo/khóa user và gán role theo phạm vi | D66: Q27 | E66: V1 | F66: CORE | G66: Cao
A67: admin.roles.manage | B67: Quản trị | C67: Thêm/sửa tên vai trò và thành phần vai trò | D67: Q27 | E67: V1 | F67: CORE | G67: Cao | H67: Vai trò tùy biến nhưng không thể tạo tính năng mới chỉ bằng cách đặt role.
A68: admin.role_permissions.manage | B68: Quản trị | C68: Cấp/thu hồi quyền của vai trò | D68: Q27 | E68: V1 | F68: CORE | G68: Cao | H68: Cấm tự động cho quyền cao hơn do seed chủ sở hữu quy định; audit và quyền bootstrap.
A69: admin.billing_settings.manage | B69: Quản trị | C69: Quản lý tham số tính phí và chức năng mở rộng | D69: Q17 | E69: V1 | F69: CORE | G69: Cao
A70: admin.legacy_correct | B70: Quản trị | C70: Sửa dữ liệu nhập lịch sử AppSheet có audit | D70: Q03,Q06 | E70: V1 | F70: CORE | G70: Cao | H70: Không chỉnh sửa trực tiếp DB; phải ghi đối chiếu lịch sử và không tạo nợ legacy chưa xác minh.
A71: accounting.invoice.prepare | B71: Hóa đơn | C71: Nhập dữ liệu hóa đơn từ bộ phận Kế toán | E71: GĐ sau | F71: E_INVOICE | G71: Nhạy cảm

Sheet 21_V5_CAP_QUYEN_SEED
A1: V5 — GÁN QUYỀN THEO VAI TRÒ (SEED)
A2: Dữ liệu mẫu triển khai role_permissions. Scope: SELF = khoản mình làm, DEPARTMENT = bộ phận, YARD = bãi, ALL = toàn hệ thống.
A4: ROLE_CODE | B4: Tên vai trò | C4: PERMISSION_CODE | D4: SCOPE | E4: Đang cấp | F4: Độ nhạy | G4: Mã tham chiếu | H4: Điều kiện hệ thống
A5: SEC_STAFF | B5: Nhân viên An ninh | C5: vehicle.visit.read | D5: YARD | E5: Có | F5: Thông thường | G5: Q01,Q03,Q25 | H5: Kiểm tra server theo dữ liệu thuộc phạm vi.
A6: SEC_LEAD | B6: Trưởng bộ phận An ninh | C6: vehicle.visit.read | D6: YARD | E6: Có | F6: Thông thường | G6: Q01,Q03,Q25 | H6: Kiểm tra server theo dữ liệu thuộc phạm vi.
A7: PORT_STAFF | B7: Nhân viên Cổng cảng kho bãi | C7: vehicle.visit.read | D7: YARD | E7: Có | F7: Thông thường | G7: Q01,Q03,Q25 | H7: Kiểm tra server theo dữ liệu thuộc phạm vi.
A8: PORT_LEAD | B8: Trưởng bộ phận Cổng cảng kho bãi | C8: vehicle.visit.read | D8: YARD | E8: Có | F8: Thông thường | G8: Q01,Q03,Q25 | H8: Kiểm tra server theo dữ liệu thuộc phạm vi.
A9: DIS_STAFF | B9: Nhân viên Điều phối | C9: vehicle.visit.read | D9: YARD | E9: Có | F9: Thông thường | G9: Q01,Q03,Q25 | H9: Kiểm tra server theo dữ liệu thuộc phạm vi.
A10: DIS_LEAD | B10: Trưởng bộ phận Điều phối | C10: vehicle.visit.read | D10: YARD | E10: Có | F10: Thông thường | G10: Q01,Q03,Q25 | H10: Kiểm tra server theo dữ liệu thuộc phạm vi.
A11: SYS_ADMIN | B11: Quản trị hệ thống | C11: vehicle.visit.read | D11: ALL | E11: Có | F11: Thông thường | G11: Q01,Q03,Q25 | H11: Kiểm tra server theo dữ liệu thuộc phạm vi.
A12: SEC_STAFF | B12: Nhân viên An ninh | C12: vehicle.visit.create | D12: YARD | E12: Có | F12: Thông thường | G12: Q01 | H12: Kiểm tra server theo dữ liệu thuộc phạm vi.
A13: SEC_LEAD | B13: Trưởng bộ phận An ninh | C13: vehicle.visit.create | D13: YARD | E13: Có | F13: Thông thường | G13: Q01 | H13: Kiểm tra server theo dữ liệu thuộc phạm vi.
A14: SYS_ADMIN | B14: Quản trị hệ thống | C14: vehicle.visit.create | D14: ALL | E14: Có | F14: Thông thường | G14: Q01 | H14: Kiểm tra server theo dữ liệu thuộc phạm vi.
A15: SEC_STAFF | B15: Nhân viên An ninh | C15: vehicle.visit.update_basic | D15: YARD | E15: Có | F15: Nhạy cảm | G15: Q03 | H15: Kiểm tra server theo dữ liệu thuộc phạm vi.
... A210: SYS_ADMIN | B210: Quản trị hệ thống | C210: admin.legacy_correct | D210: ALL | E210: Có | F210: Cao | G210: Q03,Q06 | H210: Chỉ bật nếu phân hệ đang hoạt động; ràng buộc server/RLS + audit.

Sheet 22_V5_MA_TRAN_RBAC
A1: V5 — MA TRẬN QUYỀN ĐÃ CHUẨN HÓA
A2: Thể hiện quyền theo mã thao tác và phạm vi; không còn nhầm quyền “Thực hiện tại hiện trường” với nhập dữ liệu trên PWA.
A4: PERMISSION_CODE | B4: Chức năng | C4: Giai đoạn | D4: SEC_STAFF | E4: SEC_LEAD | F4: PORT_STAFF | G4: PORT_LEAD | H4: DIS_STAFF | I4: DIS_LEAD | J4: SYS_ADMIN | K4: ACCOUNTING_FUTURE
A5: vehicle.visit.read | B5: Xem lượt xe trong bãi | C5: V1 | D5: YARD | E5: YARD | F5: YARD | G5: YARD | H5: YARD | I5: YARD | J5: ALL | K5: —
A6: vehicle.visit.create | B6: Tạo lượt xe/giờ vào | C6: V1 | D6: YARD | E6: YARD | F6: — | G6: — | H6: — | I6: — | J6: ALL | K6: —
A7: vehicle.visit.update_basic | B7: Sửa thông tin cơ bản của lượt xe | C7: V1 | D7: YARD | E7: YARD | F7: — | G7: — | H7: — | I7: — | J7: ALL | K7: —
A8: vehicle.visit.time_correction.request | B8: Yêu cầu sửa giờ vào sau khi phát sinh tiền | C8: V1 | D8: YARD | E8: YARD | F8: — | G8: — | H8: — | I8: — | J8: ALL | K8: —
A9: vehicle.visit.time_correction.approve | B9: Duyệt sửa giờ vào sau khi phát sinh tiền | C9: V1 | D9: — | E9: DEPARTMENT | F9: — | G9: — | H9: — | I9: — | J9: ALL | K9: —
A10: ticket.payment.collect | B10: Ghi nhận thu tiền vé xe vào | C10: V1 | D10: YARD | E10: YARD | F10: — | G10: — | H10: — | I10: — | J10: ALL | K10: —
A11: ticket.lost_fee.collect | B11: Ghi nhận và thu phạt mất vé | C11: V1 | D11: YARD | E11: YARD | F11: — | G11: — | H11: — | I11: — | J11: ALL | K11: —
A12: ticket.paper_number.adjust | B12: Chỉnh số seri vé giấy / in vé | C12: GĐ sau | D12: — | E12: — | F12: — | G12: — | H12: — | I12: — | J12: — | K12: —
A13: vehicle.visit.exit_confirm | B13: Xác nhận lượt xe thực tế ra | C13: V1 | D13: YARD | E13: YARD | F13: — | G13: — | H13: — | I13: — | J13: ALL | K13: —
A14: container.visit.read | B14: Xem lượt container trong bãi | C14: V1 | D14: YARD | E14: YARD | F14: YARD | G14: YARD | H14: YARD | I14: YARD | J14: ALL | K14: —
A15: container.visit.create | B15: Tạo lượt container vào và giờ vào | C15: V1 | D15: YARD | E15: YARD | F15: — | G15: — | H15: — | I15: — | J15: ALL | K15: —
... A71: accounting.invoice.prepare | B71: Nhập dữ liệu hóa đơn từ bộ phận Kế toán | C71: GĐ sau | D71: — | E71: — | F71: — | G71: — | H71: — | I71: — | J71: — | K71: —

Sheet 23_V5_PHÊ_DUYỆT
A1: V5 — CHÍNH SÁCH XỬ LÝ & PHÊ DUYỆT
A2: Không đồng nhất quyền sửa mã container với quyền sửa TIỀN đã thu. Trạng thái phê duyệt, lý do và người thực hiện đều được lưu.
A4: Mã | B4: Tình huống | C4: Quyền khởi tạo | D4: Quyền phê duyệt | E4: Trách nhiệm | F4: Tách người | G4: Lý do | H4: Giai đoạn | I4: Quy tắc
A5: AP01 | B5: Sửa giờ điện/chênh tiền SAU khi thu | C5: reefer.session.amendment.request | D5: reefer.session.amendment.approve | E5: PORT_LEAD / SYS_ADMIN | F5: Không tự duyệt | G5: Bắt buộc | H5: V1 | I5: Giữ giao dịch đã thu; tạo điều chỉnh công nợ/hoàn trả, không ghi đè.
A6: AP02 | B6: Sửa giờ điện TRƯỚC khi thu | C6: reefer.session.time.edit_unpaid | E6: PORT_STAFF / PORT_LEAD | F6: Không cần duyệt | G6: Bắt buộc | H6: V1 | I6: Ghi trước/sau, lý do, giờ thực tế khác giờ nhập.
A7: AP03 | B7: Điều chỉnh thời lượng điện trước thu | C7: reefer.session.billable.override_unpaid | E7: PORT_STAFF / PORT_LEAD | F7: Không cần duyệt | G7: Bắt buộc | H7: V1 | I7: Lưu số tự tính làm tròn 15p và số sửa tay, hiện chênh lệch.
A8: AP04 | B8: Sửa số cont SAU đã thu | C8: container.number.correct | D8: payment.post_correction.approve | E8: SEC_STAFF; CCKB đối soát | F8: Không bắt buộc duyệt sửa SỐ | G8: Bắt buộc | H8: V1 | I8: Sửa mã ngay có audit/CCKB nhận cảnh báo. Chỉ sửa TIỀN chênh sau thu mới phải duyệt.
A9: AP05 | B9: Chỉnh HÀNG/RỖNG SAU cont ra | C9: container.cargo.post_exit.request | D9: container.cargo.post_exit.approve | E9: DIS_LEAD / SYS_ADMIN | F9: Không tự duyệt | G9: Bắt buộc | H9: V1 | I9: Không cấp sửa sau ra trực tiếp cho NV/An ninh.
A10: AP06 | B10: CCKB cho xuất còn công nợ | C10: exit.clearance.debt_exception | E10: PORT_STAFF / PORT_LEAD | F10: Theo quyền CCKB, có cảnh báo | G10: Bắt buộc | H10: V1 | I10: Không xóa công nợ; thời điểm An ninh xác nhận cont ra vẫn tính tiền lưu mới.
A11: AP07 | B11: Có tiền lưu phát sinh ngay cửa ra | C11: storage.payment.collect | D11: exit.clearance.debt_exception | E11: SEC_STAFF thu; CCKB xác nhận nợ | F11: Nếu không thu cần CCKB xác nhận nợ | G11: Bắt buộc | H11: V1 | I11: Cảnh báo/đồng bộ lại số phí lưu tại giờ thực ra, không khóa tiền trước khi ra.
A12: AP08 | B12: Trạng thái PWA Đang cắm nhưng ngoài hiện trường đã rút | C12: exit.reefer_state.exception | E12: CCKB + An ninh xác minh | F12: Có xác nhận tình trạng thực tế | G12: Bắt buộc | H12: V1 | I12: Không cho phép xuất khi cont thực tế vẫn đang nối điện; lưu giải trình khi dữ liệu app chưa cập nhật.
A13: AP09 | B13: Thu hồi CCKB đã xác nhận cho ra | C13: exit.clearance.revoke.request | D13: exit.clearance.revoke.approve | E13: PORT_LEAD / SYS_ADMIN | F13: Không tự duyệt | G13: Bắt buộc | H13: V1 | I13: Chỉ thu hồi trước khi xác nhận ra thực tế; sau ra dùng sửa lịch sử.
A14: AP10 | B14: Bảng giá thay đổi | C14: tariff.change.request | D14: tariff.change.publish | E14: SYS_ADMIN | F14: Đề nghị/ban hành tách biệt | G14: Bắt buộc | H14: V1 | I14: Lưu phiên bản giá/hiệu lực; không thay tiền của lịch sử.
A15: AP11 | B15: Hoàn tiền / miễn giảm | C15: payment.refund.request | D15: payment.refund.approve | E15: Chưa triển khai | F15: Không kích hoạt | G15: Bắt buộc nếu triển khai | H15: GĐ sau | I15: Các quyền seed chưa cấp cho ai, cờ tính năng tắt.
A16: AP12 | B16: Đăng nhập bốt An ninh dùng chung thiết bị | C16: admin.users.manage | E16: SEC_STAFF / SEC_LEAD | F16: Bắt buộc xác định người thao tác | G16: Có | H16: V1 | I16: Ưu tiên đăng nhập cá nhân; nếu chế độ bốt thì phải xác minh người trực/phiên, không gắn mọi khoản thu vào email dùng chung.

Sheet 24_V5_THAM_SO
A1: V5 — THAM SỐ CÓ THỂ CẤU HÌNH
A2: Không chỉnh công thức/role cứng khi đổi giá hoặc chính sách. Tham số kỹ thuật không vượt qua các ràng buộc an toàn.
A4: STT | B4: Mã tham số | C4: Giá trị khởi tạo | D4: Loại | E4: Trạng thái | F4: Ghi chú
A5: RF01 | B5: ELECTRIC_ROUNDING_MINUTES | C5: 15 | D5: Cấu hình | E5: Đã chốt | F5: Làm tròn lên bội 15 phút theo từng phiên điện; mặc định do server tính.
A6: RF02 | B6: ELECTRIC_RATE_HOURLY_VND | C6: 100000 | D6: Bảng giá | E6: Đã chốt | F6: Mã DIEN_CONT_GIO; quản lý phiên bản giá trong DB.
A7: RF03 | B7: ELECTRIC_RATE_CONTINUOUS_VND | C7: 100000 | D7: Bảng giá | E7: Đã chốt | F7: Mã DIEN_CONT_LIEN_TUC; cấu hình độc lập dù giá hiện giống nhau.
A8: RF04 | B8: STORAGE_RATE_NIGHT_VND | C8: 100000 | D8: Bảng giá | E8: Đã chốt | F8: Phí lưu chỉ tính khi cont thực tế ra.
A9: RF05 | B9: STORAGE_FREE_NIGHTS | C9: 1 | D9: Cấu hình | E9: Đã chốt | F9: 01 đêm miễn phí theo chính sách hiện tại.
A10: RF06 | B10: STORAGE_NIGHT_START | C10: 22:00 | D10: Cấu hình | E10: Đã chốt | F10: Mốc đêm 22h; giờ địa phương Asia/Ho_Chi_Minh.
A11: RF07 | B11: STORAGE_NIGHT_END | C11: 06:00 | D11: Cấu hình | E11: Đã chốt | F11: Mốc kết thúc đêm 06h hôm sau.
A12: RF08 | B12: ALLOW_EXIT_WITH_DEBT | C12: true | D12: Cờ nghiệp vụ | E12: Đã chốt | F12: CCKB xác nhận có lý do, giữ nợ; không tự miễn khoản thu.
A13: RF09 | B13: PLANNED_REEFER_REQUEST_ENABLED | C13: true | D13: Cờ tính năng | E13: Đã chốt | F13: Cho CCKB tạo phiếu cont chưa vào; cảnh báo An ninh khi container tới.
A14: RF10 | B14: CONTAINER_NUMBER_CORRECTION_ENABLED | C14: true | D14: Cờ tính năng | E14: Đã chốt | F14: An ninh sửa mã có lịch sử và thông báo CCKB.
A15: RF11 | B15: ALLOW_REEFER_RETRO_ENTRY | C15: true | D15: Cờ tính năng | E15: Đã chốt | F15: Cho phép nhập giờ cắm/rút thực tế sau khi An ninh báo qua Zalo.
... A24: RF20 | B24: OFFLINE_GATE_EXIT_ALLOWED | C24: false | D24: An toàn | E24: Đã chốt | F24: Không tự xác nhận thành công ra cổng khi mất Internet.

Sheet 25_V5_MAPPING_Q01_Q39
A1: V5 — ĐỐI CHIẾU 39 YÊU CẦU PHÂN QUYỀN
A2: Q01–Q39 của file gốc không mất, nhưng được tách thành permission_code nhỏ để cấp quyền linh hoạt và tránh cấp nhầm.
A4: Mã gốc | B4: Chức năng gốc | C4: Các permission_code liên quan | D4: Hướng xử lý V5 | E4: Ghi chú bản rà soát V4.1
A5: Q01 | B5: Tạo lượt xe vào và giờ vào | C5: vehicle.visit.read, vehicle.visit.create | D5: Đã tách thành quyền thao tác cụ thể | E5: Giữ như bản bạn điền; vẫn phải triển khai RBAC phía server, không chỉ ẩn nút trên giao diện.
A6: Q02 | B6: Thu tiền vé vào, đính kèm ảnh chuyển khoản | C6: ticket.payment.collect, payment.bank_evidence.attach | D6: Đã tách thành quyền thao tác cụ thể | E6: Giữ như bản bạn điền; vẫn phải triển khai RBAC phía server, không chỉ ẩn nút trên giao diện.
A7: Q03 | B7: Sửa biển số / loại xe / GIO_VAO | C7: vehicle.visit.read, vehicle.visit.update_basic, vehicle.visit.time_correction.request, vehicle.visit.time_correction.approve, admin.legacy_correct | D7: Đã tách thành quyền thao tác cụ thể | E7: Tách sửa biển số, loại xe và GIO_VAO thành các quyền riêng. Trước khi xuất cho An ninh sửa có audit; sau khi đã thu/đã xuất phải kiểm tra ảnh hưởng phí và cho TBP xử lý. Không tự sửa chứng từ đã thu.
A8: Q04 | B8: Tạo/điều chỉnh số vé giấy | C8: ticket.paper_number.adjust | D8: Giai đoạn sau (không cấp quyền V1) | E8: Bạn ghi hiện chưa dùng chỉnh số vé giấy; do đó tắt thao tác thay đổi số vé giấy ở V1. Nếu cần vẫn có thể nhập số vé tham chiếu tùy chọn, không cấp quyền sửa tùy ý.
A9: Q05 | B9: Tạo lượt container vào, ghi GIO_CONT_VAO | C9: container.visit.read, container.visit.create | D9: Đã tách thành quyền thao tác cụ thể | E9: Giữ như bản bạn điền; vẫn phải triển khai RBAC phía server, không chỉ ẩn nút trên giao diện.
A10: Q06 | B10: Thay đổi số container sau khi lưu | C10: container.visit.read, container.number.correct, admin.legacy_correct | D10: Đã tách thành quyền thao tác cụ thể | E10: Giữ quyền sửa số cont cho An ninh như bạn chọn; bắt buộc ghi số trước/sau, lý do, người sửa, giờ sửa và tự gửi cảnh báo tới CCKB. Nếu đã thu thì giữ giao dịch cũ; thay đổi số cont không tự động thay tiền.
A11: Q07 | B11: Xác nhận hạ/xếp container (quản lý vị trí) | C11: container.handling.record | D11: Giai đoạn sau (không cấp quyền V1) | E11: Nghiệp vụ hạ/xếp/vị trí là thông tin vận hành, không phải điều kiện tính phí lưu. Nếu chưa áp dụng kiểm soát vị trí trong V1, ẩn phần vị trí; vẫn lưu trạng thái xe ra không container.
A12: Q08 | B12: Cập nhật HÀNG/RỖNG | C12: container.cargo.read, container.cargo.update | D12: Đã tách thành quyền thao tác cụ thể | E12: Chỉ Điều phối nhập HÀNG/RỖNG; An ninh xem để đối chiếu. Tránh 2 bộ phận cập nhật chéo làm mất nguồn dữ liệu chuẩn.
A13: Q09 | B13: Sửa HÀNG/RỖNG sau khi đã ra | C13: container.cargo.read, container.cargo.post_exit.request, container.cargo.post_exit.approve | D13: Đã tách thành quyền thao tác cụ thể | E13: Sau khi container đã xuất: NV Điều phối chỉ đề nghị sửa; TBP Điều phối/Quản trị duyệt, ghi nhật ký trước/sau. Nếu chỉ sửa chú thích không ảnh hưởng phí thì có thể đơn giản hóa.
A14: Q10 | B14: Tạo yêu cầu cắm/rút từ khách hàng | C14: reefer.request.read, reefer.request.create | D14: Đã tách thành quyền thao tác cụ thể | E14: Giữ như bản bạn điền; vẫn phải triển khai RBAC phía server, không chỉ ẩn nút trên giao diện.
A15: Q11 | B15: Thực hiện cắm/rút điện tại hiện trường | C15: reefer.field_work.note | D15: Ngoài hệ thống / ghi nhận thông tin | E15: Thao tác cắm/rút PHYSICAL chỉ An ninh thực hiện. CCKB tiếp nhận thông báo qua Zalo, sau đó nhập giờ tại Q12/Q13. Không bắt buộc An ninh nhập giờ trên PWA.
... A43: Q39 | B43: Xem và xác nhận đã xử lý cảnh báo sai số cont/không ghép được yêu cầu dự kiến | C43: container.number.discrepancy.view, container.number.discrepancy.sec_ack, container.number.discrepancy.port_reconcile | D43: Đã tách thành quyền thao tác cụ thể | E43: An ninh ghi đã báo/chụp hiện trường; CCKB đánh dấu đã kiểm tra/đối soát và đóng cảnh báo; trạng thái riêng từng BP, ai hoàn tất thao tác của mình.

Sheet 26_V5_LUONG_THAO_TAC
A1: V5 — LUỒNG THAO TÁC THỰC TẾ
A2: Người thực hiện thực tế, người nhập hệ thống và người thu là ba khái niệm riêng. Mỗi bước đối chiếu quyền theo action và scope.
A4: Mã | B4: Bước | C4: Vai trò | D4: Quyền kiểm tra | E4: Dữ liệu/hiệu lực | F4: Lưu ý thực tế
A5: WF01 | B5: Xe vào | C5: SEC_STAFF | D5: vehicle.visit.create | E5: Tạo lượt xe; thu vé theo loại xe | F5: Nếu cont có điện dự kiến hiển thị cảnh báo; không tự ghép mã gần giống.
A6: WF02 | B6: Cont vào | C6: SEC_STAFF | D6: container.visit.create | E6: Tạo lượt cont, giữ GIO_CONT_VAO | F6: Hạ hay không hạ không ảnh hưởng tính số đêm lưu.
A7: WF03 | B7: Điện dự kiến | C7: PORT_STAFF | D7: reefer.request.create | E7: Tạo 1 phiếu/container trước khi cont vào | F7: Không tự ghi giờ cont vào, không sinh phí lưu/điện.
A8: WF04 | B8: Ghép dự kiến | C8: SEC_STAFF / PORT_STAFF | D8: reefer.request.match_confirm | E8: Xác nhận mã cont thực tế | F8: Gợi ý theo số đầy đủ, 7 số cuối, gần giống phải xác nhận.
A9: WF05 | B9: An ninh cắm/rút | C9: SEC_STAFF | D9: reefer.field_work.note | E9: Thực hiện hiện trường; báo nhóm Zalo | F9: Không ép bấm bắt đầu cắm/rút trong PWA để lấy giờ thực.
A10: WF06 | B10: CCKB nhập điện | C10: PORT_STAFF | D10: reefer.session.actual_start.record / actual_end.record | E10: Nhập/bổ sung giờ cắm/rút thực tế | F10: Server làm tròn 15p theo phiên; hiển thị giá, tiền; sửa có audit.
A11: WF07 | B11: CCKB thu điện | C11: PORT_STAFF | D11: reefer.payment.collect | E11: Thu ngay khi rút hoặc khi cont xuất | F11: Nhiều lần thu / nhiều khoản; không thu trùng, không sửa dòng đã thu.
A12: WF08 | B12: CCKB kiểm tra ra | C12: PORT_STAFF | D12: exit.clearance.issue | E12: Kiểm tra điện và nợ biết trước khi ra | F12: Cho phép clearance ngoại lệ có lý do, không khóa phí lưu.
A13: WF09 | B13: An ninh chốt ra | C13: SEC_STAFF | D13: exit.actual.confirm / storage.payment.collect | E13: Ghi GIO_CONT_RA, tính tiền lưu và thu | F13: Server tính lại theo thời điểm ra; thiếu tiền thì đối soát/CCKB cho nợ có lý do.
A14: WF10 | B14: Sửa mã cont | C14: SEC_STAFF | D14: container.number.correct | E14: Sửa ID hiển thị, báo CCKB | F14: Giữ container_visit_id; cảnh báo mã trùng; không làm mất tiền điện/lưu.
A15: WF11 | B15: CCKB đóng cảnh báo | C15: PORT_STAFF | D15: container.number.discrepancy.port_reconcile | E15: Đối chiếu dữ liệu và trạng thái tiền | F15: Không xóa lịch sử số cont cũ/phiếu dự kiến.
A16: WF12 | B16: Điều phối HÀNG/RỖNG | C16: DIS_STAFF | D16: container.cargo.update | E16: Cập nhật, có thể tạm trống | F16: Sau cont ra: đề nghị/duyệt bởi DIS_LEAD.

Sheet 27_V5_RUI_RO_UAT
A1: V5 — KIỂM SOÁT RỦI RO KHI TRIỂN KHAI
